Workbook

Sheet Dashboard
A1: 🎬 CONOR'S BLU-RAY COLLECTION
A2: Physical media tracker • collection progress • wishlist • franchise completion
A4: COLLECTION | B4: VALUE | D4: FOUNDATION | E4: VALUE | G4: WISHLIST | H4: VALUE
A5: Individual films | B5: =COUNTIF(Collection!B5:B500,"<>") | D5: Film IDs | E5: =COUNTA(Collection!A5:A500) | G5: Total wishlist | H5: =COUNTA(Wishlist!A5:A100)
A6: Blu-ray entries | B6: =COUNTIF(Collection!D5:D500,"Blu-ray") | D6: Years filled | E6: =COUNTA(Collection!C5:C500) | G6: Your requested films | H6: =COUNTIF(Wishlist!B5:B100,"Your list")
A7: 4K UHD entries | B7: =COUNTIF(Collection!D5:D500,"4K UHD") | D7: Directors filled | E7: =COUNTIF(Collection!J5:J500,"<>") | G7: Recommendations | H7: =COUNTIF(Wishlist!B5:B100,"Recommended")
A8: Watched | B8: =COUNTIF(Collection!G5:G500,"Yes") | D8: Box-set films | E8: =COUNTIF(Collection!F5:F500,"Back to the Future Trilogy (Box Set)")+COUNTIF(Collection!F5:F500,"Bad Boys I & II (Box Set)")+COUNTIF(Collection!F5:F500,"Cornetto Trilogy (Box Set)")+COUNTIF(Collection!F5:F500,"Jurassic Park / World: 7-Film Collection")+COUNTIF(Collection!F5:F500,"The Lord of the Rings Trilogy (Box Set)")+COUNTIF(Collection!F5:F500,"Star Wars Episodes I–VI (Box Set)")+COUNTIF(Collection!F5:F500,"X-Men Trilogy (Box Set)") | G8: Already owned | H8: =COUNTIF(Wishlist!H5:H100,"Yes")
A9: Rated | B9: =COUNT(Collection!H5:H500) | D9: Collections tracked | E9: =COUNTA('Franchise Tracker'!A5:A47) | G9: Still to buy | H9: =COUNTIF(Wishlist!H5:H100,"No")
A12: COLLECTION | B12: OWNED | C12: TARGET | D12: MISSING | E12: COMPLETE | G12: AWARDS | H12: VALUE
A13: ='Franchise Tracker'!A5 | B13: ='Franchise Tracker'!B5 | C13: ='Franchise Tracker'!C5 | D13: ='Franchise Tracker'!D5 | E13: ='Franchise Tracker'!E5 | G13: Oscar-nominated films | H13: =COUNTIF(Collection!U5:U500,">0")
A14: ='Franchise Tracker'!A6 | C14: ='Franchise Tracker'!C6 | D14: ='Franchise Tracker'!D6 | E14: ='Franchise Tracker'!E6 | G14: Oscar-winning films | H14: =COUNTIF(Collection!V5:V500,">0")
A15: ='Franchise Tracker'!A7 | B15: ='Franchise Tracker'!B7 | C15: ='Franchise Tracker'!C7 | D15: ='Franchise Tracker'!D7 | E15: ='Franchise Tracker'!E7 | G15: Total nominations | H15: =SUM(Collection!U5:U500)
A16: ='Franchise Tracker'!A8 | B16: ='Franchise Tracker'!B8 | C16: ='Franchise Tracker'!C8 | D16: ='Franchise Tracker'!D8 | E16: ='Franchise Tracker'!E8 | G16: Total wins | H16: =SUM(Collection!V5:V500)
A17: ='Franchise Tracker'!A9 | B17: ='Franchise Tracker'!B9 | C17: ='Franchise Tracker'!C9 | D17: ='Franchise Tracker'!D9 | E17: ='Franchise Tracker'!E9 | G17: Best Picture winners | H17: =COUNTIF(Collection!W5:W500,"Winner")
A18: ='Franchise Tracker'!A10 | B18: ='Franchise Tracker'!B10 | C18: ='Franchise Tracker'!C10 | D18: ='Franchise Tracker'!D10 | E18: ='Franchise Tracker'!E10 | G18: Best Picture nominees | H18: =COUNTIF(Collection!W5:W500,"Winner")+COUNTIF(Collection!W5:W500,"Nominated")
A19: ='Franchise Tracker'!A11 | B19: ='Franchise Tracker'!B11 | C19: ='Franchise Tracker'!C11 | D19: ='Franchise Tracker'!D11 | E19: ='Franchise Tracker'!E11 | G19: Best Picture progress | H19: =H17/98
A20: ='Franchise Tracker'!A12 | B20: ='Franchise Tracker'!B12 | C20: ='Franchise Tracker'!C12 | D20: ='Franchise Tracker'!D12 | E20: ='Franchise Tracker'!E12 | G20: Animated Feature winners | H20: =COUNTIF(Awards!O5:O500,"Winner")
A21: ='Franchise Tracker'!A13 | B21: ='Franchise Tracker'!B13 | C21: ='Franchise Tracker'!C13 | D21: ='Franchise Tracker'!D13 | E21: ='Franchise Tracker'!E13 | G21: Acting-winning films | H21: =COUNTIF(Awards!H5:H500,">0")
A22: ='Franchise Tracker'!A14 | B22: ='Franchise Tracker'!B14 | C22: ='Franchise Tracker'!C14 | D22: ='Franchise Tracker'!D14 | E22: ='Franchise Tracker'!E14 | G22: Directing-winning films | H22: =COUNTIF(Awards!K5:K500,">0")
A25: ⭐ RATINGS OVERVIEW
A27: RATINGS | B27: VALUE | D27: SOURCE COVERAGE | E27: FILMS
A28: Your films rated | B28: =COUNT(Ratings!D5:D500) | D28: IMDb | E28: =COUNT(Ratings!E5:E500)
A29: External ratings entered | B29: =COUNT(Ratings!L5:L500) | D29: Rotten Tomatoes critics | E29: =COUNT(Ratings!G5:G500)
A30: Average consensus | B30: =IFERROR(AVERAGE(Ratings!L5:L500),0) | D30: Rotten Tomatoes audience | E30: =COUNT(Ratings!H5:H500)
A31: Excellent (85+) | B31: =COUNTIF(Ratings!M5:M500,"Excellent") | D31: Letterboxd | E31: =COUNT(Ratings!I5:I500)
A32: Good (70–84.9) | B32: =COUNTIF(Ratings!M5:M500,"Good") | D32: Metacritic | E32: =COUNT(Ratings!J5:J500)
A33: Mixed (55–69.9) | B33: =COUNTIF(Ratings!M5:M500,"Mixed") | D33: TMDb | E33: =COUNT(Ratings!K5:K500)
A34: Poor (<55) | B34: =COUNTIF(Ratings!M5:M500,"Poor") | D34: Consensus | E34: =COUNT(Ratings!L5:L500)

Sheet Collection
A1: 🎬 MY BLU-RAY COLLECTION — v5.0
A2: Ratings edition: dedicated ratings database added with your score, external-rating fields, consensus scoring and one-click source lookups.
A4: Film ID | B4: Title | C4: Year | D4: Format | E4: Collection | F4: Physical Release / Box Set | G4: Watched | H4: Rating (1-5) | I4: Notes | J4: Director | K4: Runtime (min) | L4: Genre | M4: Studio / Production | N4: Metadata Source | O4: Cast Source | P4: Actor 1 | Q4: Actor 2 | R4: Actor 3 | S4: Actor 4 | T4: Actor 5 | U4: Oscar Noms | V4: Oscar Wins | W4: Best Picture | X4: IMDb | Y4: RT Critics | Z4: Letterboxd | AA4: Date Watched | AB4: BBFC Rating | AC4: Date Added
A5: F0001 | B5: Casino Royale | C5: 2006 | D5: Blu-ray | E5: James Bond | I5: Le Chiffre, a banker to the world's terrorists, is scheduled to participate in a high-stakes poker game in Montenegro, where he intends to use his winnings to establish his financial grip on the terrorist market. M sends Bond—on his maiden mission as a 00 Agent—to attend this game and prevent Le Chiffre from winning. With the help of Vesper Lynd and Felix Leiter, Bond enters the most important poker game in his already dangerous career. | J5: Martin Campbell | K5: 144 | L5: Adventure, Action, Thriller | M5: Eon Productions, Stillking Films, Columbia Pictures | N5: https://huggingface.co/datasets/HenryWaltson/TMDB-IMDB-Movies-Dataset | O5: https://huggingface.co/datasets/HenryWaltson/TMDB-IMDB-Movies-Dataset | P5: Daniel Craig | Q5: Eva Green | R5: Mads Mikkelsen | S5: Judi Dench | T5: Jeffrey Wright | U5: 0 | V5: 0 | X5: {=IFERROR(INDEX(Ratings!$E$5:$E$500,MATCH(A5,Ratings!$A$5:$A$500,0)),"")} | Y5: {=IFERROR(INDEX(Ratings!$G$5:$G$500,MATCH(A5,Ratings!$A$5:$A$500,0)),"")} | Z5: {=IFERROR(INDEX(Ratings!$I$5:$I$500,MATCH(A5,Ratings!$A$5:$A$500,0)),"")} | AB5: 12A
A6: F0002 | B6: Quantum of Solace | C6: 2008 | D6: Blu-ray | E6: James Bond | I6: Betrayed by Vesper, the woman he loved, 007 fights the urge to make his latest mission personal. Pursuing his determination to uncover the truth, Bond and M interrogate Mr. White, who reveals that the organization that blackmailed Vesper is far more complex and dangerous than anyone had imagined. | J6: Marc Forster | K6: 106 | L6: Adventure, Action, Thriller, Crime | M6: Eon Productions, Metro-Goldwyn-Mayer, Columbia Pictures | N6: https://huggingface.co/datasets/HenryWaltson/TMDB-IMDB-Movies-Dataset | O6: https://huggingface.co/datasets/HenryWaltson/TMDB-IMDB-Movies-Dataset | P6: Daniel Craig | Q6: Olga Kurylenko | R6: Mathieu Amalric | S6: Judi Dench | T6: Giancarlo Giannini | U6: 0 | V6: 0 | X6: {=IFERROR(INDEX(Ratings!$E$5:$E$500,MATCH(A6,Ratings!$A$5:$A$500,0)),"")} | Y6: {=IFERROR(INDEX(Ratings!$G$5:$G$500,MATCH(A6,Ratings!$A$5:$A$500,0)),"")} | Z6: {=IFERROR(INDEX(Ratings!$I$5:$I$500,MATCH(A6,Ratings!$A$5:$A$500,0)),"")} | AB6: 12A
A7: F0003 | B7: Skyfall | C7: 2012 | D7: Blu-ray | E7: James Bond | I7: When Bond's latest assignment goes gravely wrong, agents around the world are exposed and MI6 headquarters is attacked. While M faces challenges to her authority and position from Gareth Mallory, the new Chairman of the Intelligence and Security Committee, it's up to Bond, aided only by field agent Eve, to locate the mastermind behind the attack. | J7: Sam Mendes | K7: 143 | L7: Action, Adventure, Thriller | M7: Metro-Goldwyn-Mayer, Eon Productions, Danjaq | N7: https://huggingface.co/datasets/HenryWaltson/TMDB-IMDB-Movies-Dataset | O7: https://huggingface.co/datasets/HenryWaltson/TMDB-IMDB-Movies-Dataset | P7: Daniel Craig | Q7: Judi Dench | R7: Javier Bardem | S7: Ralph Fiennes | T7: Naomie Harris | U7: 5 | V7: 2 | X7: {=IFERROR(INDEX(Ratings!$E$5:$E$500,MATCH(A7,Ratings!$A$5:$A$500,0)),"")} | Y7: {=IFERROR(INDEX(Ratings!$G$5:$G$500,MATCH(A7,Ratings!$A$5:$A$500,0)),"")} | Z7: {=IFERROR(INDEX(Ratings!$I$5:$I$500,MATCH(A7,Ratings!$A$5:$A$500,0)),"")} | AB7: 12A
A8: F0004 | B8: Spectre | C8: 2015 | D8: Blu-ray | E8: James Bond | I8: A cryptic message from Bond’s past sends him on a trail to uncover a sinister organization. While M battles political forces to keep the secret service alive, Bond peels back the layers of deceit to reveal the terrible truth behind SPECTRE. | J8: Sam Mendes | K8: 148 | L8: Action, Adventure, Thriller | M8: Columbia Pictures, Metro-Goldwyn-Mayer, Eon Productions | N8: https://huggingface.co/datasets/HenryWaltson/TMDB-IMDB-Movies-Dataset | O8: https://huggingface.co/datasets/HenryWaltson/TMDB-IMDB-Movies-Dataset | P8: Daniel Craig | Q8: Christoph Waltz | R8: Léa Seydoux | S8: Ralph Fiennes | T8: Monica Bellucci | U8: 1 | V8: 1 | X8: {=IFERROR(INDEX(Ratings!$E$5:$E$500,MATCH(A8,Ratings!$A$5:$A$500,0)),"")} | Y8: {=IFERROR(INDEX(Ratings!$G$5:$G$500,MATCH(A8,Ratings!$A$5:$A$500,0)),"")} | Z8: {=IFERROR(INDEX(Ratings!$I$5:$I$500,MATCH(A8,Ratings!$A$5:$A$500,0)),"")} | AB8: 12A
A9: F0005 | B9: No Time to Die | C9: 2021 | D9: Blu-ray | E9: James Bond | I9: Bond has left active service and is enjoying a tranquil life in Jamaica. His peace is short-lived when his old friend Felix Leiter from the CIA turns up asking for help. The mission to rescue a kidnapped scientist turns out to be far more treacherous than expected, leading Bond onto the trail of a mysterious villain armed with dangerous new technology. | J9: Cary Joji Fukunaga | K9: 163 | L9: Action, Thriller, Romance | M9: Eon Productions, Metro-Goldwyn-Mayer, Universal Pictures | N9: https://huggingface.co/datasets/HenryWaltson/TMDB-IMDB-Movies-Dataset | O9: https://huggingface.co/datasets/HenryWaltson/TMDB-IMDB-Movies-Dataset | P9: Daniel Craig | Q9: Léa Seydoux | R9: Rami Malek | S9: Lashana Lynch | T9: Ralph Fiennes | U9: 3 | V9: 1 | X9: {=IFERROR(INDEX(Ratings!$E$5:$E$500,MATCH(A9,Ratings!$A$5:$A$500,0)),"")} | Y9: {=IFERROR(INDEX(Ratings!$G$5:$G$500,MATCH(A9,Ratings!$A$5:$A$500,0)),"")} | Z9: {=IFERROR(INDEX(Ratings!$I$5:$I$500,MATCH(A9,Ratings!$A$5:$A$500,0)),"")} | AB9: 12A
A10: F0006 | B10: 2012 | C10: 2009 | D10: Blu-ray | I10: Dr. Adrian Helmsley, part of a worldwide geophysical team investigating the effect on the earth of radiation from unprecedented solar storms, learns that the earth's core is heating up. He warns U.S. President Thomas Wilson that the crust of the earth is becoming unstable and that without proper preparations for saving a fraction of the world's population, the entire race is doomed. Meanwhile, writer Jackson Curtis stumbles on the same information. While the world's leaders race to build "arks" to escape the impending cataclysm, Curtis struggles to find a way to save his family. Meanwhile, volcanic eruptions and earthquakes of unprecedented strength wreak havoc around the world. | J10: Roland Emmerich | K10: 158 | L10: Action, Adventure, Science Fiction | M10: Columbia Pictures, Centropolis Entertainment, Farewell Productions | N10: https://huggingface.co/datasets/HenryWaltson/TMDB-IMDB-Movies-Dataset | O10: https://huggingface.co/datasets/HenryWaltson/TMDB-IMDB-Movies-Dataset | P10: John Cusack | Q10: Amanda Peet | R10: Chiwetel Ejiofor | S10: Thandiwe Newton | T10: Oliver Platt | U10: 0 | V10: 0 | X10: {=IFERROR(INDEX(Ratings!$E$5:$E$500,MATCH(A10,Ratings!$A$5:$A$500,0)),"")} | Y10: {=IFERROR(INDEX(Ratings!$G$5:$G$500,MATCH(A10,Ratings!$A$5:$A$500,0)),"")} | Z10: {=IFERROR(INDEX(Ratings!$I$5:$I$500,MATCH(A10,Ratings!$A$5:$A$500,0)),"")} | AB10: 12A
A11: F0007 | B11: 21 Jump Street | C11: 2012 | D11: Blu-ray | E11: Jump Street | G11: Yes | H11: ⭐⭐⭐ | I11: When cops Schmidt and Jenko join the secret Jump Street unit, they use their youthful appearances to go undercover as high school students. They trade in their guns and badges for backpacks, and set out to shut down a dangerous drug ring. But, as time goes on, Schmidt and Jenko discover that high school is nothing like it was just a few years earlier -- and, what's more, they must again confront the teenage terror and anxiety they thought they had left behind. | J11: Phil Lord, Christopher Miller | K11: 109 | L11: Action, Comedy, Crime | M11: Columbia Pictures, Relativity Media, Original Film | N11: https://huggingface.co/datasets/HenryWaltson/TMDB-IMDB-Movies-Dataset | O11: https://huggingface.co/datasets/HenryWaltson/TMDB-IMDB-Movies-Dataset | P11: Jonah Hill | Q11: Channing Tatum | R11: Brie Larson | S11: Dave Franco | T11: Rob Riggle | U11: 0 | V11: 0 | X11: {=IFERROR(INDEX(Ratings!$E$5:$E$500,MATCH(A11,Ratings!$A$5:$A$500,0)),"")} | Y11: {=IFERROR(INDEX(Ratings!$G$5:$G$500,MATCH(A11,Ratings!$A$5:$A$500,0)),"")} | Z11: {=IFERROR(INDEX(Ratings!$I$5:$I$500,MATCH(A11,Ratings!$A$5:$A$500,0)),"")} | AA11: 2026-07-08 | AB11: 15
A12: F0008 | B12: 22 Jump Street | C12: 2014 | D12: Blu-ray | E12: Jump Street | G12: Yes | H12: ⭐⭐⭐ | I12: After making their way through high school (twice), big changes are in store for officers Schmidt and Jenko when they go deep undercover at a local college. But when Jenko meets a kindred spirit on the football team, and Schmidt infiltrates the bohemian art major scene, they begin to question their partnership. Now they don't have to just crack the case - they have to figure out if they can have a mature relationship. If these two overgrown adolescents can grow from freshmen into real men, college might be the best thing that ever happened to them. | J12: Phil Lord, Christopher Miller | K12: 112 | L12: Crime, Comedy, Action | M12: Columbia Pictures, Original Film, MRC | N12: https://huggingface.co/datasets/HenryWaltson/TMDB-IMDB-Movies-Dataset | O12: https://huggingface.co/datasets/HenryWaltson/TMDB-IMDB-Movies-Dataset | P12: Jonah Hill | Q12: Channing Tatum | R12: Peter Stormare | S12: Wyatt Russell | T12: Amber Stevens West | U12: 0 | V12: 0 | X12: {=IFERROR(INDEX(Ratings!$E$5:$E$500,MATCH(A12,Ratings!$A$5:$A$500,0)),"")} | Y12: {=IFERROR(INDEX(Ratings!$G$5:$G$500,MATCH(A12,Ratings!$A$5:$A$500,0)),"")} | Z12: {=IFERROR(INDEX(Ratings!$I$5:$I$500,MATCH(A12,Ratings!$A$5:$A$500,0)),"")} | AA12: 2026-07-09 | AB12: 15
A13: F0009 | B13: 30 Minutes or Less | C13: 2011 | D13: Blu-ray | I13: Two fledgling criminals kidnap a pizza delivery guy, strap a bomb to his chest, and advise him that he has mere hours to rob a bank or else... | J13: Ruben Fleischer | K13: 83 | L13: Action, Adventure, Comedy | M13: Columbia Pictures | N13: https://huggingface.co/datasets/HenryWaltson/TMDB-IMDB-Movies-Dataset | O13: https://huggingface.co/datasets/HenryWaltson/TMDB-IMDB-Movies-Dataset | P13: Jesse Eisenberg | Q13: Aziz Ansari | R13: Danny McBride | S13: Nick Swardson | T13: Dilshad Vadsaria | U13: 0 | V13: 0 | X13: {=IFERROR(INDEX(Ratings!$E$5:$E$500,MATCH(A13,Ratings!$A$5:$A$500,0)),"")} | Y13: {=IFERROR(INDEX(Ratings!$G$5:$G$500,MATCH(A13,Ratings!$A$5:$A$500,0)),"")} | Z13: {=IFERROR(INDEX(Ratings!$I$5:$I$500,MATCH(A13,Ratings!$A$5:$A$500,0)),"")} | AB13: 15
A14: F0010 | B14: 44 Inch Chest | C14: 2009 | D14: Blu-ray | I14: Colin is in agony, shattered by his wife’s infidelity, so his friends kidnap the wife's lover so he can have his revenge. | J14: Malcolm Venville | K14: 95 | L14: Drama, Crime | M14: Omni Films, Prescience Media, Twilight Production & Entertainment | N14: https://huggingface.co/datasets/HenryWaltson/TMDB-IMDB-Movies-Dataset | O14: https://huggingface.co/datasets/HenryWaltson/TMDB-IMDB-Movies-Dataset | P14: Ray Winstone | Q14: John Hurt | R14: Ian McShane | S14: Tom Wilkinson | T14: Joanne Whalley | U14: 0 | V14: 0 | X14: {=IFERROR(INDEX(Ratings!$E$5:$E$500,MATCH(A14,Ratings!$A$5:$A$500,0)),"")} | Y14: {=IFERROR(INDEX(Ratings!$G$5:$G$500,MATCH(A14,Ratings!$A$5:$A$500,0)),"")} | Z14: {=IFERROR(INDEX(Ratings!$I$5:$I$500,MATCH(A14,Ratings!$A$5:$A$500,0)),"")} | AB14: 18
A15: F0011 | B15: 50/50 | C15: 2011 | D15: Blu-ray | I15: Inspired by a true story, a comedy centered on a 27-year-old guy who learns of his cancer diagnosis and his subsequent struggle to beat the disease. | J15: Jonathan Levine | K15: 100 | L15: Comedy, Drama | M15: Summit Entertainment, Mandate Pictures, Point Grey Pictures | N15: https://huggingface.co/datasets/HenryWaltson/TMDB-IMDB-Movies-Dataset | O15: https://huggingface.co/datasets/HenryWaltson/TMDB-IMDB-Movies-Dataset | P15: Joseph Gordon-Levitt | Q15: Seth Rogen | R15: Anna Kendrick | S15: Bryce Dallas Howard | T15: Philip Baker Hall | U15: 0 | V15: 0 | X15: {=IFERROR(INDEX(Ratings!$E$5:$E$500,MATCH(A15,Ratings!$A$5:$A$500,0)),"")} | Y15: {=IFERROR(INDEX(Ratings!$G$5:$G$500,MATCH(A15,Ratings!$A$5:$A$500,0)),"")} | Z15: {=IFERROR(INDEX(Ratings!$I$5:$I$500,MATCH(A15,Ratings!$A$5:$A$500,0)),"")} | AB15: 15
A16: F0012 | B16: A Bug's Life | C16: 1998 | D16: Blu-ray | G16: Yes | H16: ⭐⭐⭐⭐ | I16: On behalf of "oppressed bugs everywhere," an inventive ant named Flik hires a troupe of warrior bugs to defend his bustling colony from a horde of freeloading grasshoppers led by the evil-minded Hopper. | J16: John Lasseter, Andrew Stanton | K16: 95 | L16: Adventure, Animation, Comedy, Family | M16: Pixar, Walt Disney Pictures | N16: https://huggingface.co/datasets/HenryWaltson/TMDB-IMDB-Movies-Dataset | O16: https://huggingface.co/datasets/HenryWaltson/TMDB-IMDB-Movies-Dataset | P16: Dave Foley | Q16: Kevin Spacey | R16: Julia Louis-Dreyfus | S16: Hayden Panettiere | T16: Phyllis Diller | U16: 1 | V16: 0 | X16: {=IFERROR(INDEX(Ratings!$E$5:$E$500,MATCH(A16,Ratings!$A$5:$A$500,0)),"")} | Y16: {=IFERROR(INDEX(Ratings!$G$5:$G$500,MATCH(A16,Ratings!$A$5:$A$500,0)),"")} | Z16: {=IFERROR(INDEX(Ratings!$I$5:$I$500,MATCH(A16,Ratings!$A$5:$A$500,0)),"")} | AB16: U
A17: F0013 | B17: The Accountant | C17: 2016 | D17: Blu-ray | I17: As a math savant uncooks the books for a new client, the Treasury Department closes in on his activities and the body count starts to rise. | J17: Gavin O'Connor | K17: 128 | L17: Crime, Thriller, Drama | M17: Zero Gravity Management, Electric City Entertainment, RatPac Entertainment | N17: https://huggingface.co/datasets/HenryWaltson/TMDB-IMDB-Movies-Dataset | O17: https://huggingface.co/datasets/HenryWaltson/TMDB-IMDB-Movies-Dataset | P17: Ben Affleck | Q17: Cynthia Addai-Robinson | R17: Anna Kendrick | S17: J.K. Simmons | T17: Jon Bernthal | U17: 0 | V17: 0 | X17: {=IFERROR(INDEX(Ratings!$E$5:$E$500,MATCH(A17,Ratings!$A$5:$A$500,0)),"")} | Y17: {=IFERROR(INDEX(Ratings!$G$5:$G$500,MATCH(A17,Ratings!$A$5:$A$500,0)),"")} | Z17: {=IFERROR(INDEX(Ratings!$I$5:$I$500,MATCH(A17,Ratings!$A$5:$A$500,0)),"")} | AB17: 15
A18: F0014 | B18: Alan Partridge: Alpha Papa | C18: 2013 | D18: Blu-ray | I18: When famous DJ Alan Partridge’s radio station is taken over by a new media conglomerate, it sets in motion a chain of events which see Alan having to work with the police to defuse a potentially violent siege. | J18: Declan Lowney | K18: 90 | L18: Comedy | M18: BFI, BBC Film, StudioCanal | N18: https://huggingface.co/datasets/HenryWaltson/TMDB-IMDB-Movies-Dataset | O18: https://huggingface.co/datasets/HenryWaltson/TMDB-IMDB-Movies-Dataset | P18: Steve Coogan | Q18: Colm Meaney | R18: Felicity Montagu | S18: Simon Greenall | T18: Anna Maxwell Martin | U18: 0 | V18: 0 | X18: {=IFERROR(INDEX(Ratings!$E$5:$E$500,MATCH(A18,Ratings!$A$5:$A$500,0)),"")} | Y18: {=IFERROR(INDEX(Ratings!$G$5:$G$500,MATCH(A18,Ratings!$A$5:$A$500,0)),"")} | Z18: {=IFERROR(INDEX(Ratings!$I$5:$I$500,MATCH(A18,Ratings!$A$5:$A$500,0)),"")} | AB18: 15
A19: F0015 | B19: Alien | C19: 1979 | D19: Blu-ray | E19: Alien | I19: During its return to the earth, commercial spaceship Nostromo intercepts a distress signal from a distant planet. When a three-member team of the crew discovers a chamber containing thousands of eggs on the planet, a creature inside one of the eggs attacks an explorer. The entire crew is unaware of the impending nightmare set to descend upon them when the alien parasite planted inside its unfortunate host is birthed. | J19: Ridley Scott | K19: 117 | L19: Horror, Science Fiction | M19: Brandywine Productions, 20th Century Fox | N19: https://huggingface.co/datasets/HenryWaltson/TMDB-IMDB-Movies-Dataset | O19: https://huggingface.co/datasets/HenryWaltson/TMDB-IMDB-Movies-Dataset | P19: Tom Skerritt | Q19: Sigourney Weaver | R19: Veronica Cartwright | S19: Harry Dean Stanton | T19: John Hurt | U19: 2 | V19: 1 | X19: {=IFERROR(INDEX(Ratings!$E$5:$E$500,MATCH(A19,Ratings!$A$5:$A$500,0)),"")} | Y19: {=IFERROR(INDEX(Ratings!$G$5:$G$500,MATCH(A19,Ratings!$A$5:$A$500,0)),"")} | Z19: {=IFERROR(INDEX(Ratings!$I$5:$I$500,MATCH(A19,Ratings!$A$5:$A$500,0)),"")} | AB19: 18
A20: F0016 | B20: Aliens | C20: 1986 | D20: Blu-ray | E20: Alien | I20: Ripley, the sole survivor of the Nostromo's deadly encounter with the monstrous Alien, returns to Earth after drifting through space in hypersleep for 57 years. Although her story is initially met with skepticism, she agrees to accompany a team of Colonial Marines back to LV-426. | J20: James Cameron | K20: 137 | L20: Action, Thriller, Science Fiction | M20: Brandywine Productions, SLM Production Group, 20th Century Fox | N20: https://huggingface.co/datasets/HenryWaltson/TMDB-IMDB-Movies-Dataset | O20: https://huggingface.co/datasets/HenryWaltson/TMDB-IMDB-Movies-Dataset | P20: Sigourney Weaver | Q20: Carrie Henn | R20: Michael Biehn | S20: Paul Reiser | T20: Lance Henriksen | U20: 7 | V20: 2 | X20: {=IFERROR(INDEX(Ratings!$E$5:$E$500,MATCH(A20,Ratings!$A$5:$A$500,0)),"")} | Y20: {=IFERROR(INDEX(Ratings!$G$5:$G$500,MATCH(A20,Ratings!$A$5:$A$500,0)),"")} | Z20: {=IFERROR(INDEX(Ratings!$I$5:$I$500,MATCH(A20,Ratings!$A$5:$A$500,0)),"")} | AB20: 18
A21: F0017 | B21: Alien³ | C21: 1992 | D21: Blu-ray | E21: Alien | I21: After escaping with Newt and Hicks from the alien planet, Ripley crash lands on Fiorina 161, a prison planet and host to a correctional facility. Unfortunately, although Newt and Hicks do not survive the crash, a more unwelcome visitor does. The prison does not allow weapons of any kind, and with aid being a long time away, the prisoners must simply survive in any way they can. | J21: David Fincher | K21: 114 | L21: Science Fiction, Horror, Action | M21: 20th Century Fox, Brandywine Productions | N21: https://huggingface.co/datasets/HenryWaltson/TMDB-IMDB-Movies-Dataset | O21: https://huggingface.co/datasets/HenryWaltson/TMDB-IMDB-Movies-Dataset | P21: Sigourney Weaver | Q21: Charles S. Dutton | R21: Charles Dance | S21: Paul McGann | T21: Brian Glover | U21: 0 | V21: 0 | X21: {=IFERROR(INDEX(Ratings!$E$5:$E$500,MATCH(A21,Ratings!$A$5:$A$500,0)),"")} | Y21: {=IFERROR(INDEX(Ratings!$G$5:$G$500,MATCH(A21,Ratings!$A$5:$A$500,0)),"")} | Z21: {=IFERROR(INDEX(Ratings!$I$5:$I$500,MATCH(A21,Ratings!$A$5:$A$500,0)),"")} | AB21: 18
A22: F0018 | B22: Alien Resurrection | C22: 1997 | D22: Blu-ray | E22: Alien | I22: Two hundred years after Lt. Ripley died, a group of scientists clone her, hoping to breed the ultimate weapon. But the new Ripley is full of surprises … as are the new aliens. Ripley must team with a band of smugglers to keep the creatures from reaching Earth. | J22: Jean-Pierre Jeunet | K22: 109 | L22: Science Fiction, Horror, Action | M22: Brandywine Productions, 20th Century Fox | N22: https://huggingface.co/datasets/HenryWaltson/TMDB-IMDB-Movies-Dataset | O22: https://huggingface.co/datasets/HenryWaltson/TMDB-IMDB-Movies-Dataset | P22: Sigourney Weaver | Q22: Winona Ryder | R22: Dominique Pinon | S22: Ron Perlman | T22: Gary Dourdan | U22: 0 | V22: 0 | X22: {=IFERROR(INDEX(Ratings!$E$5:$E$500,MATCH(A22,Ratings!$A$5:$A$500,0)),"")} | Y22: {=IFERROR(INDEX(Ratings!$G$5:$G$500,MATCH(A22,Ratings!$A$5:$A$500,0)),"")} | Z22: {=IFERROR(INDEX(Ratings!$I$5:$I$500,MATCH(A22,Ratings!$A$5:$A$500,0)),"")} | AB22: 18
A23: F0019 | B23: The Amazing Spider-Man | C23: 2012 | D23: Blu-ray | E23: Spider-Man | I23: A teenage Peter Parker grapples with both high school and amazing super-human crises as his alter-ego Spider-Man. | J23: Marc Webb | K23: 136 | L23: Action, Adventure, Fantasy | M23: Marvel Entertainment, Laura Ziskin Productions, Columbia Pictures | N23: https://huggingface.co/datasets/HenryWaltson/TMDB-IMDB-Movies-Dataset | O23: https://huggingface.co/datasets/HenryWaltson/TMDB-IMDB-Movies-Dataset | P23: Andrew Garfield | Q23: Emma Stone | R23: Rhys Ifans | S23: Denis Leary | T23: Martin Sheen | U23: 0 | V23: 0 | X23: {=IFERROR(INDEX(Ratings!$E$5:$E$500,MATCH(A23,Ratings!$A$5:$A$500,0)),"")} | Y23: {=IFERROR(INDEX(Ratings!$G$5:$G$500,MATCH(A23,Ratings!$A$5:$A$500,0)),"")} | Z23: {=IFERROR(INDEX(Ratings!$I$5:$I$500,MATCH(A23,Ratings!$A$5:$A$500,0)),"")} | AB23: 12A
A24: F0020 | B24: American Hustle | C24: 2013 | D24: Blu-ray | I24: A conman and his seductive partner are forced to work for a wild FBI agent, who pushes them into a world of Jersey power-brokers and the Mafia. | J24: David O. Russell | K24: 138 | L24: Drama, Crime | M24: Annapurna Pictures, Atlas Entertainment, Columbia Pictures | N24: https://huggingface.co/datasets/HenryWaltson/TMDB-IMDB-Movies-Dataset | O24: https://huggingface.co/datasets/HenryWaltson/TMDB-IMDB-Movies-Dataset | P24: Christian Bale | Q24: Bradley Cooper | R24: Amy Adams | S24: Jeremy Renner | T24: Jennifer Lawrence | U24: 10 | V24: 0 | W24: Nominated | X24: {=IFERROR(INDEX(Ratings!$E$5:$E$500,MATCH(A24,Ratings!$A$5:$A$500,0)),"")} | Y24: {=IFERROR(INDEX(Ratings!$G$5:$G$500,MATCH(A24,Ratings!$A$5:$A$500,0)),"")} | Z24: {=IFERROR(INDEX(Ratings!$I$5:$I$500,MATCH(A24,Ratings!$A$5:$A$500,0)),"")} | AB24: 15
A25: F0021 | B25: A Million Ways to Die in the West | C25: 2014 | D25: Blu-ray | I25: As a cowardly farmer begins to fall for the mysterious new woman in town, he must put his new-found courage to the test when her husband, a notorious gun-slinger, announces his arrival. | J25: Seth MacFarlane | K25: 116 | L25: Comedy, Western | M25: RGB Media, Fuzzy Door Productions, MRC | N25: https://huggingface.co/datasets/HenryWaltson/TMDB-IMDB-Movies-Dataset | O25: https://huggingface.co/datasets/HenryWaltson/TMDB-IMDB-Movies-Dataset | P25: Seth MacFarlane | Q25: Charlize Theron | R25: Amanda Seyfried | S25: Liam Neeson | T25: Giovanni Ribisi | U25: 0 | V25: 0 | X25: {=IFERROR(INDEX(Ratings!$E$5:$E$500,MATCH(A25,Ratings!$A$5:$A$500,0)),"")} | Y25: {=IFERROR(INDEX(Ratings!$G$5:$G$500,MATCH(A25,Ratings!$A$5:$A$500,0)),"")} | Z25: {=IFERROR(INDEX(Ratings!$I$5:$I$500,MATCH(A25,Ratings!$A$5:$A$500,0)),"")} | AB25: 15
A26: F0022 | B26: Anchorman: The Legend of Ron Burgundy | C26: 2004 | D26: Blu-ray | E26: Anchorman | G26: Yes | H26: ⭐⭐⭐⭐ | I26: It's the 1970s and San Diego anchorman Ron Burgundy is the top dog in local TV, but that's all about to change when ambitious reporter Veronica Corningstone arrives as a new employee at his station. | J26: Adam McKay | K26: 95 | L26: Comedy | M26: DreamWorks Pictures, Apatow Productions | N26: https://huggingface.co/datasets/HenryWaltson/TMDB-IMDB-Movies-Dataset | O26: https://huggingface.co/datasets/HenryWaltson/TMDB-IMDB-Movies-Dataset | P26: Will Ferrell | Q26: Christina Applegate | R26: Paul Rudd | S26: Steve Carell | T26: David Koechner | U26: 0 | V26: 0 | X26: {=IFERROR(INDEX(Ratings!$E$5:$E$500,MATCH(A26,Ratings!$A$5:$A$500,0)),"")} | Y26: {=IFERROR(INDEX(Ratings!$G$5:$G$500,MATCH(A26,Ratings!$A$5:$A$500,0)),"")} | Z26: {=IFERROR(INDEX(Ratings!$I$5:$I$500,MATCH(A26,Ratings!$A$5:$A$500,0)),"")} | AA26: 2026-09-12 | AB26: 15
A27: F0023 | B27: Angels & Demons | C27: 2009 | D27: Blu-ray | I27: Harvard symbologist Robert Langdon is recruited by the Vatican to investigate the apparent return of the Illuminati – a secret, underground organization – after four cardinals are kidnapped on the night of the papal conclave. | J27: Ron Howard | K27: 138 | L27: Thriller, Mystery | M27: Columbia Pictures, Imagine Entertainment, Skylark Productions | N27: https://huggingface.co/datasets/HenryWaltson/TMDB-IMDB-Movies-Dataset | O27: https://huggingface.co/datasets/HenryWaltson/TMDB-IMDB-Movies-Dataset | P27: Tom Hanks | Q27: Ewan McGregor | R27: Ayelet Zurer | S27: Stellan Skarsgård | T27: Pierfrancesco Favino | U27: 0 | V27: 0 | X27: {=IFERROR(INDEX(Ratings!$E$5:$E$500,MATCH(A27,Ratings!$A$5:$A$500,0)),"")} | Y27: {=IFERROR(INDEX(Ratings!$G$5:$G$500,MATCH(A27,Ratings!$A$5:$A$500,0)),"")} | Z27: {=IFERROR(INDEX(Ratings!$I$5:$I$500,MATCH(A27,Ratings!$A$5:$A$500,0)),"")} | AB27: 12A
A28: F0024 | B28: Anuvahood | C28: 2011 | D28: Blu-ray | I28: Kenneth (who likes to call himself Kay) begins to realise he's just another wannabe bad boy... even less than a loser in fact. After quitting his job at Laimsbury's, Kay vows to become a respected gangster... or cry trying. A pulls-no-punches, coming-of-age story, centering on one directionless hopeless "shotter", who finds his true worth in the face of urban adversity. | J28: Adam Deacon, Daniel Toland | K28: 88 | L28: Comedy | M28: Gunslinger, Gateway Films, Cabin Fever Films | N28: https://huggingface.co/datasets/HenryWaltson/TMDB-IMDB-Movies-Dataset | O28: https://huggingface.co/datasets/HenryWaltson/TMDB-IMDB-Movies-Dataset | P28: Adam Deacon | Q28: Ollie Barbieri | R28: Jazzie Zonzolo | S28: Richie Campbell | T28: Jaime Winstone | U28: 0 | V28: 0 | X28: {=IFERROR(INDEX(Ratings!$E$5:$E$500,MATCH(A28,Ratings!$A$5:$A$500,0)),"")} | Y28: {=IFERROR(INDEX(Ratings!$G$5:$G$500,MATCH(A28,Ratings!$A$5:$A$500,0)),"")} | Z28: {=IFERROR(INDEX(Ratings!$I$5:$I$500,MATCH(A28,Ratings!$A$5:$A$500,0)),"")} | AB28: 15
A29: F0025 | B29: Argo | C29: 2012 | D29: Blu-ray | I29: As the Iranian revolution reaches a boiling point, a CIA 'exfiltration' specialist concocts a risky plan to free six Americans who have found shelter at the home of the Canadian ambassador. | J29: Ben Affleck | K29: 120 | L29: Drama, Thriller | M29: GK Films, Warner Bros. Pictures, Smoke House Pictures | N29: https://huggingface.co/datasets/HenryWaltson/TMDB-IMDB-Movies-Dataset | O29: https://huggingface.co/datasets/HenryWaltson/TMDB-IMDB-Movies-Dataset | P29: Ben Affleck | Q29: Bryan Cranston | R29: Alan Arkin | S29: John Goodman | T29: Victor Garber | U29: 7 | V29: 3 | W29: Winner | X29: {=IFERROR(INDEX(Ratings!$E$5:$E$500,MATCH(A29,Ratings!$A$5:$A$500,0)),"")} | Y29: {=IFERROR(INDEX(Ratings!$G$5:$G$500,MATCH(A29,Ratings!$A$5:$A$500,0)),"")} | Z29: {=IFERROR(INDEX(Ratings!$I$5:$I$500,MATCH(A29,Ratings!$A$5:$A$500,0)),"")} | AB29: 15
A30: F0026 | B30: The A-Team | C30: 2010 | D30: Blu-ray | I30: A man who loves when a plan comes together, Col. Hannibal Smith leads a close-knit team of elite operatives and Iraq War veterans. Framed for a crime they didn't commit, Smith and his men, Capt. H.M. ‘Howling Mad’ Murdock , Sgt. Bosco ‘B.A.’ Baracus, and Lt. Templeton ‘Faceman’ Peck, break out and go rogue, using their special talents to clear their names and find the perpetrator. Hot on their trail is Capt. Charissa Sosa, who was once involved with a member of Smith's team and has sworn to capture them, no matter what it takes. | J30: Joe Carnahan | K30: 117 | L30: Thriller, Action, Adventure, Comedy, Crime | M30: Phoenix Film Partners, Dune Entertainment, Stephen J. Cannell Productions | N30: https://huggingface.co/datasets/HenryWaltson/TMDB-IMDB-Movies-Dataset | O30: https://huggingface.co/datasets/HenryWaltson/TMDB-IMDB-Movies-Dataset | P30: Liam Neeson | Q30: Bradley Cooper | R30: Jessica Biel | S30: Quinton 'Rampage' Jackson | T30: Sharlto Copley | U30: 0 | V30: 0 | X30: {=IFERROR(INDEX(Ratings!$E$5:$E$500,MATCH(A30,Ratings!$A$5:$A$500,0)),"")} | Y30: {=IFERROR(INDEX(Ratings!$G$5:$G$500,MATCH(A30,Ratings!$A$5:$A$500,0)),"")} | Z30: {=IFERROR(INDEX(Ratings!$I$5:$I$500,MATCH(A30,Ratings!$A$5:$A$500,0)),"")} | AB30: 12A
A31: F0027 | B31: Attack the Block | C31: 2011 | D31: Blu-ray | I31: A South London teen gang must team up with the other residents of their housing estate to protect the neighbourhood from a terrifying alien invasion. | J31: Joe Cornish | K31: 88 | L31: Action, Comedy, Science Fiction | M31: UK Film Council, Film4 Productions, StudioCanal | N31: https://huggingface.co/datasets/HenryWaltson/TMDB-IMDB-Movies-Dataset | O31: https://huggingface.co/datasets/HenryWaltson/TMDB-IMDB-Movies-Dataset | P31: John Boyega | Q31: Jodie Whittaker | R31: Nick Frost | S31: Alex Esmail | T31: Luke Treadaway | U31: 0 | V31: 0 | X31: {=IFERROR(INDEX(Ratings!$E$5:$E$500,MATCH(A31,Ratings!$A$5:$A$500,0)),"")} | Y31: {=IFERROR(INDEX(Ratings!$G$5:$G$500,MATCH(A31,Ratings!$A$5:$A$500,0)),"")} | Z31: {=IFERROR(INDEX(Ratings!$I$5:$I$500,MATCH(A31,Ratings!$A$5:$A$500,0)),"")} | AB31: 15
A32: F0028 | B32: Avatar | C32: 2009 | D32: Blu-ray | E32: Avatar | I32: In the 22nd century, a paraplegic Marine is dispatched to the moon Pandora on a unique mission, but becomes torn between following orders and protecting an alien civilization. | J32: James Cameron | K32: 162 | L32: Action, Adventure, Fantasy, Science Fiction | M32: Dune Entertainment, Lightstorm Entertainment, 20th Century Fox | N32: https://huggingface.co/datasets/HenryWaltson/TMDB-IMDB-Movies-Dataset | O32: https://huggingface.co/datasets/HenryWaltson/TMDB-IMDB-Movies-Dataset | P32: Sam Worthington | Q32: Zoe Saldaña | R32: Sigourney Weaver | S32: Stephen Lang | T32: Michelle Rodriguez | U32: 9 | V32: 3 | W32: Nominated | X32: {=IFERROR(INDEX(Ratings!$E$5:$E$500,MATCH(A32,Ratings!$A$5:$A$500,0)),"")} | Y32: {=IFERROR(INDEX(Ratings!$G$5:$G$500,MATCH(A32,Ratings!$A$5:$A$500,0)),"")} | Z32: {=IFERROR(INDEX(Ratings!$I$5:$I$500,MATCH(A32,Ratings!$A$5:$A$500,0)),"")} | AB32: 12A
A33: F0029 | B33: The Avengers | C33: 2012 | D33: Blu-ray | E33: MCU | I33: When an unexpected enemy emerges and threatens global safety and security, Nick Fury, director of the international peacekeeping agency known as S.H.I.E.L.D., finds himself in need of a team to pull the world back from the brink of disaster. Spanning the globe, a daring recruitment effort begins! | J33: Joss Whedon | K33: 143 | L33: Science Fiction, Action, Adventure | M33: Marvel Studios | N33: https://huggingface.co/datasets/HenryWaltson/TMDB-IMDB-Movies-Dataset | O33: https://huggingface.co/datasets/HenryWaltson/TMDB-IMDB-Movies-Dataset | P33: Robert Downey Jr. | Q33: Chris Evans | R33: Mark Ruffalo | S33: Chris Hemsworth | T33: Scarlett Johansson | U33: 1 | V33: 0 | X33: {=IFERROR(INDEX(Ratings!$E$5:$E$500,MATCH(A33,Ratings!$A$5:$A$500,0)),"")} | Y33: {=IFERROR(INDEX(Ratings!$G$5:$G$500,MATCH(A33,Ratings!$A$5:$A$500,0)),"")} | Z33: {=IFERROR(INDEX(Ratings!$I$5:$I$500,MATCH(A33,Ratings!$A$5:$A$500,0)),"")} | AB33: 12A
A34: F0030 | B34: Avengers: Infinity War | C34: 2018 | D34: 4K UHD | E34: MCU | I34: As the Avengers and their allies have continued to protect the world from threats too large for any one hero to handle, a new danger has emerged from the cosmic shadows: Thanos. A despot of intergalactic infamy, his goal is to collect all six Infinity Stones, artifacts of unimaginable power, and use them to inflict his twisted will on all of reality. Everything the Avengers have fought for has led up to this moment - the fate of Earth and existence itself has never been more uncertain. | J34: Anthony Russo, Joe Russo | K34: 149 | L34: Adventure, Action, Science Fiction | M34: Marvel Studios | N34: https://huggingface.co/datasets/HenryWaltson/TMDB-IMDB-Movies-Dataset | O34: https://huggingface.co/datasets/HenryWaltson/TMDB-IMDB-Movies-Dataset | P34: Robert Downey Jr. | Q34: Chris Evans | R34: Chris Hemsworth | S34: Josh Brolin | T34: Mark Ruffalo | U34: 1 | V34: 0 | X34: {=IFERROR(INDEX(Ratings!$E$5:$E$500,MATCH(A34,Ratings!$A$5:$A$500,0)),"")} | Y34: {=IFERROR(INDEX(Ratings!$G$5:$G$500,MATCH(A34,Ratings!$A$5:$A$500,0)),"")} | Z34: {=IFERROR(INDEX(Ratings!$I$5:$I$500,MATCH(A34,Ratings!$A$5:$A$500,0)),"")} | AB34: 12A
A35: F0031 | B35: Avengers: Endgame | C35: 2019 | D35: 4K UHD | E35: MCU | I35: After the devastating events of Avengers: Infinity War, the universe is in ruins due to the efforts of the Mad Titan, Thanos. With the help of remaining allies, the Avengers must assemble once more in order to undo Thanos' actions and restore order to the universe once and for all, no matter what consequences may be in store. | J35: Anthony Russo, Joe Russo | K35: 181 | L35: Adventure, Science Fiction, Action | M35: Marvel Studios | N35: https://huggingface.co/datasets/HenryWaltson/TMDB-IMDB-Movies-Dataset | O35: https://huggingface.co/datasets/HenryWaltson/TMDB-IMDB-Movies-Dataset | P35: Robert Downey Jr. | Q35: Chris Evans | R35: Mark Ruffalo | S35: Chris Hemsworth | T35: Scarlett Johansson | U35: 1 | V35: 0 | X35: {=IFERROR(INDEX(Ratings!$E$5:$E$500,MATCH(A35,Ratings!$A$5:$A$500,0)),"")} | Y35: {=IFERROR(INDEX(Ratings!$G$5:$G$500,MATCH(A35,Ratings!$A$5:$A$500,0)),"")} | Z35: {=IFERROR(INDEX(Ratings!$I$5:$I$500,MATCH(A35,Ratings!$A$5:$A$500,0)),"")} | AB35: 12A
A36: F0032 | B36: Baby Driver | C36: 2017 | D36: Blu-ray | I36: After being coerced into working for a crime boss, a young getaway driver finds himself taking part in a heist doomed to fail. | J36: Edgar Wright | K36: 113 | L36: Action, Crime | M36: Big Talk Productions, Working Title Films | N36: https://huggingface.co/datasets/HenryWaltson/TMDB-IMDB-Movies-Dataset | O36: https://huggingface.co/datasets/HenryWaltson/TMDB-IMDB-Movies-Dataset | P36: Ansel Elgort | Q36: Kevin Spacey | R36: Lily James | S36: Jon Hamm | T36: Jamie Foxx | U36: 3 | V36: 0 | X36: {=IFERROR(INDEX(Ratings!$E$5:$E$500,MATCH(A36,Ratings!$A$5:$A$500,0)),"")} | Y36: {=IFERROR(INDEX(Ratings!$G$5:$G$500,MATCH(A36,Ratings!$A$5:$A$500,0)),"")} | Z36: {=IFERROR(INDEX(Ratings!$I$5:$I$500,MATCH(A36,Ratings!$A$5:$A$500,0)),"")} | AB36: 15
A37: F0033 | B37: Back to the Future | C37: 1985 | D37: Blu-ray | E37: Back to the Future | F37: Back to the Future Trilogy (Box Set) | I37: Owned via Back to the Future Trilogy (Box Set). | J37: Robert Zemeckis | K37: 116 | L37: Adventure, Comedy, Science Fiction | M37: Universal Pictures, Amblin Entertainment | N37: https://huggingface.co/datasets/HenryWaltson/TMDB-IMDB-Movies-Dataset | O37: https://huggingface.co/datasets/HenryWaltson/TMDB-IMDB-Movies-Dataset | P37: Michael J. Fox | Q37: Christopher Lloyd | R37: Crispin Glover | S37: Lea Thompson | T37: Claudia Wells | U37: 4 | V37: 1 | X37: {=IFERROR(INDEX(Ratings!$E$5:$E$500,MATCH(A37,Ratings!$A$5:$A$500,0)),"")} | Y37: {=IFERROR(INDEX(Ratings!$G$5:$G$500,MATCH(A37,Ratings!$A$5:$A$500,0)),"")} | Z37: {=IFERROR(INDEX(Ratings!$I$5:$I$500,MATCH(A37,Ratings!$A$5:$A$500,0)),"")} | AB37: PG
A38: F0034 | B38: Back to the Future Part II | C38: 1989 | D38: Blu-ray | E38: Back to the Future | F38: Back to the Future Trilogy (Box Set) | I38: Owned via Back to the Future Trilogy (Box Set). | J38: Robert Zemeckis | K38: 108 | L38: Adventure, Comedy, Science Fiction | M38: Universal Pictures, Amblin Entertainment | N38: https://huggingface.co/datasets/HenryWaltson/TMDB-IMDB-Movies-Dataset | O38: https://huggingface.co/datasets/HenryWaltson/TMDB-IMDB-Movies-Dataset | P38: Michael J. Fox | Q38: Christopher Lloyd | R38: Lea Thompson | S38: Thomas F. Wilson | T38: Elisabeth Shue | U38: 1 | V38: 0 | X38: {=IFERROR(INDEX(Ratings!$E$5:$E$500,MATCH(A38,Ratings!$A$5:$A$500,0)),"")} | Y38: {=IFERROR(INDEX(Ratings!$G$5:$G$500,MATCH(A38,Ratings!$A$5:$A$500,0)),"")} | Z38: {=IFERROR(INDEX(Ratings!$I$5:$I$500,MATCH(A38,Ratings!$A$5:$A$500,0)),"")} | AB38: PG
A39: F0035 | B39: Back to the Future Part III | C39: 1990 | D39: Blu-ray | E39: Back to the Future | F39: Back to the Future Trilogy (Box Set) | I39: Owned via Back to the Future Trilogy (Box Set). | J39: Robert Zemeckis | K39: 118 | L39: Adventure, Comedy, Science Fiction, Western | M39: Universal Pictures, Amblin Entertainment | N39: https://huggingface.co/datasets/HenryWaltson/TMDB-IMDB-Movies-Dataset | O39: https://huggingface.co/datasets/HenryWaltson/TMDB-IMDB-Movies-Dataset | P39: Michael J. Fox | Q39: Christopher Lloyd | R39: Mary Steenburgen | S39: Thomas F. Wilson | T39: Lea Thompson | U39: 0 | V39: 0 | X39: {=IFERROR(INDEX(Ratings!$E$5:$E$500,MATCH(A39,Ratings!$A$5:$A$500,0)),"")} | Y39: {=IFERROR(INDEX(Ratings!$G$5:$G$500,MATCH(A39,Ratings!$A$5:$A$500,0)),"")} | Z39: {=IFERROR(INDEX(Ratings!$I$5:$I$500,MATCH(A39,Ratings!$A$5:$A$500,0)),"")} | AB39: PG
A40: F0036 | B40: Bad Boys | C40: 1995 | D40: Blu-ray | E40: Bad Boys | F40: Bad Boys I & II (Box Set) | I40: Owned via Bad Boys I & II (Box Set). | J40: Michael Bay | K40: 119 | L40: Action, Comedy, Crime, Thriller | M40: Columbia Pictures, Don Simpson/Jerry Bruckheimer Films | N40: https://huggingface.co/datasets/HenryWaltson/TMDB-IMDB-Movies-Dataset | O40: https://huggingface.co/datasets/HenryWaltson/TMDB-IMDB-Movies-Dataset | P40: Will Smith | Q40: Martin Lawrence | R40: Téa Leoni | S40: Tchéky Karyo | T40: Joe Pantoliano | U40: 0 | V40: 0 | X40: {=IFERROR(INDEX(Ratings!$E$5:$E$500,MATCH(A40,Ratings!$A$5:$A$500,0)),"")} | Y40: {=IFERROR(INDEX(Ratings!$G$5:$G$500,MATCH(A40,Ratings!$A$5:$A$500,0)),"")} | Z40: {=IFERROR(INDEX(Ratings!$I$5:$I$500,MATCH(A40,Ratings!$A$5:$A$500,0)),"")} | AB40: 18
A41: F0037 | B41: Bad Boys II | C41: 2003 | D41: Blu-ray | E41: Bad Boys | F41: Bad Boys I & II (Box Set) | I41: Owned via Bad Boys I & II (Box Set). | J41: Michael Bay | K41: 147 | L41: Action, Comedy, Crime, Thriller | M41: Columbia Pictures, Don Simpson/Jerry Bruckheimer Films | N41: https://huggingface.co/datasets/HenryWaltson/TMDB-IMDB-Movies-Dataset | O41: https://huggingface.co/datasets/HenryWaltson/TMDB-IMDB-Movies-Dataset | P41: Martin Lawrence | Q41: Will Smith | R41: Jordi Mollà | S41: Gabrielle Union | T41: Peter Stormare | U41: 0 | V41: 0 | X41: {=IFERROR(INDEX(Ratings!$E$5:$E$500,MATCH(A41,Ratings!$A$5:$A$500,0)),"")} | Y41: {=IFERROR(INDEX(Ratings!$G$5:$G$500,MATCH(A41,Ratings!$A$5:$A$500,0)),"")} | Z41: {=IFERROR(INDEX(Ratings!$I$5:$I$500,MATCH(A41,Ratings!$A$5:$A$500,0)),"")} | AB41: 15
A42: F0038 | B42: Bad Moms | C42: 2016 | D42: Blu-ray | I42: When three overworked and under-appreciated moms are pushed beyond their limits, they ditch their conventional responsibilities for a jolt of long overdue freedom, fun, and comedic self-indulgence. | J42: Jon Lucas, Scott Moore | K42: 100 | L42: Comedy | M42: STX Films, BillBlock Media, Robert Simonds Productions | N42: https://huggingface.co/datasets/HenryWaltson/TMDB-IMDB-Movies-Dataset | O42: https://huggingface.co/datasets/HenryWaltson/TMDB-IMDB-Movies-Dataset | P42: Mila Kunis | Q42: Kristen Bell | R42: Kathryn Hahn | S42: Christina Applegate | T42: Jada Pinkett Smith | U42: 0 | V42: 0 | X42: {=IFERROR(INDEX(Ratings!$E$5:$E$500,MATCH(A42,Ratings!$A$5:$A$500,0)),"")} | Y42: {=IFERROR(INDEX(Ratings!$G$5:$G$500,MATCH(A42,Ratings!$A$5:$A$500,0)),"")} | Z42: {=IFERROR(INDEX(Ratings!$I$5:$I$500,MATCH(A42,Ratings!$A$5:$A$500,0)),"")} | AB42: 15
A43: F0039 | B43: Bad Teacher | C43: 2011 | D43: Blu-ray | I43: A lazy, incompetent middle school teacher who hates her job and her students is forced to return to her job to make enough money for a boob job after her rich fiancé dumps her. | J43: Jake Kasdan | K43: 92 | L43: Comedy | M43: Columbia Pictures, Mosaic Media Group | N43: https://huggingface.co/datasets/HenryWaltson/TMDB-IMDB-Movies-Dataset | O43: https://huggingface.co/datasets/HenryWaltson/TMDB-IMDB-Movies-Dataset | P43: Cameron Diaz | Q43: Jason Segel | R43: Justin Timberlake | S43: Lucy Punch | T43: John Michael Higgins | U43: 0 | V43: 0 | X43: {=IFERROR(INDEX(Ratings!$E$5:$E$500,MATCH(A43,Ratings!$A$5:$A$500,0)),"")} | Y43: {=IFERROR(INDEX(Ratings!$G$5:$G$500,MATCH(A43,Ratings!$A$5:$A$500,0)),"")} | Z43: {=IFERROR(INDEX(Ratings!$I$5:$I$500,MATCH(A43,Ratings!$A$5:$A$500,0)),"")} | AB43: 15
A44: F0040 | B44: The Bank Job | C44: 2008 | D44: Blu-ray | I44: Terry is a small-time car dealer trying to leave his shady past behind and start a family. Martine is a beautiful model from Terry's old neighbourhood who knows that Terry is no angel. When Martine proposes a foolproof plan to rob a bank, Terry recognises the danger but realises this may be the opportunity of a lifetime. | J44: Roger Donaldson | K44: 112 | L44: Thriller, Crime, Drama | M44: Omnilab Media, Mosaic Media Group, Relativity Media | N44: https://huggingface.co/datasets/HenryWaltson/TMDB-IMDB-Movies-Dataset | O44: https://huggingface.co/datasets/HenryWaltson/TMDB-IMDB-Movies-Dataset | P44: Jason Statham | Q44: Saffron Burrows | R44: Stephen Campbell Moore | S44: Daniel Mays | T44: James Faulkner | U44: 0 | V44: 0 | X44: {=IFERROR(INDEX(Ratings!$E$5:$E$500,MATCH(A44,Ratings!$A$5:$A$500,0)),"")} | Y44: {=IFERROR(INDEX(Ratings!$G$5:$G$500,MATCH(A44,Ratings!$A$5:$A$500,0)),"")} | Z44: {=IFERROR(INDEX(Ratings!$I$5:$I$500,MATCH(A44,Ratings!$A$5:$A$500,0)),"")} | AB44: 15
A45: F0041 | B45: Barbie | C45: 2023 | D45: Blu-ray | I45: Barbie and Ken are having the time of their lives in the colorful and seemingly perfect world of Barbie Land. However, when they get a chance to go to the real world, they soon discover the joys and perils of living among humans. | J45: Greta Gerwig | K45: 114 | L45: Comedy, Adventure, Fantasy | M45: LuckyChap Entertainment, Heyday Films, NB/GG Pictures | N45: https://huggingface.co/datasets/HenryWaltson/TMDB-IMDB-Movies-Dataset | O45: https://huggingface.co/datasets/HenryWaltson/TMDB-IMDB-Movies-Dataset | P45: Margot Robbie | Q45: Ryan Gosling | R45: America Ferrera | S45: Ariana Greenblatt | T45: Issa Rae | U45: 8 | V45: 1 | W45: Nominated | X45: {=IFERROR(INDEX(Ratings!$E$5:$E$500,MATCH(A45,Ratings!$A$5:$A$500,0)),"")} | Y45: {=IFERROR(INDEX(Ratings!$G$5:$G$500,MATCH(A45,Ratings!$A$5:$A$500,0)),"")} | Z45: {=IFERROR(INDEX(Ratings!$I$5:$I$500,MATCH(A45,Ratings!$A$5:$A$500,0)),"")} | AB45: 12A
A46: F0042 | B46: The Batman | C46: 2022 | D46: 4K UHD | E46: The Batman | I46: In his second year of fighting crime, Batman uncovers corruption in Gotham City that connects to his own family while facing a serial killer known as the Riddler. | J46: Matt Reeves | K46: 177 | L46: Crime, Mystery, Thriller | M46: 6th & Idaho, Dylan Clark Productions, DC Films | N46: https://huggingface.co/datasets/HenryWaltson/TMDB-IMDB-Movies-Dataset | O46: https://huggingface.co/datasets/HenryWaltson/TMDB-IMDB-Movies-Dataset | P46: Robert Pattinson | Q46: Zoë Kravitz | R46: Jeffrey Wright | S46: Colin Farrell | T46: Paul Dano | U46: 3 | V46: 0 | X46: {=IFERROR(INDEX(Ratings!$E$5:$E$500,MATCH(A46,Ratings!$A$5:$A$500,0)),"")} | Y46: {=IFERROR(INDEX(Ratings!$G$5:$G$500,MATCH(A46,Ratings!$A$5:$A$500,0)),"")} | Z46: {=IFERROR(INDEX(Ratings!$I$5:$I$500,MATCH(A46,Ratings!$A$5:$A$500,0)),"")} | AB46: 15
A47: F0043 | B47: Batman Begins | C47: 2005 | D47: Blu-ray | E47: The Dark Knight Trilogy | I47: Driven by tragedy, billionaire Bruce Wayne dedicates his life to uncovering and defeating the corruption that plagues his home, Gotham City. Unable to work within the system, he instead creates a new identity, a symbol of fear for the criminal underworld - The Batman. | J47: Christopher Nolan | K47: 140 | L47: Action, Crime, Drama | M47: Warner Bros. Pictures, DC Comics, Syncopy | N47: https://huggingface.co/datasets/HenryWaltson/TMDB-IMDB-Movies-Dataset | O47: https://huggingface.co/datasets/HenryWaltson/TMDB-IMDB-Movies-Dataset | P47: Christian Bale | Q47: Michael Caine | R47: Liam Neeson | S47: Katie Holmes | T47: Gary Oldman | U47: 1 | V47: 0 | X47: {=IFERROR(INDEX(Ratings!$E$5:$E$500,MATCH(A47,Ratings!$A$5:$A$500,0)),"")} | Y47: {=IFERROR(INDEX(Ratings!$G$5:$G$500,MATCH(A47,Ratings!$A$5:$A$500,0)),"")} | Z47: {=IFERROR(INDEX(Ratings!$I$5:$I$500,MATCH(A47,Ratings!$A$5:$A$500,0)),"")} | AB47: 12A
A48: F0044 | B48: The Dark Knight | C48: 2008 | D48: Blu-ray | E48: The Dark Knight Trilogy | I48: Batman raises the stakes in his war on crime. With the help of Lt. Jim Gordon and District Attorney Harvey Dent, Batman sets out to dismantle the remaining criminal organizations that plague the streets. The partnership proves to be effective, but they soon find themselves prey to a reign of chaos unleashed by a rising criminal mastermind known to the terrified citizens of Gotham as the Joker. | J48: Christopher Nolan | K48: 152 | L48: Drama, Action, Crime, Thriller | M48: DC Comics, Legendary Pictures, Syncopy | N48: https://huggingface.co/datasets/HenryWaltson/TMDB-IMDB-Movies-Dataset | O48: https://huggingface.co/datasets/HenryWaltson/TMDB-IMDB-Movies-Dataset | P48: Christian Bale | Q48: Heath Ledger | R48: Aaron Eckhart | S48: Michael Caine | T48: Maggie Gyllenhaal | U48: 8 | V48: 2 | X48: {=IFERROR(INDEX(Ratings!$E$5:$E$500,MATCH(A48,Ratings!$A$5:$A$500,0)),"")} | Y48: {=IFERROR(INDEX(Ratings!$G$5:$G$500,MATCH(A48,Ratings!$A$5:$A$500,0)),"")} | Z48: {=IFERROR(INDEX(Ratings!$I$5:$I$500,MATCH(A48,Ratings!$A$5:$A$500,0)),"")} | AB48: 12A
A49: F0045 | B49: The Dark Knight Rises | C49: 2012 | D49: Blu-ray | E49: The Dark Knight Trilogy | I49: Following the death of District Attorney Harvey Dent, Batman assumes responsibility for Dent's crimes to protect the late attorney's reputation and is subsequently hunted by the Gotham City Police Department. Eight years later, Batman encounters the mysterious Selina Kyle and the villainous Bane, a new terrorist leader who overwhelms Gotham's finest. The Dark Knight resurfaces to protect a city that has branded him an enemy. | J49: Christopher Nolan | K49: 165 | L49: Action, Crime, Drama, Thriller | M49: Syncopy, Legendary Pictures, DC Entertainment | N49: https://huggingface.co/datasets/HenryWaltson/TMDB-IMDB-Movies-Dataset | O49: https://huggingface.co/datasets/HenryWaltson/TMDB-IMDB-Movies-Dataset | P49: Christian Bale | Q49: Gary Oldman | R49: Tom Hardy | S49: Joseph Gordon-Levitt | T49: Anne Hathaway | U49: 0 | V49: 0 | X49: {=IFERROR(INDEX(Ratings!$E$5:$E$500,MATCH(A49,Ratings!$A$5:$A$500,0)),"")} | Y49: {=IFERROR(INDEX(Ratings!$G$5:$G$500,MATCH(A49,Ratings!$A$5:$A$500,0)),"")} | Z49: {=IFERROR(INDEX(Ratings!$I$5:$I$500,MATCH(A49,Ratings!$A$5:$A$500,0)),"")} | AB49: 12A
A50: F0046 | B50: Battle: Los Angeles | C50: 2011 | D50: Blu-ray | I50: When once distant UFOs become a terrifying threat and an alien invasion force begins attacking Earths major costal and riverside cities, a U.S Marine staff sergeant and his team are sent into battle only to find they must take it upon themselves to defeat an unknown enemy and protect what remains of Los Angeles. | J50: Jonathan Liebesman | K50: 116 | L50: Science Fiction, Action | M50: Columbia Pictures, Relativity Media, Original Film | N50: https://huggingface.co/datasets/HenryWaltson/TMDB-IMDB-Movies-Dataset | O50: https://huggingface.co/datasets/HenryWaltson/TMDB-IMDB-Movies-Dataset | P50: Aaron Eckhart | Q50: Ramón Rodríguez | R50: Will Rothhaar | S50: Michael Peña | T50: Bridget Moynahan | U50: 0 | V50: 0 | X50: {=IFERROR(INDEX(Ratings!$E$5:$E$500,MATCH(A50,Ratings!$A$5:$A$500,0)),"")} | Y50: {=IFERROR(INDEX(Ratings!$G$5:$G$500,MATCH(A50,Ratings!$A$5:$A$500,0)),"")} | Z50: {=IFERROR(INDEX(Ratings!$I$5:$I$500,MATCH(A50,Ratings!$A$5:$A$500,0)),"")} | AB50: 12A
A51: F0047 | B51: The BFG | C51: 2016 | D51: Blu-ray | I51: Best guess: 2016 Spielberg film. | J51: Steven Spielberg | K51: 117 | L51: Adventure, Family, Fantasy | M51: Walt Disney Pictures, Amblin Entertainment, Reliance Entertainment | N51: https://huggingface.co/datasets/HenryWaltson/TMDB-IMDB-Movies-Dataset | O51: https://huggingface.co/datasets/HenryWaltson/TMDB-IMDB-Movies-Dataset | P51: Mark Rylance | Q51: Ruby Barnhill | R51: Rebecca Hall | S51: Jemaine Clement | T51: Bill Hader | U51: 0 | V51: 0 | X51: {=IFERROR(INDEX(Ratings!$E$5:$E$500,MATCH(A51,Ratings!$A$5:$A$500,0)),"")} | Y51: {=IFERROR(INDEX(Ratings!$G$5:$G$500,MATCH(A51,Ratings!$A$5:$A$500,0)),"")} | Z51: {=IFERROR(INDEX(Ratings!$I$5:$I$500,MATCH(A51,Ratings!$A$5:$A$500,0)),"")} | AB51: PG
A52: F0048 | B52: Big Hero 6 | C52: 2014 | D52: Blu-ray | I52: A special bond develops between plus-sized inflatable robot Baymax, and prodigy Hiro Hamada, who team up with a group of friends to form a band of high-tech heroes. | J52: Don Hall, Chris Williams | K52: 102 | L52: Adventure, Family, Animation, Action, Comedy | M52: Walt Disney Pictures, Walt Disney Animation Studios | N52: https://huggingface.co/datasets/HenryWaltson/TMDB-IMDB-Movies-Dataset | O52: https://huggingface.co/datasets/HenryWaltson/TMDB-IMDB-Movies-Dataset | P52: Scott Adsit | Q52: Ryan Potter | R52: Daniel Henney | S52: T.J. Miller | T52: Jamie Chung | U52: 1 | V52: 1 | X52: {=IFERROR(INDEX(Ratings!$E$5:$E$500,MATCH(A52,Ratings!$A$5:$A$500,0)),"")} | Y52: {=IFERROR(INDEX(Ratings!$G$5:$G$500,MATCH(A52,Ratings!$A$5:$A$500,0)),"")} | Z52: {=IFERROR(INDEX(Ratings!$I$5:$I$500,MATCH(A52,Ratings!$A$5:$A$500,0)),"")} | AB52: PG
A53: F0049 | B53: The Big Lebowski | C53: 1998 | D53: Blu-ray | I53: Jeffrey 'The Dude' Lebowski, a Los Angeles slacker who only wants to bowl and drink White Russians, is mistaken for another Jeffrey Lebowski, a wheelchair-bound millionaire, and finds himself dragged into a strange series of events involving nihilists, adult film producers, ferrets, errant toes, and large sums of money. | J53: Joel Coen, Ethan Coen | K53: 117 | L53: Comedy, Crime | M53: Gramercy Pictures, PolyGram Filmed Entertainment, Working Title Films | N53: https://huggingface.co/datasets/HenryWaltson/TMDB-IMDB-Movies-Dataset | O53: https://huggingface.co/datasets/HenryWaltson/TMDB-IMDB-Movies-Dataset | P53: Jeff Bridges | Q53: John Goodman | R53: Julianne Moore | S53: Steve Buscemi | T53: David Huddleston | U53: 0 | V53: 0 | X53: {=IFERROR(INDEX(Ratings!$E$5:$E$500,MATCH(A53,Ratings!$A$5:$A$500,0)),"")} | Y53: {=IFERROR(INDEX(Ratings!$G$5:$G$500,MATCH(A53,Ratings!$A$5:$A$500,0)),"")} | Z53: {=IFERROR(INDEX(Ratings!$I$5:$I$500,MATCH(A53,Ratings!$A$5:$A$500,0)),"")} | AB53: 18
A54: F0050 | B54: Black Hawk Down | C54: 2001 | D54: Blu-ray | I54: When U.S. Rangers and an elite Delta Force team attempt to kidnap two underlings of a Somali warlord, their Black Hawk helicopters are shot down, and the Americans suffer heavy casualties, facing intense fighting from the militia on the ground. | J54: Ridley Scott | K54: 145 | L54: Action, History, War | M54: Jerry Bruckheimer Films, Revolution Studios, Scott Free Productions | N54: https://huggingface.co/datasets/HenryWaltson/TMDB-IMDB-Movies-Dataset | O54: https://huggingface.co/datasets/HenryWaltson/TMDB-IMDB-Movies-Dataset | P54: Josh Hartnett | Q54: Eric Bana | R54: Ewan McGregor | S54: Tom Sizemore | T54: William Fichtner | U54: 4 | V54: 2 | X54: {=IFERROR(INDEX(Ratings!$E$5:$E$500,MATCH(A54,Ratings!$A$5:$A$500,0)),"")} | Y54: {=IFERROR(INDEX(Ratings!$G$5:$G$500,MATCH(A54,Ratings!$A$5:$A$500,0)),"")} | Z54: {=IFERROR(INDEX(Ratings!$I$5:$I$500,MATCH(A54,Ratings!$A$5:$A$500,0)),"")} | AB54: 15
A55: F0051 | B55: Body of Lies | C55: 2008 | D55: Blu-ray | I55: The CIA’s hunt is on for the mastermind of a wave of terrorist attacks. Roger Ferris is the agency’s man on the ground, moving from place to place, scrambling to stay ahead of ever-shifting events. An eye in the sky – a satellite link – watches Ferris. At the other end of that real-time link is the CIA’s Ed Hoffman, strategizing events from thousands of miles away. And as Ferris nears the target, he discovers trust can be just as dangerous as it is necessary for survival. | J55: Ridley Scott | K55: 128 | L55: Action, Drama, Thriller | M55: Scott Free Productions, De Line Pictures, Warner Bros. Pictures | N55: https://huggingface.co/datasets/HenryWaltson/TMDB-IMDB-Movies-Dataset | O55: https://huggingface.co/datasets/HenryWaltson/TMDB-IMDB-Movies-Dataset | P55: Leonardo DiCaprio | Q55: Russell Crowe | R55: Mark Strong | S55: Ali Suliman | T55: Simon McBurney | U55: 0 | V55: 0 | X55: {=IFERROR(INDEX(Ratings!$E$5:$E$500,MATCH(A55,Ratings!$A$5:$A$500,0)),"")} | Y55: {=IFERROR(INDEX(Ratings!$G$5:$G$500,MATCH(A55,Ratings!$A$5:$A$500,0)),"")} | Z55: {=IFERROR(INDEX(Ratings!$I$5:$I$500,MATCH(A55,Ratings!$A$5:$A$500,0)),"")} | AB55: 15
A56: F0052 | B56: Bohemian Rhapsody | C56: 2018 | D56: Blu-ray | I56: Singer Freddie Mercury, guitarist Brian May, drummer Roger Taylor and bass guitarist John Deacon take the music world by storm when they form the rock 'n' roll band Queen in 1970. Hit songs become instant classics. When Mercury's increasingly wild lifestyle starts to spiral out of control, Queen soon faces its greatest challenge yet – finding a way to keep the band together amid the success and excess. | J56: Bryan Singer | K56: 135 | L56: Music, Drama | M56: 20th Century Fox, New Regency Pictures, GK Films | N56: https://huggingface.co/datasets/HenryWaltson/TMDB-IMDB-Movies-Dataset | O56: https://huggingface.co/datasets/HenryWaltson/TMDB-IMDB-Movies-Dataset | P56: Rami Malek | Q56: Gwilym Lee | R56: Ben Hardy | S56: Joseph Mazzello | T56: Lucy Boynton | U56: 5 | V56: 4 | W56: Nominated | X56: {=IFERROR(INDEX(Ratings!$E$5:$E$500,MATCH(A56,Ratings!$A$5:$A$500,0)),"")} | Y56: {=IFERROR(INDEX(Ratings!$G$5:$G$500,MATCH(A56,Ratings!$A$5:$A$500,0)),"")} | Z56: {=IFERROR(INDEX(Ratings!$I$5:$I$500,MATCH(A56,Ratings!$A$5:$A$500,0)),"")} | AB56: 12A
A57: F0053 | B57: The Bourne Identity | C57: 2002 | D57: Blu-ray | E57: Bourne | G57: Yes | H57: ⭐⭐⭐ | I57: Wounded to the brink of death and suffering from amnesia, Jason Bourne is rescued at sea by a fisherman. With nothing to go on but a Swiss bank account number, he starts to reconstruct his life, but finds that many people he encounters want him dead. However, Bourne realizes that he has the combat and mental skills of a world-class spy—but who does he work for? | J57: Doug Liman | K57: 119 | L57: Action, Drama, Mystery, Thriller | M57: Universal Pictures, Hypnotic, Kalima Productions | N57: https://huggingface.co/datasets/HenryWaltson/TMDB-IMDB-Movies-Dataset | O57: https://huggingface.co/datasets/HenryWaltson/TMDB-IMDB-Movies-Dataset | P57: Matt Damon | Q57: Franka Potente | R57: Chris Cooper | S57: Clive Owen | T57: Brian Cox | U57: 0 | V57: 0 | X57: {=IFERROR(INDEX(Ratings!$E$5:$E$500,MATCH(A57,Ratings!$A$5:$A$500,0)),"")} | Y57: {=IFERROR(INDEX(Ratings!$G$5:$G$500,MATCH(A57,Ratings!$A$5:$A$500,0)),"")} | Z57: {=IFERROR(INDEX(Ratings!$I$5:$I$500,MATCH(A57,Ratings!$A$5:$A$500,0)),"")} | AA57: 2026-08-21 | AB57: 12A
A58: F0054 | B58: The Bourne Supremacy | C58: 2004 | D58: Blu-ray | E58: Bourne | G58: Yes | H58: ⭐⭐⭐⭐ | I58: A CIA operation to purchase classified Russian documents is blown by a rival agent, who then shows up in the sleepy seaside village where Bourne and Marie have been living. The pair run for their lives and Bourne, who promised retaliation should anyone from his former life attempt contact, is forced to once again take up his life as a trained assassin to survive. | J58: Paul Greengrass | K58: 108 | L58: Action, Drama, Thriller | M58: Universal Pictures, The Kennedy/Marshall Company, Hypnotic | N58: https://huggingface.co/datasets/HenryWaltson/TMDB-IMDB-Movies-Dataset | O58: https://huggingface.co/datasets/HenryWaltson/TMDB-IMDB-Movies-Dataset | P58: Matt Damon | Q58: Franka Potente | R58: Brian Cox | S58: Julia Stiles | T58: Karl Urban | U58: 0 | V58: 0 | X58: {=IFERROR(INDEX(Ratings!$E$5:$E$500,MATCH(A58,Ratings!$A$5:$A$500,0)),"")} | Y58: {=IFERROR(INDEX(Ratings!$G$5:$G$500,MATCH(A58,Ratings!$A$5:$A$500,0)),"")} | Z58: {=IFERROR(INDEX(Ratings!$I$5:$I$500,MATCH(A58,Ratings!$A$5:$A$500,0)),"")} | AA58: 2026-09-13 | AB58: 12A
A59: F0055 | B59: The Bourne Ultimatum | C59: 2007 | D59: Blu-ray | E59: Bourne | G59: Yes | H59: ⭐⭐⭐⭐ | I59: Bourne is brought out of hiding once again by reporter Simon Ross who is trying to unveil Operation Blackbriar, an upgrade to Project Treadstone, in a series of newspaper columns. Information from the reporter stirs a new set of memories, and Bourne must finally uncover his dark past while dodging The Company's best efforts to eradicate him. | J59: Paul Greengrass | K59: 115 | L59: Action, Drama, Mystery, Thriller | M59: Universal Pictures, The Kennedy/Marshall Company, Ludlum Entertainment | N59: https://huggingface.co/datasets/HenryWaltson/TMDB-IMDB-Movies-Dataset | O59: https://huggingface.co/datasets/HenryWaltson/TMDB-IMDB-Movies-Dataset | P59: Matt Damon | Q59: Julia Stiles | R59: David Strathairn | S59: Scott Glenn | T59: Paddy Considine | U59: 3 | V59: 3 | X59: {=IFERROR(INDEX(Ratings!$E$5:$E$500,MATCH(A59,Ratings!$A$5:$A$500,0)),"")} | Y59: {=IFERROR(INDEX(Ratings!$G$5:$G$500,MATCH(A59,Ratings!$A$5:$A$500,0)),"")} | Z59: {=IFERROR(INDEX(Ratings!$I$5:$I$500,MATCH(A59,Ratings!$A$5:$A$500,0)),"")} | AA59: 2026-09-14 | AB59: 12A
A60: F0056 | B60: The Bourne Legacy | C60: 2012 | D60: Blu-ray | E60: Bourne | G60: Yes | H60: ⭐⭐⭐ | I60: New CIA operative Aaron Cross experiences life-or-death stakes that have been triggered by the previous actions of Jason Bourne. | J60: Tony Gilroy | K60: 135 | L60: Action, Thriller | M60: Universal Pictures, Relativity Media, Captivate Entertainment | N60: https://huggingface.co/datasets/HenryWaltson/TMDB-IMDB-Movies-Dataset | O60: https://huggingface.co/datasets/HenryWaltson/TMDB-IMDB-Movies-Dataset | P60: Jeremy Renner | Q60: Rachel Weisz | R60: Edward Norton | S60: Stacy Keach | T60: Dennis Boutsikaris | U60: 0 | V60: 0 | X60: {=IFERROR(INDEX(Ratings!$E$5:$E$500,MATCH(A60,Ratings!$A$5:$A$500,0)),"")} | Y60: {=IFERROR(INDEX(Ratings!$G$5:$G$500,MATCH(A60,Ratings!$A$5:$A$500,0)),"")} | Z60: {=IFERROR(INDEX(Ratings!$I$5:$I$500,MATCH(A60,Ratings!$A$5:$A$500,0)),"")} | AA60: 2026-09-14 | AB60: 12A
A61: F0057 | B61: The Breakfast Club | C61: 1985 | D61: Blu-ray | I61: Five high school students from different walks of life endure a Saturday detention under a power-hungry principal. The disparate group includes rebel John, princess Claire, outcast Allison, brainy Brian and Andrew, the jock. Each has a chance to tell his or her story, making the others see them a little differently -- and when the day ends, they question whether school will ever be the same. | J61: John Hughes | K61: 98 | L61: Comedy, Drama | M61: Universal Pictures, A&M Films, Channel Productions | N61: https://huggingface.co/datasets/HenryWaltson/TMDB-IMDB-Movies-Dataset | O61: https://huggingface.co/datasets/HenryWaltson/TMDB-IMDB-Movies-Dataset | P61: Emilio Estevez | Q61: Judd Nelson | R61: Molly Ringwald | S61: Anthony Michael Hall | T61: Ally Sheedy | U61: 0 | V61: 0 | X61: {=IFERROR(INDEX(Ratings!$E$5:$E$500,MATCH(A61,Ratings!$A$5:$A$500,0)),"")} | Y61: {=IFERROR(INDEX(Ratings!$G$5:$G$500,MATCH(A61,Ratings!$A$5:$A$500,0)),"")} | Z61: {=IFERROR(INDEX(Ratings!$I$5:$I$500,MATCH(A61,Ratings!$A$5:$A$500,0)),"")} | AB61: 15
A62: F0058 | B62: Bridesmaids | C62: 2011 | D62: Blu-ray | I62: Annie's life is a mess. But when she finds out her lifetime best friend is engaged, she simply must serve as Lillian's maid of honor. Though lovelorn and broke, Annie bluffs her way through the expensive and bizarre rituals. With one chance to get it perfect, she’ll show Lillian and her bridesmaids just how far you’ll go for someone you love. | J62: Paul Feig | K62: 125 | L62: Comedy, Romance | M62: Apatow Productions, Relativity Media | N62: https://huggingface.co/datasets/HenryWaltson/TMDB-IMDB-Movies-Dataset | O62: https://huggingface.co/datasets/HenryWaltson/TMDB-IMDB-Movies-Dataset | P62: Kristen Wiig | Q62: Maya Rudolph | R62: Rose Byrne | S62: Chris O'Dowd | T62: Wendi McLendon-Covey | U62: 2 | V62: 0 | X62: {=IFERROR(INDEX(Ratings!$E$5:$E$500,MATCH(A62,Ratings!$A$5:$A$500,0)),"")} | Y62: {=IFERROR(INDEX(Ratings!$G$5:$G$500,MATCH(A62,Ratings!$A$5:$A$500,0)),"")} | Z62: {=IFERROR(INDEX(Ratings!$I$5:$I$500,MATCH(A62,Ratings!$A$5:$A$500,0)),"")} | AB62: 15
A63: F0059 | B63: Brüno | C63: 2009 | D63: Blu-ray | I63: Flamboyantly gay Austrian television reporter Bruno stirs up trouble with unsuspecting guests and large crowds through brutally frank interviews and painfully hilarious public displays of homosexuality. | J63: Larry Charles | K63: 83 | L63: Comedy | M63: Universal Pictures, MRC, Four by Two | N63: https://huggingface.co/datasets/HenryWaltson/TMDB-IMDB-Movies-Dataset | O63: https://huggingface.co/datasets/HenryWaltson/TMDB-IMDB-Movies-Dataset | P63: Sacha Baron Cohen | Q63: Gustaf Hammarsten | R63: Clifford Bañagale | S63: Josh Meyers | T63: Robert Huerta | U63: 0 | V63: 0 | X63: {=IFERROR(INDEX(Ratings!$E$5:$E$500,MATCH(A63,Ratings!$A$5:$A$500,0)),"")} | Y63: {=IFERROR(INDEX(Ratings!$G$5:$G$500,MATCH(A63,Ratings!$A$5:$A$500,0)),"")} | Z63: {=IFERROR(INDEX(Ratings!$I$5:$I$500,MATCH(A63,Ratings!$A$5:$A$500,0)),"")} | AB63: 18
A64: F0060 | B64: The Bucket List | C64: 2007 | D64: Blu-ray | I64: Corporate billionaire Edward Cole and working class mechanic Carter Chambers are worlds apart. At a crossroads in their lives, they share a hospital room and discover they have two things in common: a desire to spend the time they have left doing everything they ever wanted to do and an unrealized need to come to terms with who they are. Together they embark on the road trip of a lifetime, becoming friends along the way and learning to live life to the fullest, with insight and humor. | J64: Rob Reiner | K64: 97 | L64: Drama, Comedy | M64: Two Ton Films, Zadan / Meron Productions, Reiner / Greisman Productions | N64: https://huggingface.co/datasets/HenryWaltson/TMDB-IMDB-Movies-Dataset | O64: https://huggingface.co/datasets/HenryWaltson/TMDB-IMDB-Movies-Dataset | P64: Jack Nicholson | Q64: Morgan Freeman | R64: Sean Hayes | S64: Beverly Todd | T64: Alfonso Freeman | U64: 0 | V64: 0 | X64: {=IFERROR(INDEX(Ratings!$E$5:$E$500,MATCH(A64,Ratings!$A$5:$A$500,0)),"")} | Y64: {=IFERROR(INDEX(Ratings!$G$5:$G$500,MATCH(A64,Ratings!$A$5:$A$500,0)),"")} | Z64: {=IFERROR(INDEX(Ratings!$I$5:$I$500,MATCH(A64,Ratings!$A$5:$A$500,0)),"")} | AB64: 12A
A65: F0061 | B65: Bumblebee | C65: 2018 | D65: Blu-ray | E65: Transformers | G65: Yes | H65: ⭐⭐⭐⭐ | I65: On the run in the year 1987, Bumblebee finds refuge in a junkyard in a small Californian beach town. Charlie, on the cusp of turning 18 and trying to find her place in the world, discovers Bumblebee, battle-scarred and broken. When Charlie revives him, she quickly learns this is no ordinary yellow VW bug. | J65: Travis Knight | K65: 113 | L65: Action, Adventure, Science Fiction | M65: Paramount, Allspark Pictures, Bay Films | N65: https://huggingface.co/datasets/HenryWaltson/TMDB-IMDB-Movies-Dataset | O65: https://huggingface.co/datasets/HenryWaltson/TMDB-IMDB-Movies-Dataset | P65: Hailee Steinfeld | Q65: John Cena | R65: Jorge Lendeborg Jr. | S65: John Ortiz | T65: Jason Ian Drucker | U65: 0 | V65: 0 | X65: {=IFERROR(INDEX(Ratings!$E$5:$E$500,MATCH(A65,Ratings!$A$5:$A$500,0)),"")} | Y65: {=IFERROR(INDEX(Ratings!$G$5:$G$500,MATCH(A65,Ratings!$A$5:$A$500,0)),"")} | Z65: {=IFERROR(INDEX(Ratings!$I$5:$I$500,MATCH(A65,Ratings!$A$5:$A$500,0)),"")} | AA65: 2026-09-14 | AB65: 12A
A66: F0062 | B66: Captain Phillips | C66: 2013 | D66: Blu-ray | I66: The true story of Captain Richard Phillips and the 2009 hijacking by Somali pirates of the US-flagged MV Maersk Alabama, the first American cargo ship to be hijacked in two hundred years. | J66: Paul Greengrass | K66: 134 | L66: Action, Drama, Thriller | M66: Columbia Pictures, Michael De Luca Productions, Scott Rudin Productions | N66: https://huggingface.co/datasets/HenryWaltson/TMDB-IMDB-Movies-Dataset | O66: https://huggingface.co/datasets/HenryWaltson/TMDB-IMDB-Movies-Dataset | P66: Tom Hanks | Q66: Barkhad Abdi | R66: Barkhad Abdirahman | S66: Faysal Ahmed | T66: Mahat M. Ali | U66: 6 | V66: 0 | W66: Nominated | X66: {=IFERROR(INDEX(Ratings!$E$5:$E$500,MATCH(A66,Ratings!$A$5:$A$500,0)),"")} | Y66: {=IFERROR(INDEX(Ratings!$G$5:$G$500,MATCH(A66,Ratings!$A$5:$A$500,0)),"")} | Z66: {=IFERROR(INDEX(Ratings!$I$5:$I$500,MATCH(A66,Ratings!$A$5:$A$500,0)),"")} | AB66: 12A
A67: F0063 | B67: Catch.44 | C67: 2011 | D67: Blu-ray | I67: The lives of three female assassins take a sudden turn when their charming boss lures them into one last job. They soon find themselves thrust into a bizarre situation involving a psychotic hit man, a grizzled trucker and a delusional line cook. | J67: Aaron Harvey | K67: 93 | L67: Drama, Action, Thriller | M67: Sakonnet Capital Partners, EFO Films, Benaroya Pictures | N67: https://huggingface.co/datasets/HenryWaltson/TMDB-IMDB-Movies-Dataset | O67: https://huggingface.co/datasets/HenryWaltson/TMDB-IMDB-Movies-Dataset | P67: Bruce Willis | Q67: Malin Åkerman | R67: Nikki Reed | S67: Deborah Ann Woll | T67: Forest Whitaker | U67: 0 | V67: 0 | X67: {=IFERROR(INDEX(Ratings!$E$5:$E$500,MATCH(A67,Ratings!$A$5:$A$500,0)),"")} | Y67: {=IFERROR(INDEX(Ratings!$G$5:$G$500,MATCH(A67,Ratings!$A$5:$A$500,0)),"")} | Z67: {=IFERROR(INDEX(Ratings!$I$5:$I$500,MATCH(A67,Ratings!$A$5:$A$500,0)),"")} | AB67: 15
A68: F0064 | B68: Catch Me If You Can | C68: 2002 | D68: Blu-ray | I68: A true story about Frank Abagnale Jr. who, before his 19th birthday, successfully conned millions of dollars worth of checks as a Pan Am pilot, doctor, and legal prosecutor. An FBI agent makes it his mission to put him behind bars. But Frank not only eludes capture, he revels in the pursuit. | J68: Steven Spielberg | K68: 141 | L68: Drama, Crime | M68: Parkes/MacDonald Productions, Kemp Company, Splendid Pictures | N68: https://huggingface.co/datasets/HenryWaltson/TMDB-IMDB-Movies-Dataset | O68: https://huggingface.co/datasets/HenryWaltson/TMDB-IMDB-Movies-Dataset | P68: Leonardo DiCaprio | Q68: Tom Hanks | R68: Christopher Walken | S68: Martin Sheen | T68: Nathalie Baye | U68: 2 | V68: 0 | X68: {=IFERROR(INDEX(Ratings!$E$5:$E$500,MATCH(A68,Ratings!$A$5:$A$500,0)),"")} | Y68: {=IFERROR(INDEX(Ratings!$G$5:$G$500,MATCH(A68,Ratings!$A$5:$A$500,0)),"")} | Z68: {=IFERROR(INDEX(Ratings!$I$5:$I$500,MATCH(A68,Ratings!$A$5:$A$500,0)),"")} | AB68: 12A
A69: F0065 | B69: Chef | C69: 2014 | D69: Blu-ray | G69: Yes | H69: ⭐⭐⭐⭐⭐ | I69: When Chef Carl Casper suddenly quits his job at a prominent Los Angeles restaurant after refusing to compromise his creative integrity for its controlling owner, he is left to figure out what's next. Finding himself in Miami, he teams up with his ex-wife, his friend and his son to launch a food truck. Taking to the road, Chef Carl goes back to his roots to reignite his passion for the kitchen -- and zest for life and love. | J69: Jon Favreau | K69: 114 | L69: Comedy | M69: Altus Media, Fairview Entertainment, Prescience | N69: https://huggingface.co/datasets/HenryWaltson/TMDB-IMDB-Movies-Dataset | O69: https://huggingface.co/datasets/HenryWaltson/TMDB-IMDB-Movies-Dataset | P69: Jon Favreau | Q69: John Leguizamo | R69: Bobby Cannavale | S69: Emjay Anthony | T69: Scarlett Johansson | U69: 0 | V69: 0 | X69: {=IFERROR(INDEX(Ratings!$E$5:$E$500,MATCH(A69,Ratings!$A$5:$A$500,0)),"")} | Y69: {=IFERROR(INDEX(Ratings!$G$5:$G$500,MATCH(A69,Ratings!$A$5:$A$500,0)),"")} | Z69: {=IFERROR(INDEX(Ratings!$I$5:$I$500,MATCH(A69,Ratings!$A$5:$A$500,0)),"")} | AA69: 2026-08-18 | AB69: 15
A70: F0066 | B70: Clash of the Titans | C70: 2010 | D70: Blu-ray | I70: Best guess: 2010 remake. | J70: Louis Leterrier | K70: 106 | L70: Adventure, Fantasy, Action | M70: The Zanuck Company, Legendary Pictures, Thunder Road | N70: https://huggingface.co/datasets/HenryWaltson/TMDB-IMDB-Movies-Dataset | O70: https://huggingface.co/datasets/HenryWaltson/TMDB-IMDB-Movies-Dataset | P70: Sam Worthington | Q70: Gemma Arterton | R70: Mads Mikkelsen | S70: Alexa Davalos | T70: Jason Flemyng | U70: 0 | V70: 0 | X70: {=IFERROR(INDEX(Ratings!$E$5:$E$500,MATCH(A70,Ratings!$A$5:$A$500,0)),"")} | Y70: {=IFERROR(INDEX(Ratings!$G$5:$G$500,MATCH(A70,Ratings!$A$5:$A$500,0)),"")} | Z70: {=IFERROR(INDEX(Ratings!$I$5:$I$500,MATCH(A70,Ratings!$A$5:$A$500,0)),"")} | AB70: 12A
A71: F0067 | B71: Cloudy with a Chance of Meatballs 2 | C71: 2013 | D71: Blu-ray | E71: Cloudy with a Chance of Meatballs | I71: After the disastrous food storm in the first film, Flint and his friends are forced to leave the town. Flint accepts the invitation from his idol Chester V to join The Live Corp Company, which has been tasked to clean the island, and where the best inventors in the world create technologies for the betterment of mankind. When Flint discovers that his machine still operates and now creates mutant food beasts like living pickles, hungry tacodiles, shrimpanzees and apple pie-thons, he and his friends must return to save the world. | J71: Cody Cameron, Kris Pearn | K71: 95 | L71: Animation, Family, Comedy | M71: Columbia Pictures, Sony Pictures Animation | N71: https://huggingface.co/datasets/HenryWaltson/TMDB-IMDB-Movies-Dataset | O71: https://huggingface.co/datasets/HenryWaltson/TMDB-IMDB-Movies-Dataset | P71: Bill Hader | Q71: Anna Faris | R71: James Caan | S71: Will Forte | T71: Andy Samberg | U71: 0 | V71: 0 | X71: {=IFERROR(INDEX(Ratings!$E$5:$E$500,MATCH(A71,Ratings!$A$5:$A$500,0)),"")} | Y71: {=IFERROR(INDEX(Ratings!$G$5:$G$500,MATCH(A71,Ratings!$A$5:$A$500,0)),"")} | Z71: {=IFERROR(INDEX(Ratings!$I$5:$I$500,MATCH(A71,Ratings!$A$5:$A$500,0)),"")} | AB71: U
A72: F0068 | B72: Con Air | C72: 1997 | D72: Blu-ray | I72: Newly-paroled former US Army ranger Cameron Poe is headed back to his wife, but must fly home aboard a prison transport flight dubbed "Jailbird" taking the “worst of the worst” prisoners, a group described as “pure predators”, to a new super-prison. Poe faces impossible odds when the transport plane is skyjacked mid-flight by the most vicious criminals in the country led by the mastermind — genius serial killer Cyrus "The Virus" Grissom, and backed by black militant Diamond Dog and psychopath Billy Bedlam. | J72: Simon West | K72: 116 | L72: Action, Thriller, Crime | M72: Touchstone Pictures, Jerry Bruckheimer Films | N72: https://huggingface.co/datasets/HenryWaltson/TMDB-IMDB-Movies-Dataset | O72: https://huggingface.co/datasets/HenryWaltson/TMDB-IMDB-Movies-Dataset | P72: Nicolas Cage | Q72: John Cusack | R72: John Malkovich | S72: Ving Rhames | T72: Mykelti Williamson | U72: 2 | V72: 0 | X72: {=IFERROR(INDEX(Ratings!$E$5:$E$500,MATCH(A72,Ratings!$A$5:$A$500,0)),"")} | Y72: {=IFERROR(INDEX(Ratings!$G$5:$G$500,MATCH(A72,Ratings!$A$5:$A$500,0)),"")} | Z72: {=IFERROR(INDEX(Ratings!$I$5:$I$500,MATCH(A72,Ratings!$A$5:$A$500,0)),"")} | AB72: 15
A73: F0069 | B73: Cop Out | C73: 2010 | D73: Blu-ray | I73: Detectives Jimmy and Paul, despite nine years as partners, can still sometimes seem like polar opposites—especially when Paul's unpredictable antics get them suspended without pay. Already strapped for cash and trying to pay for his daughter's wedding, Jimmy decides to sell a rare baseball card that's worth tens of thousands. Unfortunately, when the collector's shop is robbed and the card vanishes with the crook, Paul and Jimmy end up going rogue, tracking down the card and the drug ring behind its theft, all on their own time and without any backup—except for each other. | J73: Kevin Smith | K73: 107 | L73: Action, Comedy, Crime | M73: Marc Platt Productions | N73: https://huggingface.co/datasets/HenryWaltson/TMDB-IMDB-Movies-Dataset | O73: https://huggingface.co/datasets/HenryWaltson/TMDB-IMDB-Movies-Dataset | P73: Bruce Willis | Q73: Tracy Morgan | R73: Seann William Scott | S73: Ana de la Reguera | T73: Adam Brody | U73: 0 | V73: 0 | X73: {=IFERROR(INDEX(Ratings!$E$5:$E$500,MATCH(A73,Ratings!$A$5:$A$500,0)),"")} | Y73: {=IFERROR(INDEX(Ratings!$G$5:$G$500,MATCH(A73,Ratings!$A$5:$A$500,0)),"")} | Z73: {=IFERROR(INDEX(Ratings!$I$5:$I$500,MATCH(A73,Ratings!$A$5:$A$500,0)),"")} | AB73: 15
A74: F0070 | B74: Shaun of the Dead | C74: 2004 | D74: Blu-ray | E74: Cornetto Trilogy | F74: Cornetto Trilogy (Box Set) | I74: Owned via Cornetto Trilogy (Box Set). | J74: Edgar Wright | K74: 99 | L74: Comedy, Horror | M74: StudioCanal, Working Title Films, Big Talk Productions | N74: https://huggingface.co/datasets/HenryWaltson/TMDB-IMDB-Movies-Dataset | O74: https://huggingface.co/datasets/HenryWaltson/TMDB-IMDB-Movies-Dataset | P74: Simon Pegg | Q74: Nick Frost | R74: Kate Ashfield | S74: Lucy Davis | T74: Dylan Moran | U74: 0 | V74: 0 | X74: {=IFERROR(INDEX(Ratings!$E$5:$E$500,MATCH(A74,Ratings!$A$5:$A$500,0)),"")} | Y74: {=IFERROR(INDEX(Ratings!$G$5:$G$500,MATCH(A74,Ratings!$A$5:$A$500,0)),"")} | Z74: {=IFERROR(INDEX(Ratings!$I$5:$I$500,MATCH(A74,Ratings!$A$5:$A$500,0)),"")} | AB74: 15
A75: F0071 | B75: Hot Fuzz | C75: 2007 | D75: Blu-ray | E75: Cornetto Trilogy | F75: Cornetto Trilogy (Box Set) | I75: Owned via Cornetto Trilogy (Box Set). | J75: Edgar Wright | K75: 121 | L75: Action, Comedy, Mystery | M75: Universal Pictures, StudioCanal, Working Title Films | N75: https://huggingface.co/datasets/HenryWaltson/TMDB-IMDB-Movies-Dataset | O75: https://huggingface.co/datasets/HenryWaltson/TMDB-IMDB-Movies-Dataset | P75: Simon Pegg | Q75: Nick Frost | R75: Jim Broadbent | S75: Paddy Considine | T75: Rafe Spall | U75: 0 | V75: 0 | X75: {=IFERROR(INDEX(Ratings!$E$5:$E$500,MATCH(A75,Ratings!$A$5:$A$500,0)),"")} | Y75: {=IFERROR(INDEX(Ratings!$G$5:$G$500,MATCH(A75,Ratings!$A$5:$A$500,0)),"")} | Z75: {=IFERROR(INDEX(Ratings!$I$5:$I$500,MATCH(A75,Ratings!$A$5:$A$500,0)),"")} | AB75: 15
A76: F0072 | B76: The World's End | C76: 2013 | D76: Blu-ray | E76: Cornetto Trilogy | F76: Cornetto Trilogy (Box Set) | I76: Owned via Cornetto Trilogy (Box Set). | J76: Edgar Wright | K76: 109 | L76: Comedy, Science Fiction | M76: Universal Pictures, Focus Features, Working Title Films | N76: https://huggingface.co/datasets/HenryWaltson/TMDB-IMDB-Movies-Dataset | O76: https://huggingface.co/datasets/HenryWaltson/TMDB-IMDB-Movies-Dataset | P76: Simon Pegg | Q76: Nick Frost | R76: Martin Freeman | S76: Paddy Considine | T76: Eddie Marsan | U76: 0 | V76: 0 | X76: {=IFERROR(INDEX(Ratings!$E$5:$E$500,MATCH(A76,Ratings!$A$5:$A$500,0)),"")} | Y76: {=IFERROR(INDEX(Ratings!$G$5:$G$500,MATCH(A76,Ratings!$A$5:$A$500,0)),"")} | Z76: {=IFERROR(INDEX(Ratings!$I$5:$I$500,MATCH(A76,Ratings!$A$5:$A$500,0)),"")} | AB76: 15
A77: F0073 | B77: Cowboys & Aliens | C77: 2011 | D77: Blu-ray | I77: A stranger stumbles into the desert town of Absolution with no memory of his past and a futuristic shackle around his wrist. With the help of mysterious beauty Ella and the iron-fisted Colonel Dolarhyde, he finds himself leading an unlikely posse of cowboys, outlaws, and Apache warriors against a common enemy from beyond this world in an epic showdown for survival. | J77: Jon Favreau | K77: 119 | L77: Action, Science Fiction, Thriller, Western | M77: DreamWorks Pictures, Universal Pictures, Reliance Entertainment | N77: https://huggingface.co/datasets/HenryWaltson/TMDB-IMDB-Movies-Dataset | O77: https://huggingface.co/datasets/HenryWaltson/TMDB-IMDB-Movies-Dataset | P77: Daniel Craig | Q77: Harrison Ford | R77: Olivia Wilde | S77: Sam Rockwell | T77: Adam Beach | U77: 0 | V77: 0 | X77: {=IFERROR(INDEX(Ratings!$E$5:$E$500,MATCH(A77,Ratings!$A$5:$A$500,0)),"")} | Y77: {=IFERROR(INDEX(Ratings!$G$5:$G$500,MATCH(A77,Ratings!$A$5:$A$500,0)),"")} | Z77: {=IFERROR(INDEX(Ratings!$I$5:$I$500,MATCH(A77,Ratings!$A$5:$A$500,0)),"")} | AB77: 12A
A78: F0074 | B78: Creed | C78: 2015 | D78: Blu-ray | I78: The former World Heavyweight Champion Rocky Balboa serves as a trainer and mentor to Adonis Johnson, the son of his late friend and former rival Apollo Creed. | J78: Ryan Coogler | K78: 133 | L78: Action, Drama | M78: Metro-Goldwyn-Mayer, New Line Cinema, Chartoff-Winkler Productions | N78: https://huggingface.co/datasets/HenryWaltson/TMDB-IMDB-Movies-Dataset | O78: https://huggingface.co/datasets/HenryWaltson/TMDB-IMDB-Movies-Dataset | P78: Michael B. Jordan | Q78: Sylvester Stallone | R78: Tessa Thompson | S78: Phylicia Rashād | T78: Andre Ward | U78: 1 | V78: 0 | X78: {=IFERROR(INDEX(Ratings!$E$5:$E$500,MATCH(A78,Ratings!$A$5:$A$500,0)),"")} | Y78: {=IFERROR(INDEX(Ratings!$G$5:$G$500,MATCH(A78,Ratings!$A$5:$A$500,0)),"")} | Z78: {=IFERROR(INDEX(Ratings!$I$5:$I$500,MATCH(A78,Ratings!$A$5:$A$500,0)),"")} | AB78: 12A
A79: F0075 | B79: The Croods | C79: 2013 | D79: Blu-ray | E79: The Croods | I79: The prehistoric Croods family live in a particularly dangerous moment in time. Patriarch Grug, his mate Ugga, teenage daughter Eep, son Thunk, and feisty Gran gather food by day and huddle together in a cave at night. When a more evolved caveman named Guy arrives on the scene, Grug is distrustful, but it soon becomes apparent that Guy is correct about the impending destruction of their world. | J79: Kirk DeMicco, Chris Sanders | K79: 98 | L79: Animation, Adventure, Family, Fantasy, Comedy, Action | M79: DreamWorks Animation, 20th Century Fox | N79: https://huggingface.co/datasets/HenryWaltson/TMDB-IMDB-Movies-Dataset | O79: https://huggingface.co/datasets/HenryWaltson/TMDB-IMDB-Movies-Dataset | P79: Nicolas Cage | Q79: Emma Stone | R79: Ryan Reynolds | S79: Catherine Keener | T79: Cloris Leachman | U79: 1 | V79: 0 | X79: {=IFERROR(INDEX(Ratings!$E$5:$E$500,MATCH(A79,Ratings!$A$5:$A$500,0)),"")} | Y79: {=IFERROR(INDEX(Ratings!$G$5:$G$500,MATCH(A79,Ratings!$A$5:$A$500,0)),"")} | Z79: {=IFERROR(INDEX(Ratings!$I$5:$I$500,MATCH(A79,Ratings!$A$5:$A$500,0)),"")} | AB79: U
A80: F0076 | B80: Deadpool | C80: 2016 | D80: Blu-ray | E80: Deadpool / X-Men | G80: Yes | H80: ⭐⭐⭐⭐⭐ | I80: The origin story of former Special Forces operative turned mercenary Wade Wilson, who, after being subjected to a rogue experiment that leaves him with accelerated healing powers, adopts the alter ego Deadpool. Armed with his new abilities and a dark, twisted sense of humor, Deadpool hunts down the man who nearly destroyed his life. | J80: Tim Miller | K80: 108 | L80: Action, Adventure, Comedy | M80: 20th Century Fox, The Donners' Company, Genre Films | N80: https://huggingface.co/datasets/HenryWaltson/TMDB-IMDB-Movies-Dataset | O80: https://huggingface.co/datasets/HenryWaltson/TMDB-IMDB-Movies-Dataset | P80: Ryan Reynolds | Q80: Morena Baccarin | R80: Ed Skrein | S80: T.J. Miller | T80: Gina Carano | U80: 0 | V80: 0 | X80: {=IFERROR(INDEX(Ratings!$E$5:$E$500,MATCH(A80,Ratings!$A$5:$A$500,0)),"")} | Y80: {=IFERROR(INDEX(Ratings!$G$5:$G$500,MATCH(A80,Ratings!$A$5:$A$500,0)),"")} | Z80: {=IFERROR(INDEX(Ratings!$I$5:$I$500,MATCH(A80,Ratings!$A$5:$A$500,0)),"")} | AA80: 2026-09-03 | AB80: 15
A81: F0077 | B81: Deadpool 2 | C81: 2018 | D81: 4K UHD | E81: Deadpool / X-Men | G81: Yes | H81: ⭐⭐⭐⭐⭐ | I81: Wisecracking mercenary Deadpool battles the evil and powerful Cable and other bad guys to save a boy's life. | J81: David Leitch | K81: 120 | L81: Action, Comedy, Adventure | M81: Maximum Effort, Genre Films, 20th Century Fox | N81: https://huggingface.co/datasets/HenryWaltson/TMDB-IMDB-Movies-Dataset | O81: https://huggingface.co/datasets/HenryWaltson/TMDB-IMDB-Movies-Dataset | P81: Ryan Reynolds | Q81: Josh Brolin | R81: Morena Baccarin | S81: Julian Dennison | T81: Zazie Beetz | U81: 0 | V81: 0 | X81: {=IFERROR(INDEX(Ratings!$E$5:$E$500,MATCH(A81,Ratings!$A$5:$A$500,0)),"")} | Y81: {=IFERROR(INDEX(Ratings!$G$5:$G$500,MATCH(A81,Ratings!$A$5:$A$500,0)),"")} | Z81: {=IFERROR(INDEX(Ratings!$I$5:$I$500,MATCH(A81,Ratings!$A$5:$A$500,0)),"")} | AA81: 2026-09-05 | AB81: 15
A82: F0078 | B82: Deadpool & Wolverine | C82: 2024 | D82: 4K UHD | E82: X-Men | G82: Yes | H82: ⭐⭐⭐⭐⭐ | I82: A listless Wade Wilson toils away in civilian life with his days as the morally flexible mercenary, Deadpool, behind him. But when his homeworld faces an existential threat, Wade must reluctantly suit-up again with an even more reluctant Wolverine. | J82: Shawn Levy | K82: 128 | L82: Action, Comedy, Science Fiction | M82: Marvel Studios, Maximum Effort, 21 Laps Entertainment | N82: https://huggingface.co/datasets/HenryWaltson/TMDB-IMDB-Movies-Dataset | O82: https://huggingface.co/datasets/HenryWaltson/TMDB-IMDB-Movies-Dataset | P82: Ryan Reynolds | Q82: Hugh Jackman | R82: Emma Corrin | S82: Matthew Macfadyen | T82: Dafne Keen | U82: 0 | V82: 0 | X82: {=IFERROR(INDEX(Ratings!$E$5:$E$500,MATCH(A82,Ratings!$A$5:$A$500,0)),"")} | Y82: {=IFERROR(INDEX(Ratings!$G$5:$G$500,MATCH(A82,Ratings!$A$5:$A$500,0)),"")} | Z82: {=IFERROR(INDEX(Ratings!$I$5:$I$500,MATCH(A82,Ratings!$A$5:$A$500,0)),"")} | AA82: 2026-09-06 | AB82: 15
A83: F0079 | B83: Dear John | C83: 2010 | D83: Blu-ray | I83: While Sergeant John Tyree is home on two weeks leave from Germany, he meets Savannah after he dives into the ocean to retrieve Savannah's purse that had fallen off a pier. John eventually falls in love with Savannah, who promises to write to him until he returns from overseas. | J83: Lasse Hallström | K83: 108 | L83: Drama, Romance, War | M83: Screen Gems, Relativity Media, Temple Hill Entertainment | N83: https://huggingface.co/datasets/HenryWaltson/TMDB-IMDB-Movies-Dataset | O83: https://huggingface.co/datasets/HenryWaltson/TMDB-IMDB-Movies-Dataset | P83: Amanda Seyfried | Q83: Channing Tatum | R83: Richard Jenkins | S83: Henry Thomas | T83: D.J. Cotrona | U83: 0 | V83: 0 | X83: {=IFERROR(INDEX(Ratings!$E$5:$E$500,MATCH(A83,Ratings!$A$5:$A$500,0)),"")} | Y83: {=IFERROR(INDEX(Ratings!$G$5:$G$500,MATCH(A83,Ratings!$A$5:$A$500,0)),"")} | Z83: {=IFERROR(INDEX(Ratings!$I$5:$I$500,MATCH(A83,Ratings!$A$5:$A$500,0)),"")} | AB83: 12A
A84: F0080 | B84: Delivery Man | C84: 2013 | D84: Blu-ray | I84: An affable underachiever finds out he's fathered 533 children through anonymous donations to a fertility clinic 20 years ago. Now he must decide whether or not to come forward when 142 of them file a lawsuit to reveal his identity. | J84: Ken Scott | K84: 105 | L84: Comedy | M84: Touchstone Pictures, DreamWorks Pictures, Reliance Entertainment | N84: https://huggingface.co/datasets/HenryWaltson/TMDB-IMDB-Movies-Dataset | O84: https://huggingface.co/datasets/HenryWaltson/TMDB-IMDB-Movies-Dataset | P84: Vince Vaughn | Q84: Cobie Smulders | R84: Chris Pratt | S84: Britt Robertson | T84: Jack Reynor | U84: 0 | V84: 0 | X84: {=IFERROR(INDEX(Ratings!$E$5:$E$500,MATCH(A84,Ratings!$A$5:$A$500,0)),"")} | Y84: {=IFERROR(INDEX(Ratings!$G$5:$G$500,MATCH(A84,Ratings!$A$5:$A$500,0)),"")} | Z84: {=IFERROR(INDEX(Ratings!$I$5:$I$500,MATCH(A84,Ratings!$A$5:$A$500,0)),"")} | AB84: 12A
A85: F0081 | B85: The Departed | C85: 2006 | D85: Blu-ray | I85: To take down South Boston's Irish Mafia, the police send in one of their own to infiltrate the underworld, not realizing the syndicate has done likewise. While an undercover cop curries favor with the mob kingpin, a career criminal rises through the police ranks. But both sides soon discover there's a mole among them. | J85: Martin Scorsese | K85: 151 | L85: Drama, Thriller, Crime | M85: Vertigo Entertainment, Media Asia Films, Initial Entertainment Group | N85: https://huggingface.co/datasets/HenryWaltson/TMDB-IMDB-Movies-Dataset | O85: https://huggingface.co/datasets/HenryWaltson/TMDB-IMDB-Movies-Dataset | P85: Leonardo DiCaprio | Q85: Matt Damon | R85: Jack Nicholson | S85: Mark Wahlberg | T85: Martin Sheen | U85: 5 | V85: 4 | W85: Winner | X85: {=IFERROR(INDEX(Ratings!$E$5:$E$500,MATCH(A85,Ratings!$A$5:$A$500,0)),"")} | Y85: {=IFERROR(INDEX(Ratings!$G$5:$G$500,MATCH(A85,Ratings!$A$5:$A$500,0)),"")} | Z85: {=IFERROR(INDEX(Ratings!$I$5:$I$500,MATCH(A85,Ratings!$A$5:$A$500,0)),"")} | AB85: 18
A86: F0082 | B86: Despicable Me | C86: 2010 | D86: Blu-ray | E86: Despicable Me / Minions | I86: Determined to prove he's the world's greatest supervillain, Gru hatches an audacious plan to steal the Moon. To pull it off, he adopts three orphaned girls—Margo, Edith, and Agnes—intending to use them as pawns in his scheme. But the unexpected bond they form forces him to question the criminal life he's always known. | J86: Pierre Coffin, Chris Renaud | K86: 95 | L86: Family, Animation, Comedy | M86: Illumination, Universal Pictures | N86: https://huggingface.co/datasets/HenryWaltson/TMDB-IMDB-Movies-Dataset | O86: https://huggingface.co/datasets/HenryWaltson/TMDB-IMDB-Movies-Dataset | P86: Steve Carell | Q86: Jason Segel | R86: Miranda Cosgrove | S86: Elsie Fisher | T86: Dana Gaier | U86: 0 | V86: 0 | X86: {=IFERROR(INDEX(Ratings!$E$5:$E$500,MATCH(A86,Ratings!$A$5:$A$500,0)),"")} | Y86: {=IFERROR(INDEX(Ratings!$G$5:$G$500,MATCH(A86,Ratings!$A$5:$A$500,0)),"")} | Z86: {=IFERROR(INDEX(Ratings!$I$5:$I$500,MATCH(A86,Ratings!$A$5:$A$500,0)),"")} | AB86: U
A87: F0083 | B87: Despicable Me 2 | C87: 2013 | D87: Blu-ray | E87: Despicable Me / Minions | I87: Gru is recruited by the Anti-Villain League to help deal with a powerful new super criminal. | J87: Pierre Coffin, Chris Renaud | K87: 98 | L87: Animation, Comedy, Family | M87: Illumination, Universal Pictures | N87: https://huggingface.co/datasets/HenryWaltson/TMDB-IMDB-Movies-Dataset | O87: https://huggingface.co/datasets/HenryWaltson/TMDB-IMDB-Movies-Dataset | P87: Steve Carell | Q87: Kristen Wiig | R87: Benjamin Bratt | S87: Miranda Cosgrove | T87: Russell Brand | U87: 2 | V87: 0 | X87: {=IFERROR(INDEX(Ratings!$E$5:$E$500,MATCH(A87,Ratings!$A$5:$A$500,0)),"")} | Y87: {=IFERROR(INDEX(Ratings!$G$5:$G$500,MATCH(A87,Ratings!$A$5:$A$500,0)),"")} | Z87: {=IFERROR(INDEX(Ratings!$I$5:$I$500,MATCH(A87,Ratings!$A$5:$A$500,0)),"")} | AB87: U
A88: F0084 | B88: Despicable Me 3 | C88: 2017 | D88: Blu-ray | E88: Despicable Me / Minions | I88: Gru and his wife Lucy must stop former '80s child star Balthazar Bratt from achieving world domination. | J88: Kyle Balda, Pierre Coffin, Eric Guillon | K88: 90 | L88: Action, Animation, Comedy, Family, Adventure | M88: Illumination, Universal Pictures | N88: https://huggingface.co/datasets/HenryWaltson/TMDB-IMDB-Movies-Dataset | O88: https://huggingface.co/datasets/HenryWaltson/TMDB-IMDB-Movies-Dataset | P88: Steve Carell | Q88: Kristen Wiig | R88: Miranda Cosgrove | S88: Dana Gaier | T88: Nev Scharrel | U88: 0 | V88: 0 | X88: {=IFERROR(INDEX(Ratings!$E$5:$E$500,MATCH(A88,Ratings!$A$5:$A$500,0)),"")} | Y88: {=IFERROR(INDEX(Ratings!$G$5:$G$500,MATCH(A88,Ratings!$A$5:$A$500,0)),"")} | Z88: {=IFERROR(INDEX(Ratings!$I$5:$I$500,MATCH(A88,Ratings!$A$5:$A$500,0)),"")} | AB88: U
A89: F0085 | B89: The Dictator | C89: 2012 | D89: Blu-ray | I89: The heroic story of a dictator who risks his life to ensure that democracy would never come to the country he so lovingly oppressed. | J89: Larry Charles | K89: 83 | L89: Comedy | M89: Four By Two Productions, Paramount | N89: https://huggingface.co/datasets/HenryWaltson/TMDB-IMDB-Movies-Dataset | O89: https://huggingface.co/datasets/HenryWaltson/TMDB-IMDB-Movies-Dataset | P89: Sacha Baron Cohen | Q89: Ben Kingsley | R89: Anna Faris | S89: Jason Mantzoukas | T89: Sayed Badreya | U89: 0 | V89: 0 | X89: {=IFERROR(INDEX(Ratings!$E$5:$E$500,MATCH(A89,Ratings!$A$5:$A$500,0)),"")} | Y89: {=IFERROR(INDEX(Ratings!$G$5:$G$500,MATCH(A89,Ratings!$A$5:$A$500,0)),"")} | Z89: {=IFERROR(INDEX(Ratings!$I$5:$I$500,MATCH(A89,Ratings!$A$5:$A$500,0)),"")} | AB89: 15
A90: F0086 | B90: Live Free or Die Hard | C90: 2007 | D90: Blu-ray | I90: John McClane is back and badder than ever, and this time he calls on the services of a young hacker in his bid to stop a ring of Internet terrorists intent on taking control of America's computer infrastructure. | J90: Len Wiseman | K90: 128 | L90: Action, Thriller | M90: Dune Entertainment, Cheyenne Enterprises, Wintergreen Productions | N90: https://huggingface.co/datasets/HenryWaltson/TMDB-IMDB-Movies-Dataset | O90: https://huggingface.co/datasets/HenryWaltson/TMDB-IMDB-Movies-Dataset | P90: Bruce Willis | Q90: Justin Long | R90: Timothy Olyphant | S90: Cliff Curtis | T90: Maggie Q | U90: 0 | V90: 0 | X90: {=IFERROR(INDEX(Ratings!$E$5:$E$500,MATCH(A90,Ratings!$A$5:$A$500,0)),"")} | Y90: {=IFERROR(INDEX(Ratings!$G$5:$G$500,MATCH(A90,Ratings!$A$5:$A$500,0)),"")} | Z90: {=IFERROR(INDEX(Ratings!$I$5:$I$500,MATCH(A90,Ratings!$A$5:$A$500,0)),"")} | AB90: 15
A91: F0087 | B91: Dirty Grandpa | C91: 2016 | D91: Blu-ray | I91: Jason Kelly is one week away from marrying his boss's uber-controlling daughter, putting him on the fast track for a partnership at the law firm. However, when the straight-laced Jason is tricked into driving his foul-mouthed grandfather, Dick, to Daytona for spring break, his pending nuptials are suddenly in jeopardy. Between riotous frat parties, bar fights, and an epic night of karaoke, Dick is on a quest to live his life to the fullest and bring Jason along for the ride. | J91: Dan Mazer | K91: 102 | L91: Comedy | M91: Covert Media, Lionsgate, BillBlock Media | N91: https://huggingface.co/datasets/HenryWaltson/TMDB-IMDB-Movies-Dataset | O91: https://huggingface.co/datasets/HenryWaltson/TMDB-IMDB-Movies-Dataset | P91: Robert De Niro | Q91: Zac Efron | R91: Aubrey Plaza | S91: Zoey Deutch | T91: Julianne Hough | U91: 0 | V91: 0 | X91: {=IFERROR(INDEX(Ratings!$E$5:$E$500,MATCH(A91,Ratings!$A$5:$A$500,0)),"")} | Y91: {=IFERROR(INDEX(Ratings!$G$5:$G$500,MATCH(A91,Ratings!$A$5:$A$500,0)),"")} | Z91: {=IFERROR(INDEX(Ratings!$I$5:$I$500,MATCH(A91,Ratings!$A$5:$A$500,0)),"")} | AB91: 15
A92: F0088 | B92: District 9 | C92: 2009 | D92: Blu-ray | I92: Thirty years ago, aliens arrive on Earth. Not to conquer or give aid, but to find refuge from their dying planet. Separated from humans in a South African area called District 9, the aliens are managed by Multi-National United, which is unconcerned with the aliens' welfare but will do anything to master their advanced technology. When a company field agent contracts a mysterious virus that begins to alter his DNA, there is only one place he can hide: District 9. | J92: Neill Blomkamp | K92: 112 | L92: Science Fiction | M92: TriStar Pictures, Block / Hanson, WingNut Films | N92: https://huggingface.co/datasets/HenryWaltson/TMDB-IMDB-Movies-Dataset | O92: https://huggingface.co/datasets/HenryWaltson/TMDB-IMDB-Movies-Dataset | P92: Sharlto Copley | Q92: Jason Cope | R92: Nathalie Boltt | S92: Sylvaine Strike | T92: Elizabeth Mkandawie | U92: 4 | V92: 0 | W92: Nominated | X92: {=IFERROR(INDEX(Ratings!$E$5:$E$500,MATCH(A92,Ratings!$A$5:$A$500,0)),"")} | Y92: {=IFERROR(INDEX(Ratings!$G$5:$G$500,MATCH(A92,Ratings!$A$5:$A$500,0)),"")} | Z92: {=IFERROR(INDEX(Ratings!$I$5:$I$500,MATCH(A92,Ratings!$A$5:$A$500,0)),"")} | AB92: 15
A93: F0089 | B93: Divergent | C93: 2014 | D93: Blu-ray | E93: Divergent | I93: In a world divided into factions based on personality types, Tris learns that she's been classified as Divergent and won't fit in. When she discovers a plot to destroy Divergents, Tris and the mysterious Four must find out what makes Divergents dangerous before it's too late. | J93: Neil Burger | K93: 139 | L93: Action, Adventure, Science Fiction | M93: Summit Entertainment, Red Wagon Entertainment | N93: https://huggingface.co/datasets/HenryWaltson/TMDB-IMDB-Movies-Dataset | O93: https://huggingface.co/datasets/HenryWaltson/TMDB-IMDB-Movies-Dataset | P93: Shailene Woodley | Q93: Theo James | R93: Zoë Kravitz | S93: Miles Teller | T93: Jai Courtney | U93: 0 | V93: 0 | X93: {=IFERROR(INDEX(Ratings!$E$5:$E$500,MATCH(A93,Ratings!$A$5:$A$500,0)),"")} | Y93: {=IFERROR(INDEX(Ratings!$G$5:$G$500,MATCH(A93,Ratings!$A$5:$A$500,0)),"")} | Z93: {=IFERROR(INDEX(Ratings!$I$5:$I$500,MATCH(A93,Ratings!$A$5:$A$500,0)),"")} | AB93: 12A
A94: F0090 | B94: Django Unchained | C94: 2012 | D94: Blu-ray | I94: With the help of a German bounty hunter, a freed slave sets out to rescue his wife from a brutal Mississippi plantation owner. | J94: Quentin Tarantino | K94: 165 | L94: Drama, Western | M94: The Weinstein Company, Columbia Pictures | N94: https://huggingface.co/datasets/HenryWaltson/TMDB-IMDB-Movies-Dataset | O94: https://huggingface.co/datasets/HenryWaltson/TMDB-IMDB-Movies-Dataset | P94: Jamie Foxx | Q94: Christoph Waltz | R94: Leonardo DiCaprio | S94: Kerry Washington | T94: Samuel L. Jackson | U94: 5 | V94: 2 | W94: Nominated | X94: {=IFERROR(INDEX(Ratings!$E$5:$E$500,MATCH(A94,Ratings!$A$5:$A$500,0)),"")} | Y94: {=IFERROR(INDEX(Ratings!$G$5:$G$500,MATCH(A94,Ratings!$A$5:$A$500,0)),"")} | Z94: {=IFERROR(INDEX(Ratings!$I$5:$I$500,MATCH(A94,Ratings!$A$5:$A$500,0)),"")} | AB94: 18
A95: F0091 | B95: Due Date | C95: 2010 | D95: Blu-ray | G95: Yes | H95: ⭐⭐⭐⭐ | I95: Peter Highman must scramble across the US in five days to be present for the birth of his first child. He gets off to a bad start when his wallet and luggage are stolen, and put on the 'no-fly' list. Peter embarks on a terrifying journey when he accepts a ride from an actor. | J95: Todd Phillips | K95: 95 | L95: Comedy, Drama | M95: Legendary Pictures, Green Hat Films, Warner Bros. Pictures | N95: https://huggingface.co/datasets/HenryWaltson/TMDB-IMDB-Movies-Dataset | O95: https://huggingface.co/datasets/HenryWaltson/TMDB-IMDB-Movies-Dataset | P95: Robert Downey Jr. | Q95: Zach Galifianakis | R95: Michelle Monaghan | S95: Jamie Foxx | T95: Juliette Lewis | U95: 0 | V95: 0 | X95: {=IFERROR(INDEX(Ratings!$E$5:$E$500,MATCH(A95,Ratings!$A$5:$A$500,0)),"")} | Y95: {=IFERROR(INDEX(Ratings!$G$5:$G$500,MATCH(A95,Ratings!$A$5:$A$500,0)),"")} | Z95: {=IFERROR(INDEX(Ratings!$I$5:$I$500,MATCH(A95,Ratings!$A$5:$A$500,0)),"")} | AA95: 2026-08-08 | AB95: 15
A96: F0092 | B96: Elf | C96: 2003 | D96: 4K UHD | I96: When young Buddy falls into Santa's gift sack on Christmas Eve, he's transported back to the North Pole and raised as a toy-making elf by Santa's helpers. But as he grows into adulthood, he can't shake the nagging feeling that he doesn't belong. Buddy vows to visit Manhattan and find his real dad, a workaholic. | J96: Jon Favreau | K96: 97 | L96: Comedy, Family, Fantasy | M96: New Line Cinema, Guy Walks into a Bar Productions | N96: https://huggingface.co/datasets/HenryWaltson/TMDB-IMDB-Movies-Dataset | O96: https://huggingface.co/datasets/HenryWaltson/TMDB-IMDB-Movies-Dataset | P96: Will Ferrell | Q96: James Caan | R96: Bob Newhart | S96: Ed Asner | T96: Mary Steenburgen | U96: 0 | V96: 0 | X96: {=IFERROR(INDEX(Ratings!$E$5:$E$500,MATCH(A96,Ratings!$A$5:$A$500,0)),"")} | Y96: {=IFERROR(INDEX(Ratings!$G$5:$G$500,MATCH(A96,Ratings!$A$5:$A$500,0)),"")} | Z96: {=IFERROR(INDEX(Ratings!$I$5:$I$500,MATCH(A96,Ratings!$A$5:$A$500,0)),"")} | AB96: PG
A97: F0093 | B97: Elysium | C97: 2013 | D97: Blu-ray | I97: In the year 2159, two classes of people exist: the very wealthy who live on a pristine man-made space station called Elysium, and the rest, who live on an overpopulated, ruined Earth. Secretary Rhodes, a hard line government official, will stop at nothing to enforce anti-immigration laws and preserve the luxurious lifestyle of the citizens of Elysium. That doesn’t stop the people of Earth from trying to get in, by any means they can. When unlucky Max is backed into a corner, he agrees to take on a daunting mission that, if successful, will not only save his life, but could bring equality to these polarized worlds. | J97: Neill Blomkamp | K97: 109 | L97: Science Fiction, Action, Drama, Thriller | M97: Genre Films, TriStar Pictures, MRC | N97: https://huggingface.co/datasets/HenryWaltson/TMDB-IMDB-Movies-Dataset | O97: https://huggingface.co/datasets/HenryWaltson/TMDB-IMDB-Movies-Dataset | P97: Matt Damon | Q97: Jodie Foster | R97: Sharlto Copley | S97: Diego Luna | T97: Wagner Moura | U97: 0 | V97: 0 | X97: {=IFERROR(INDEX(Ratings!$E$5:$E$500,MATCH(A97,Ratings!$A$5:$A$500,0)),"")} | Y97: {=IFERROR(INDEX(Ratings!$G$5:$G$500,MATCH(A97,Ratings!$A$5:$A$500,0)),"")} | Z97: {=IFERROR(INDEX(Ratings!$I$5:$I$500,MATCH(A97,Ratings!$A$5:$A$500,0)),"")} | AB97: 15
A98: F0094 | B98: Enemy of the State | C98: 1998 | D98: Blu-ray | I98: When the videotape of the murder of a congressman unknowingly ends up in the hands of labor lawyer and dedicated family man Robert Clayton Dean, he is framed for the murder. With the help of the mysterious Brill, Dean attempts to throw the NSA off his trail and prove his innocence. | J98: Tony Scott | K98: 132 | L98: Action, Drama, Thriller | M98: Touchstone Pictures, Jerry Bruckheimer Films, Don Simpson/Jerry Bruckheimer Films | N98: https://huggingface.co/datasets/HenryWaltson/TMDB-IMDB-Movies-Dataset | O98: https://huggingface.co/datasets/HenryWaltson/TMDB-IMDB-Movies-Dataset | P98: Will Smith | Q98: Gene Hackman | R98: Jon Voight | S98: Regina King | T98: Loren Dean | U98: 0 | V98: 0 | X98: {=IFERROR(INDEX(Ratings!$E$5:$E$500,MATCH(A98,Ratings!$A$5:$A$500,0)),"")} | Y98: {=IFERROR(INDEX(Ratings!$G$5:$G$500,MATCH(A98,Ratings!$A$5:$A$500,0)),"")} | Z98: {=IFERROR(INDEX(Ratings!$I$5:$I$500,MATCH(A98,Ratings!$A$5:$A$500,0)),"")} | AB98: 15
A99: F0095 | B99: The Expendables | C99: 2010 | D99: Blu-ray | E99: Expendables | I99: Barney Ross leads a band of highly skilled mercenaries including knife enthusiast Lee Christmas, a martial arts expert Yin Yang, heavy weapons specialist Hale Caesar, demolitionist Toll Road, and a loose-cannon sniper Gunner Jensen. When the group is commissioned by the mysterious Mr. Church to assassinate the dictator of a small South American island, Barney and Lee visit the remote locale to scout out their opposition and discover the true nature of the conflict engulfing the city. | J99: Sylvester Stallone | K99: 103 | L99: Thriller, Adventure, Action | M99: Nimar Studios, Rogue Marble, Millennium Media | N99: https://huggingface.co/datasets/HenryWaltson/TMDB-IMDB-Movies-Dataset | O99: https://huggingface.co/datasets/HenryWaltson/TMDB-IMDB-Movies-Dataset | P99: Sylvester Stallone | Q99: Jason Statham | R99: Jet Li | S99: Dolph Lundgren | T99: Eric Roberts | U99: 0 | V99: 0 | X99: {=IFERROR(INDEX(Ratings!$E$5:$E$500,MATCH(A99,Ratings!$A$5:$A$500,0)),"")} | Y99: {=IFERROR(INDEX(Ratings!$G$5:$G$500,MATCH(A99,Ratings!$A$5:$A$500,0)),"")} | Z99: {=IFERROR(INDEX(Ratings!$I$5:$I$500,MATCH(A99,Ratings!$A$5:$A$500,0)),"")} | AB99: 18
A100: F0096 | B100: The Expendables 2 | C100: 2012 | D100: Blu-ray | E100: Expendables | I100: Mr. Church reunites the Expendables for what should be an easy paycheck, but when one of their men is murdered on the job, their quest for revenge puts them deep in enemy territory and up against an unexpected threat. | J100: Simon West | K100: 103 | L100: Action, Adventure, Thriller | M100: Nu Image, Millennium Media, Lionsgate | N100: https://huggingface.co/datasets/HenryWaltson/TMDB-IMDB-Movies-Dataset | O100: https://huggingface.co/datasets/HenryWaltson/TMDB-IMDB-Movies-Dataset | P100: Sylvester Stallone | Q100: Jason Statham | R100: Jet Li | S100: Dolph Lundgren | T100: Chuck Norris | U100: 0 | V100: 0 | X100: {=IFERROR(INDEX(Ratings!$E$5:$E$500,MATCH(A100,Ratings!$A$5:$A$500,0)),"")} | Y100: {=IFERROR(INDEX(Ratings!$G$5:$G$500,MATCH(A100,Ratings!$A$5:$A$500,0)),"")} | Z100: {=IFERROR(INDEX(Ratings!$I$5:$I$500,MATCH(A100,Ratings!$A$5:$A$500,0)),"")} | AB100: 15
A101: F0097 | B101: The Expendables 3 | C101: 2014 | D101: Blu-ray | E101: Expendables | I101: Barney, Christmas and the rest of the team comes face-to-face with Conrad Stonebanks, who years ago co-founded The Expendables with Barney. Stonebanks subsequently became a ruthless arms trader and someone who Barney was forced to kill… or so he thought. Stonebanks, who eluded death once before, now is making it his mission to end The Expendables -- but Barney has other plans. Barney decides that he has to fight old blood with new blood, and brings in a new era of Expendables team members, recruiting individuals who are younger, faster and more tech-savvy. The latest mission becomes a clash of classic old-school style versus high-tech expertise in the Expendables’ most personal battle yet. | J101: Patrick Hughes | K101: 126 | L101: Action, Adventure, Thriller | M101: Davis Films, Nu Image, Ex3 Productions | N101: https://huggingface.co/datasets/HenryWaltson/TMDB-IMDB-Movies-Dataset | O101: https://huggingface.co/datasets/HenryWaltson/TMDB-IMDB-Movies-Dataset | P101: Sylvester Stallone | Q101: Jason Statham | R101: Harrison Ford | S101: Mel Gibson | T101: Arnold Schwarzenegger | U101: 0 | V101: 0 | X101: {=IFERROR(INDEX(Ratings!$E$5:$E$500,MATCH(A101,Ratings!$A$5:$A$500,0)),"")} | Y101: {=IFERROR(INDEX(Ratings!$G$5:$G$500,MATCH(A101,Ratings!$A$5:$A$500,0)),"")} | Z101: {=IFERROR(INDEX(Ratings!$I$5:$I$500,MATCH(A101,Ratings!$A$5:$A$500,0)),"")} | AB101: 12A
...

Sheet Wishlist
A1: 🛒 WISHLIST & NEXT BUYS
A2: Your original wanted films plus recommendations based on the collection. Prices can be filled in as we hunt for bargains.
A4: Title | B4: Type | C4: Priority (1-5) | D4: Target Price (£) | E4: Cheapest Found (£) | F4: Where | G4: Date Checked | H4: Already Owned? | I4: Notes
A5: Everything Everywhere All at Once | B5: Your list | C5: 3 | H5: =IF(A6="","",IF(COUNTIF(Collection!$B$5:$B$500,A6)>0,"Yes","No")) | I5: From your original wishlist
A6: CODA | B6: Your list | C6: 2 | H6: =IF(A7="","",IF(COUNTIF(Collection!$B$5:$B$500,A7)>0,"Yes","No")) | I6: From your original wishlist
A7: Parasite | B7: Your list | C7: 3 | H7: =IF(A8="","",IF(COUNTIF(Collection!$B$5:$B$500,A8)>0,"Yes","No")) | I7: From your original wishlist
A8: The Shape of Water | B8: Your list | C8: 3 | H8: =IF(A10="","",IF(COUNTIF(Collection!$B$5:$B$500,A10)>0,"Yes","No")) | I8: From your original wishlist
A9: Moonlight | B9: Your list | C9: 3 | H9: =IF(A11="","",IF(COUNTIF(Collection!$B$5:$B$500,A11)>0,"Yes","No")) | I9: From your original wishlist
A10: Spotlight | B10: Your list | C10: 3 | H10: =IF(A12="","",IF(COUNTIF(Collection!$B$5:$B$500,A12)>0,"Yes","No")) | I10: From your original wishlist
A11: Birdman or (The Unexpected Virtue of Ignorance) | B11: Your list | C11: 4 | E11: 10 | F11: HMV | G11: 2026-08-23 | H11: =IF(A13="","",IF(COUNTIF(Collection!$B$5:$B$500,A13)>0,"Yes","No")) | I11: From your original wishlist
A12: 12 Years a Slave | B12: Your list | C12: 2 | H12: =IF(A14="","",IF(COUNTIF(Collection!$B$5:$B$500,A14)>0,"Yes","No")) | I12: From your original wishlist
A13: The Artist | B13: Your list | C13: 2 | H13: =IF(A15="","",IF(COUNTIF(Collection!$B$5:$B$500,A15)>0,"Yes","No")) | I13: From your original wishlist
A14: The Hurt Locker | B14: Your list | C14: 2 | H14: =IF(A16="","",IF(COUNTIF(Collection!$B$5:$B$500,A16)>0,"Yes","No")) | I14: From your original wishlist
A15: No Country for Old Men | B15: Your list | C15: 3 | H15: =IF(A17="","",IF(COUNTIF(Collection!$B$5:$B$500,A17)>0,"Yes","No")) | I15: From your original wishlist
A16: Gladiator | B16: Your list | C16: 3 | H16: =IF(A18="","",IF(COUNTIF(Collection!$B$5:$B$500,A18)>0,"Yes","No")) | I16: From your original wishlist
A17: A Beautiful Mind | B17: Your list | C17: 3 | H17: =IF(A19="","",IF(COUNTIF(Collection!$B$5:$B$500,A19)>0,"Yes","No")) | I17: From your original wishlist
A18: The Silence of the Lambs | B18: Your list | C18: 2 | H18: =IF(A21="","",IF(COUNTIF(Collection!$B$5:$B$500,A21)>0,"Yes","No")) | I18: From your original wishlist
A19: Le Mans '66 (Ford v Ferrari) | B19: Your list | C19: 5 | E19: 5 | F19: CEX | G19: 2026-08-23 | H19: =IF(A22="","",IF(COUNTIF(Collection!$B$5:$B$500,A22)>0,"Yes","No")) | I19: From your original wishlist
A20: Million Dollar Baby | B20: Your list | C20: 2 | H20: =IF(A23="","",IF(COUNTIF(Collection!$B$5:$B$500,A23)>0,"Yes","No")) | I20: From your original wishlist
A21: American Beauty | B21: Your list | C21: 2 | H21: =IF(A24="","",IF(COUNTIF(Collection!$B$5:$B$500,A24)>0,"Yes","No")) | I21: From your original wishlist
A22: Rocky | B22: Your list | C22: 3 | H22: =IF(A25="","",IF(COUNTIF(Collection!$B$5:$B$500,A25)>0,"Yes","No")) | I22: From your original wishlist
A23: One Flew Over the Cuckoo's Nest | B23: Your list | C23: 2 | H23: =IF(A26="","",IF(COUNTIF(Collection!$B$5:$B$500,A26)>0,"Yes","No")) | I23: From your original wishlist
A24: Sinners | B24: Your list | C24: 3 | H24: =IF(A27="","",IF(COUNTIF(Collection!$B$5:$B$500,A27)>0,"Yes","No")) | I24: From your original wishlist
A25: Marty Supreme | B25: Your list | C25: 5 | E25: 10 | F25: HMV | G25: 2026-08-23 | H25: =IF(A28="","",IF(COUNTIF(Collection!$B$5:$B$500,A28)>0,"Yes","No")) | I25: From your original wishlist
A26: Whiplash | B26: Recommended | C26: 5 | E26: 7 | F26: HMV | G26: 2026-08-11 | H26: =IF(A29="","",IF(COUNTIF(Collection!$B$5:$B$500,A29)>0,"Yes","No")) | I26: Strong fit with your taste for intense, acclaimed dramas.
A27: The Social Network | B27: Recommended | C27: 3 | H27: =IF(A30="","",IF(COUNTIF(Collection!$B$5:$B$500,A30)>0,"Yes","No")) | I27: Sharp modern classic; fits alongside Fincher, prestige drama and biopics in your collection.
A28: Arrival | B28: Recommended | C28: 3 | H28: =IF(A31="","",IF(COUNTIF(Collection!$B$5:$B$500,A31)>0,"Yes","No")) | I28: Smart sci-fi that should land well if you like Interstellar, Inception and District 9.
A29: Sicario | B29: Recommended | C29: 3 | H29: =IF(A36="","",IF(COUNTIF(Collection!$B$5:$B$500,A36)>0,"Yes","No")) | I29: Tense crime thriller from Denis Villeneuve; fits Prisoners and your darker thrillers.
A30: Nightcrawler | B30: Recommended | C30: 2 | H30: =IF(A38="","",IF(COUNTIF(Collection!$B$5:$B$500,A38)>0,"Yes","No")) | I30: Dark, slick thriller that pairs nicely with Zodiac, Se7en and Prisoners.
A31: The Grand Budapest Hotel | B31: Recommended | C31: 2 | H31: =IF(A39="","",IF(COUNTIF(Collection!$B$5:$B$500,A39)>0,"Yes","No")) | I31: Acclaimed, distinctive and very rewatchable; broadens the prestige side of the shelf.
A32: The Revenant | B32: Recommended | C32: 2 | H32: =IF(A40="","",IF(COUNTIF(Collection!$B$5:$B$500,A40)>0,"Yes","No")) | I32: Large-scale survival drama with strong cinematography and awards pedigree.
A33: There Will Be Blood | B33: Recommended | C33: 4 | E33: 8 | F33: Amazon | G33: 2026-08-23 | H33: =IF(A41="","",IF(COUNTIF(Collection!$B$5:$B$500,A41)>0,"Yes","No")) | I33: Modern classic and a strong Best Picture-era addition.
A34: The Banshees of Inisherin | B34: Recommended | C34: 4 | E34: 7 | F34: Amazon | G34: 2026-08-23 | H34: =IF(A42="","",IF(COUNTIF(Collection!$B$5:$B$500,A42)>0,"Yes","No")) | I34: Excellent recent awards film with dark humour.
A35: The Holdovers | B35: Recommended | C35: 4 | E35: 12 | F35: CEX | G35: 2026-08-23 | H35: =IF(A43="","",IF(COUNTIF(Collection!$B$5:$B$500,A43)>0,"Yes","No")) | I35: Warm, funny modern drama with a classic feel.
A36: The Wolf of Wall Street | B36: Recommended | C36: 3 | H36: =IF(A46="","",IF(COUNTIF(Collection!$B$5:$B$500,A46)>0,"Yes","No")) | I36: If your existing copy turns out not to be in the catalogue, this is worth confirming rather than rebuying.
H37: =IF(A47="","",IF(COUNTIF(Collection!$B$5:$B$500,A47)>0,"Yes","No"))
H38: =IF(A48="","",IF(COUNTIF(Collection!$B$5:$B$500,A48)>0,"Yes","No"))
H39: =IF(A49="","",IF(COUNTIF(Collection!$B$5:$B$500,A49)>0,"Yes","No"))
H40: =IF(A50="","",IF(COUNTIF(Collection!$B$5:$B$500,A50)>0,"Yes","No"))
H41: =IF(A51="","",IF(COUNTIF(Collection!$B$5:$B$500,A51)>0,"Yes","No"))
H42: =IF(A52="","",IF(COUNTIF(Collection!$B$5:$B$500,A52)>0,"Yes","No"))
H43: =IF(A53="","",IF(COUNTIF(Collection!$B$5:$B$500,A53)>0,"Yes","No"))
H44: =IF(A54="","",IF(COUNTIF(Collection!$B$5:$B$500,A54)>0,"Yes","No"))
H45: =IF(A55="","",IF(COUNTIF(Collection!$B$5:$B$500,A55)>0,"Yes","No"))
H46: =IF(A56="","",IF(COUNTIF(Collection!$B$5:$B$500,A56)>0,"Yes","No"))
H47: =IF(A57="","",IF(COUNTIF(Collection!$B$5:$B$500,A57)>0,"Yes","No"))
H48: =IF(A58="","",IF(COUNTIF(Collection!$B$5:$B$500,A58)>0,"Yes","No"))
... H87: =IF(A97="","",IF(COUNTIF(Collection!$B$5:$B$500,A97)>0,"Yes","No"))
A91: Pulp Fiction | C91: 2 | D91: 8 | H91: No
A92: Jumanji | C92: 3 | H92: No
A93: Pirates of the Caribbean: Dead Men Tell No Tales | C93: 3 | H93: No
A94: Pirates of the Caribbean: Dead Man's Chest | C94: 3 | H94: No
A95: Napoleon Dynamite | C95: 3 | H95: No
A994: The accountant 2 | C994: 4 | H994: No
A995: Air | C995: 4 | H995: No
A996: Avatar 3 | C996: 4 | H996: No
A997: Cloudy with a chance of meatballs | C997: 4 | H997: No
A998: Clerks | C998: 4 | E998: 5 | F998: cex | G998: 2026-08-27 | H998: No
A999: Clerks 2 | C999: 4 | H999: No
A1000: Clerks 3 | C1000: 4 | E1000: 6 | F1000: CEX | G1000: 2026-08-27 | H1000: No
A1001: Die hard | C1001: 4 | H1001: No
A1002: Die hard 2 | C1002: 4 | H1002: No
A1003: Die hard 3 | C1003: 4 | H1003: No
A1004: Die hard 5 | C1004: 4 | H1004: No
A1005: Despicable me 4 | C1005: 4 | E1005: 8 | F1005: CEX | G1005: 2026-08-26 | H1005: No
A1006: Dodgeball | C1006: 4 | E1006: 12 | F1006: Amazon | G1006: 2026-08-23 | H1006: No
A1007: Expendables 4 | C1007: 4 | E1007: 7 | F1007: HMV | G1007: 2026-08-23 | H1007: No
A1008: Happy feet | C1008: 4 | E1008: 3 | F1008: CEX | G1008: 2026-08-26 | H1008: No
A1009: Httyd 2 | C1009: 4 | H1009: No
A1010: Httyd 3 | C1010: 4 | H1010: No
A1011: Howls moving castle | C1011: 4 | E1011: 18 | F1011: CEX | G1011: 2026-08-23 | H1011: No
A1012: Ice age 1 | C1012: 4 | H1012: No
A1013: Ice age 4 | C1013: 4 | H1013: No
A1014: Ice age 5 | C1014: 4 | H1014: No
A1015: Inside out 2 | C1015: 4 | H1015: No
A1016: Jason bourne | C1016: 4 | H1016: No
A1017: John wick 3 | C1017: 4 | H1017: No
A1018: John wick 4 | C1018: 4 | H1018: No
A1019: Madagascar 1 | C1019: 4 | H1019: No
A1020: Madagascar 2 | C1020: 4 | H1020: No
A1021: Madagascar 3 | C1021: 4 | H1021: No
A1022: Matrix 4 | C1022: 4 | H1022: No
A1023: Men in black 2 | C1023: 4 | H1023: No
... A1036: Underworld blood wars | C1036: 4 | H1036: No

Sheet Franchise Tracker
A1: 🏆 COLLECTION / FRANCHISE TRACKER
A2: Owned counts are calculated from the Collection tab. Target totals are editable so you can define exactly what 'complete' means to you.
A4: Collection | B4: Owned Films | C4: Target Films | D4: Missing | E4: % Complete
A5: James Bond | B5: =COUNTIF(Collection!$E$5:$E$500,A5) | C5: 5 | D5: =IF(C5="","",MAX(C5-B5,0)) | E5: =IF(C5="","",MIN(B5/C5,1))
A6: Alien | B6: =COUNTIF(Collection!$E$5:$E$500,A6) | C6: 7 | D6: =IF(C6="","",MAX(C6-B6,0)) | E6: =IF(C6="","",MIN(B6/C6,1))
A7: Bourne | B7: =COUNTIF(Collection!$E$5:$E$500,A7) | C7: 5 | D7: =IF(C7="","",MAX(C7-B7,0)) | E7: =IF(C7="","",MIN(B7/C7,1))
A8: Fast & Furious | B8: =COUNTIF(Collection!$E$5:$E$500,A8) | C8: 11 | D8: =IF(C8="","",MAX(C8-B8,0)) | E8: =IF(C8="","",MIN(B8/C8,1))
A9: Harry Potter | B9: =COUNTIF(Collection!$E$5:$E$500,A9) | C9: 8 | D9: =IF(C9="","",MAX(C9-B9,0)) | E9: =IF(C9="","",MIN(B9/C9,1))
A10: Wizarding World | B10: =COUNTIF(Collection!$E$5:$E$500,A10) | C10: 3 | D10: =IF(C10="","",MAX(C10-B10,0)) | E10: =IF(C10="","",MIN(B10/C10,1))
A11: Hobbit | B11: =COUNTIF(Collection!$E$5:$E$500,A11) | C11: 3 | D11: =IF(C11="","",MAX(C11-B11,0)) | E11: =IF(C11="","",MIN(B11/C11,1))
A12: Lord of the Rings | B12: =COUNTIF(Collection!$E$5:$E$500,A12) | C12: 3 | D12: =IF(C12="","",MAX(C12-B12,0)) | E12: =IF(C12="","",MIN(B12/C12,1))
A13: Mission: Impossible | B13: =COUNTIF(Collection!$E$5:$E$500,A13) | C13: 8 | D13: =IF(C13="","",MAX(C13-B13,0)) | E13: =IF(C13="","",MIN(B13/C13,1))
A14: X-Men | B14: =COUNTIF(Collection!$E$5:$E$500,A14) | C14: 10 | D14: =IF(C14="","",MAX(C14-B14,0)) | E14: =IF(C14="","",MIN(B14/C14,1))
A15: Deadpool / X-Men | B15: =COUNTIF(Collection!$E$5:$E$500,A15) | C15: 3 | D15: =IF(C15="","",MAX(C15-B15,0)) | E15: =IF(C15="","",MIN(B15/C15,1))
A16: Transformers | B16: =COUNTIF(Collection!$E$5:$E$500,A16) | C16: 8 | D16: =IF(C16="","",MAX(C16-B16,0)) | E16: =IF(C16="","",MIN(B16/C16,1))
... A29: Rio | B29: =COUNTIF(Collection!$E$5:$E$500,A29) | C29: 2 | D29: =IF(C29="","",MAX(C29-B29,0)) | E29: =IF(C29="","",MIN(B29/C29,1))
A30: Pitch Perfect
A31: Jurassic Park / World | B31: =COUNTIF(Collection!$E$5:$E$500,A31) | C31: 7 | D31: =IF(C31="","",MAX(C31-B31,0)) | E31: =IF(C31="","",MIN(B31/C31,1))
A32: Kick-Ass | B32: =COUNTIF(Collection!$E$5:$E$500,A32) | C32: 2 | D32: =IF(C32="","",MAX(C32-B32,0)) | E32: =IF(C32="","",MIN(B32/C32,1))
A33: LEGO Movie | B33: =COUNTIF(Collection!$E$5:$E$500,A33) | C33: 4 | D33: =IF(C33="","",MAX(C33-B33,0)) | E33: =IF(C33="","",MIN(B33/C33,1))
A34: How to Train Your Dragon | B34: =COUNTIF(Collection!$E$5:$E$500,A34) | C34: 3 | D34: =IF(C34="","",MAX(C34-B34,0)) | E34: =IF(C34="","",MIN(B34/C34,1))
A35: Grown Ups | B35: =COUNTIF(Collection!$E$5:$E$500,A35) | C35: 2 | D35: =IF(C35="","",MAX(C35-B35,0)) | E35: =IF(C35="","",MIN(B35/C35,1))
A36: Sherlock Holmes | B36: =COUNTIF(Collection!$E$5:$E$500,A36) | C36: 2 | D36: =IF(C36="","",MAX(C36-B36,0)) | E36: =IF(C36="","",MIN(B36/C36,1))
A37: Taken | B37: =COUNTIF(Collection!$E$5:$E$500,A37) | C37: 3 | D37: =IF(C37="","",MAX(C37-B37,0)) | E37: =IF(C37="","",MIN(B37/C37,1))
A38: Wreck-It Ralph | B38: =COUNTIF(Collection!$E$5:$E$500,A38) | C38: 2 | D38: =IF(C38="","",MAX(C38-B38,0)) | E38: =IF(C38="","",MIN(B38/C38,1))
A39: Monsters, Inc. | B39: =COUNTIF(Collection!$E$5:$E$500,A39) | C39: 2 | D39: =IF(C39="","",MAX(C39-B39,0)) | E39: =IF(C39="","",MIN(B39/C39,1))
A40: MonsterVerse | B40: =COUNTIF(Collection!$E$5:$E$500,A40) | C40: 5 | D40: =IF(C40="","",MAX(C40-B40,0)) | E40: =IF(C40="","",MIN(B40/C40,1))
A41: The Inbetweeners | B41: =COUNTIF(Collection!$E$5:$E$500,A41) | C41: 2 | D41: =IF(C41="","",MAX(C41-B41,0)) | E41: =IF(C41="","",MIN(B41/C41,1))
A42: Anchorman | B42: =COUNTIF(Collection!$E$5:$E$500,A42) | C42: 2 | D42: =IF(C42="","",MAX(C42-B42,0)) | E42: =IF(C42="","",MIN(B42/C42,1))
... A45: Back to the Future | B45: =COUNTIF(Collection!$E$5:$E$500,A45) | C45: 3 | D45: =IF(C45="","",MAX(C45-B45,0)) | E45: =IF(C45="","",MIN(B45/C45,1))
A46: MCU | B46: =COUNTIF(Collection!$E$5:$E$500,A46) | D46: =IF(C46="","",MAX(C46-B46,0)) | E46: =IF(C46="","",MIN(B46/C46,1))
A47: The Dark Knight Trilogy | B47: =COUNTIF(Collection!$E$5:$E$500,A47) | C47: 3 | D47: =IF(C47="","",MAX(C47-B47,0)) | E47: =IF(C47="","",MIN(B47/C47,1))

Sheet Actors
A1: 🎭 ACTORS
A2: Search or filter this sheet by actor name to see every film in your collection where they appear in the top five billed cast.
A4: Actor | B4: Films Owned | C4: Earliest Film | D4: Latest Film | E4: Films in Collection | F4: Film IDs
A5: Hugh Jackman | B5: 12 | C5: 2000 | D5: 2024 | E5: Deadpool & Wolverine, The Greatest Showman, Les Misérables, Logan, The Prestige, Prisoners, X-Men: Days of Future Past, X-Men Origins: Wolverine, X-Men, X2: X-Men United, X-Men: The Last Stand, The Wolverine | F5: F0078, F0127, F0199, F0201, F0257, F0258, F0341, F0343, F0344, F0345, F0346, F0347
A6: Tom Cruise | B6: 12 | C6: 1996 | D6: 2025 | E6: Jack Reacher, Mission: Impossible, Mission: Impossible II, Mission: Impossible III, Mission: Impossible - Ghost Protocol, Mission: Impossible - Rogue Nation, Mission: Impossible - Fallout, Mission: Impossible - Dead Reckoning Part One, Mission: Impossible - The Final Reckoning, Oblivion, War of the Worlds, Tropic Thunder | F6: F0171, F0221, F0222, F0223, F0224, F0225, F0226, F0227, F0228, F0239, F0332, F0324
A7: Ian McKellen | B7: 10 | C7: 2000 | D7: 2014 | E7: The Hobbit: An Unexpected Journey, The Hobbit: The Desolation of Smaug, The Hobbit: The Battle of the Five Armies, The Lord of the Rings: The Fellowship of the Ring, The Lord of the Rings: The Two Towers, The Lord of the Rings: The Return of the King, X-Men: Days of Future Past, X-Men, X2: X-Men United, X-Men: The Last Stand | F7: F0150, F0151, F0152, F0203, F0204, F0205, F0341, F0344, F0345, F0346
A8: Matt Damon | B8: 16 | C8: 1997 | D8: 2023 | E8: The Bourne Identity, The Bourne Supremacy, The Bourne Ultimatum, The Departed, Elysium, Good Will Hunting, Green Zone, The Martian, Oppenheimer, True Grit, Dogma, Deadpool 2, Happy Feet Two, Interstellar, Jason bourne, Le Mans ‘66 | F8: F0053, F0054, F0055, F0081, F0093, F0124, F0129, F0213, F0242, F0325, F0351, F0077, F0145, F0168, F0358, F0393
A9: Robert Downey Jr. | B9: 11 | C9: 2007 | D9: 2023 | E9: The Avengers, Avengers: Infinity War, Avengers: Endgame, Due Date, Iron Man 3, Oppenheimer, Sherlock Holmes, Sherlock Holmes: A Game of Shadows, Tropic Thunder, Zodiac, Chef | F9: F0029, F0030, F0031, F0091, F0169, F0242, F0278, F0279, F0324, F0350, F0065
A10: Simon Pegg | B10: 14 | C10: 2004 | D10: 2025 | E10: Shaun of the Dead, Hot Fuzz, The World's End, Ice Age: Dawn of the Dinosaurs, Mission: Impossible - Ghost Protocol, Mission: Impossible - Rogue Nation, Mission: Impossible - Fallout, Mission: Impossible - Dead Reckoning Part One, Mission: Impossible - The Final Reckoning, Paul, Mission: Impossible III, Star Trek, Star Wars: The Force Awakens, Ready player one | F10: F0070, F0071, F0072, F0161, F0224, F0225, F0226, F0227, F0228, F0245, F0223, F0291, F0298, F0352
A11: Emma Watson | B11: 9 | C11: 2001 | D11: 2014 | E11: Harry Potter and the Philosopher's Stone, Harry Potter and the Chamber of Secrets, Harry Potter and the Prisoner of Azkaban, Harry Potter and the Goblet of Fire, Harry Potter and the Order of the Phoenix, Harry Potter and the Half-Blood Prince, Harry Potter and the Deathly Hallows: Part 1, Harry Potter and the Deathly Hallows: Part 2, Noah | F11: F0137, F0138, F0139, F0140, F0141, F0142, F0143, F0144, F0238
A12: Jason Statham | B12: 10 | C12: 2008 | D12: 2023 | E12: The Bank Job, The Expendables, The Expendables 2, The Expendables 3, Furious 7, The Fate of the Furious, Fast & Furious Presents: Hobbs & Shaw, Hummingbird, Spy, Fast X | F12: F0040, F0095, F0096, F0097, F0107, F0108, F0111, F0156, F0290, F0110
A13: Vin Diesel | B13: 10 | C13: 2001 | D13: 2023 | E13: The Fast and the Furious, Fast & Furious, Fast Five, Fast & Furious 6, Furious 7, The Fate of the Furious, F9: The Fast Saga, Fast X, Riddick, Avengers: Infinity War | F13: F0101, F0104, F0105, F0106, F0107, F0108, F0109, F0110, F0264, F0030
A14: Brad Pitt | B14: 10 | C14: 1995 | D14: 2025 | E14: F1, Fight Club, Fury, Inglourious Basterds, Killing Them Softly, Mr. & Mrs. Smith, Once Upon a Time… in Hollywood, Se7en, Deadpool 2, Happy Feet Two | F14: F0098, F0112, F0117, F0166, F0187, F0231, F0241, F0276, F0077, F0145
A15: Chris Pratt | B15: 10 | C15: 2012 | D15: 2023 | E15: Delivery Man, Jurassic World, Jurassic World: Fallen Kingdom, Jurassic World Dominion, The Lego Movie, The Lego Movie 2: The Second Part, The Magnificent Seven, The Super Mario Bros. Movie, Avengers: Infinity War, Zero Dark Thirty | F15: F0080, F0179, F0180, F0181, F0195, F0196, F0207, F0212, F0030, F0349
A16: Daniel Radcliffe | B16: 8 | C16: 2001 | D16: 2011 | E16: Harry Potter and the Philosopher's Stone, Harry Potter and the Chamber of Secrets, Harry Potter and the Prisoner of Azkaban, Harry Potter and the Goblet of Fire, Harry Potter and the Order of the Phoenix, Harry Potter and the Half-Blood Prince, Harry Potter and the Deathly Hallows: Part 1, Harry Potter and the Deathly Hallows: Part 2 | F16: F0137, F0138, F0139, F0140, F0141, F0142, F0143, F0144
... A481: Dan Fogler | B481: 2 | C481: 2016 | D481: 2018 | E481: Fantastic Beasts and Where to Find Them, Fantastic beasts: the crimes of grindelwald | F481: F0100, F0360
A482: Dan O'Herlihy | B482: 1 | E482: RoboCop | F482: F0268
A483: Daniel Brühl | B483: 3 | C483: 2007 | D483: 2013 | E483: Rush, The Bourne Ultimatum, Inglourious Basterds | F483: F0270, F0055, F0166
A484: Daniel Henney | B484: 2 | C484: 2009 | D484: 2014 | E484: Big Hero 6, X-Men Origins: Wolverine | F484: F0048, F0343
A485: Daniel Mays | B485: 2 | C485: 2008 | D485: 2019 | E485: The Bank Job, 1917 | F485: F0040, F0356
A486: Daniel Olbrychski | B486: 1 | C486: 2010 | D486: 2010 | E486: Salt | F486: F0273
A487: Daniella Pineda | B487: 2 | C487: 2018 | D487: 2022 | E487: Jurassic World: Fallen Kingdom, Jurassic World Dominion | F487: F0180, F0181
A488: Danny Huston | B488: 2 | C488: 2009 | D488: 2010 | E488: X-Men Origins: Wolverine, Robin Hood | F488: F0343, F0267
A489: Dave Bautista | B489: 8 | C489: 2013 | D489: 2024 | E489: Riddick, Spectre, Avengers: Infinity War, Avengers: Endgame, blade runner 2049, dune, dune part two, dune | F489: F0264, F0004, F0030, F0031, F0366, F0367, F0368
A490: Dave Foley | B490: 2 | C490: 1998 | D490: 2013 | E490: A Bug's Life, Monsters University | F490: F0012, F0230
A491: Dave Franco | B491: 3 | C491: 2007 | D491: 2014 | E491: 21 Jump Street, The Lego Movie, Superbad | F491: F0007, F0195, F0303
A492: David Corenswet | B492: 1 | C492: 2025 | D492: 2025 | E492: Superman | F492: F0304
A493: David Harris | B493: 1 | C493: 1979 | D493: 1979 | E493: The Warriors | F493: F0334
A494: David Huddleston | B494: 1 | C494: 1998 | D494: 1998 | E494: The Big Lebowski | F494: F0049
... A781: Mélanie Laurent | B781: 1 | C781: 2009 | D781: 2009 | E781: Inglourious Basterds | F781: F0166
A782: Nancy Allen | B782: 1 | E782: RoboCop | F782: F0268
A783: Naomi Watts | B783: 1 | C783: 2005 | D783: 2005 | E783: King Kong | F783: F0188
A784: Nathalie Baye | B784: 1 | C784: 2002 | D784: 2002 | E784: Catch Me If You Can | F784: F0064
A785: Nathalie Boltt | B785: 1 | C785: 2009 | D785: 2009 | E785: District 9 | F785: F0088
A786: Nathalie Kelley | B786: 1 | C786: 2006 | D786: 2006 | E786: The Fast and the Furious: Tokyo Drift | F786: F0103
A787: Nathan Lane | B787: 1 | C787: 1994 | D787: 1994 | E787: The Lion King | F787: F0200
A788: Neil Brown Jr. | B788: 3 | C788: 2009 | D788: 2015 | E788: Straight Outta Compton, Battle: Los Angeles, Fast & Furious | F788: F0301, F0046, F0104
A789: Neil Patrick Harris | B789: 5 | C789: 2013 | D789: 2022 | E789: The Smurfs 2, A Million Ways to Die in the West, Cloudy with a Chance of Meatballs 2, Unbearable weight of massive talent, Unbearable weight of massive talent | F789: F0282, F0021, F0067, F0388
A790: Nev Scharrel | B790: 1 | C790: 2017 | D790: 2017 | E790: Despicable Me 3 | F790: F0084
A791: Nick Nolte | B791: 3 | C791: 2008 | D791: 2014 | E791: Warrior, Noah, Tropic Thunder | F791: F0333, F0238, F0324
A792: Nicola Peltz Beckham | B792: 1 | C792: 2014 | D792: 2014 | E792: Transformers: Age of Extinction | F792: F0319
A793: Nicole Kidman | B793: 2 | C793: 2011 | D793: 2014 | E793: Just Go with It, Paddington | F793: F0183, F0244
A794: Nikki Reed | B794: 1 | C794: 2011 | D794: 2011 | E794: Catch.44 | F794: F0063
... A825: Peter Sohn | B825: 1 | C825: 2013 | D825: 2013 | E825: Monsters University | F825: F0230
A826: Peter Weller | B826: 1 | E826: RoboCop | F826: F0268
A827: Philip Baker Hall | B827: 3 | C827: 2007 | D827: 2011 | E827: 50/50, Rush Hour 3, Zodiac | F827: F0011, F0271, F0350
A828: Philip Seymour Hoffman | B828: 6 | C828: 1998 | D828: 2016 | E828: Mission: Impossible III, The Big Lebowski, The Hunger Games: Mockingjay - Part 1, Catching fire, Mockingjay part 2, Catching fire | F828: F0223, F0049, F0158, F0382, F0383, F0384
A829: Phylicia Rashād | B829: 1 | C829: 2015 | D829: 2015 | E829: Creed | F829: F0074
A830: Phyllis Diller | B830: 1 | C830: 1998 | D830: 1998 | E830: A Bug's Life | F830: F0012
A831: Phyllis Smith | B831: 2 | C831: 2011 | D831: 2015 | E831: Inside Out, Bad Teacher | F831: F0167, F0039
A832: Pierce Brosnan | B832: 2 | C832: 2008 | D832: 2013 | E832: Mamma Mia!, The World's End | F832: F0209, F0072
A833: Pink | B833: 1 | C833: 2011 | D833: 2011 | E833: Happy Feet Two | F833: F0145
A834: Piper Perabo | B834: 1 | C834: 2006 | D834: 2006 | E834: The Prestige | F834: F0257
A835: Plan B | B835: 1 | C835: 2012 | D835: 2012 | E835: The Sweeney | F835: F0305
A836: Quinton 'Rampage' Jackson | B836: 1 | C836: 2010 | D836: 2010 | E836: The A-Team | F836: F0026
A837: Rachel Bilson | B837: 1 | C837: 2008 | D837: 2008 | E837: Jumper | F837: F0175
A838: Rachel Brosnahan | B838: 1 | C838: 2025 | D838: 2025 | E838: Superman | F838: F0304
... A867: Ron Dennis | B867: 1 | C867: 2010 | D867: 2010 | E867: Senna | F867: F0275
A868: Ronny Cox | B868: 1 | E868: RoboCop | F868: F0268
A869: Rooney Mara | B869: 1 | C869: 2011 | D869: 2011 | E869: The Girl with the Dragon Tattoo | F869: F0120
A870: Rory Kinnear | B870: 5 | C870: 2008 | D870: 2021 | E870: The Imitation Game, Quantum of Solace, Skyfall, Spectre, No Time to Die | F870: F0162, F0002, F0003, F0004, F0005
A871: Rosamund Pike | B871: 2 | C871: 2012 | D871: 2013 | E871: Jack Reacher, The World's End | F871: F0171, F0072
A872: Rosario Dawson | B872: 1 | C872: 2017 | D872: 2017 | E872: The Lego Batman Movie | F872: F0193
A873: Rosemary Harris | B873: 3 | C873: 2002 | D873: 2007 | E873: Spider-Man 2, Spider-Man, Spider-Man 3 | F873: F0288, F0287, F0289
A874: Rosie Huntington-Whiteley | B874: 2 | C874: 2011 | D874: 2015 | E874: Transformers: Dark of the Moon, Mad max fury road | F874: F0318, F0354
A875: Rosie Perez | B875: 1 | C875: 2008 | D875: 2008 | E875: Pineapple Express | F875: F0247
A876: Roxanne McKee | B876: 1 | C876: 2014 | D876: 2014 | E876: The Legend of Hercules | F876: F0148
A877: Ruby Barnhill | B877: 1 | C877: 2016 | D877: 2016 | E877: The BFG | F877: F0047
A878: Rufus Sewell | B878: 1 | C878: 2014 | D878: 2014 | E878: Hercules | F878: F0147
A879: Rupert Friend | B879: 1 | C879: 2025 | D879: 2025 | E879: Jurassic World Rebirth | F879: F0182
A880: Ryan Dunn | B880: 1 | C880: 2010 | D880: 2010 | E880: Jackass 3D | F880: F0172
... A5778: Joel Kinnaman | B5778: 2 | C5778: 2012 | D5778: 2012 | E5778: RoboCop, Safe House | F5778: F0268, F0272
A5779: Abbie Cornish | B5779: 1 | E5779: RoboCop | F5779: F0268
A5780: Jackie Earle Haley | B5780: 1 | E5780: RoboCop | F5780: F0268
A5781: Michael Kenneth Williams | B5781: 1 | E5781: RoboCop | F5781: F0268
A5782: Marianne Jean-Baptiste | B5782: 1 | E5782: RoboCop | F5782: F0268
A5783: Aimee Garcia | B5783: 1 | E5783: RoboCop | F5783: F0268
A5784: Douglas Urbanski | B5784: 1 | E5784: RoboCop | F5784: F0268
A5785: John Paul Ruttan | B5785: 1 | E5785: RoboCop | F5785: F0268
A5786: Patrick Garrow | B5786: 1 | E5786: RoboCop | F5786: F0268
A5787: K.C. Collins | B5787: 1 | E5787: RoboCop | F5787: F0268
A5788: Maura Grierson | B5788: 1 | E5788: RoboCop | F5788: F0268
A5789: Stewart Arnott | B5789: 1 | E5789: RoboCop | F5789: F0268
A5790: Matt Cooke | B5790: 1 | E5790: RoboCop | F5790: F0268
... A5800: Rick Hughes | B5800: 1 | E5800: RoboCop | F5800: F0268
A5801: Tom Bennett | B5801: 1 | C5801: 2019 | D5801: 2019 | E5801: Rocketman | F5801: F0269
A5802: Matthew Illesley | B5802: 1 | C5802: 2019 | D5802: 2019 | E5802: Rocketman | F5802: F0269
A5803: Kit Connor | B5803: 2 | C5803: 2018 | D5803: 2019 | E5803: Rocketman, Ready player one | F5803: F0269, F0352
A5804: Charlie Rowe | B5804: 1 | C5804: 2019 | D5804: 2019 | E5804: Rocketman | F5804: F0269
A5805: Peter O'Hanlon | B5805: 1 | C5805: 2019 | D5805: 2019 | E5805: Rocketman | F5805: F0269
A5806: Ross Farrelly | B5806: 1 | C5806: 2019 | D5806: 2019 | E5806: Rocketman | F5806: F0269
A5807: Evan Walsh | B5807: 1 | C5807: 2019 | D5807: 2019 | E5807: Rocketman | F5807: F0269
A5808: Sharmina Harrower | B5808: 1 | C5808: 2019 | D5808: 2019 | E5808: Rocketman | F5808: F0269
A5809: Ophelia Lovibond | B5809: 1 | C5809: 2019 | D5809: 2019 | E5809: Rocketman | F5809: F0269
A5810: Celinde Schoenmaker | B5810: 1 | C5810: 2019 | D5810: 2019 | E5810: Rocketman | F5810: F0269
A5811: Harriet Walter | B5811: 1 | C5811: 2019 | D5811: 2019 | E5811: Rocketman | F5811: F0269
A5812: Sharon D. Clarke | B5812: 1 | C5812: 2019 | D5812: 2019 | E5812: Rocketman | F5812: F0269
... A7164: Monica Hampton | B7164: 1 | C7164: 1999 | D7164: 1999 | E7164: Dogma | F7164: F0351
A7165: Robert DoQui | B7165: 1 | E7165: RoboCop | F7165: F0268
A7166: Ray Wise | B7166: 1 | E7166: RoboCop | F7166: F0268
...

Sheet Directors
A1: 🎥 DIRECTORS
A2: Search or filter this sheet by director to see every film in your collection credited to them.
A4: Director | B4: Films Owned | C4: Earliest Film | D4: Latest Film | E4: Films in Collection | F4: Film IDs
A5: Michael Bay | B5: 8 | C5: 1995 | D5: 2017 | E5: Bad Boys, Bad Boys II, Pearl Harbor, Transformers, Transformers: Revenge of the Fallen, Transformers: Dark of the Moon, Transformers: Age of Extinction, Transformers: The Last Knight | F5: F0036, F0037, F0246, F0316, F0317, F0318, F0319, F0320
A6: Christopher Nolan | B6: 8 | C6: 2005 | D6: 2023 | E6: Batman Begins, The Dark Knight, The Dark Knight Rises, Inception, Interstellar, Oppenheimer, The Prestige, Tenet | F6: F0043, F0044, F0045, F0165, F0168, F0242, F0257, F0387
A7: Peter Jackson | B7: 7 | C7: 2001 | D7: 2014 | E7: The Hobbit: An Unexpected Journey, The Hobbit: The Desolation of Smaug, The Hobbit: The Battle of the Five Armies, King Kong, The Lord of the Rings: The Fellowship of the Ring, The Lord of the Rings: The Two Towers, The Lord of the Rings: The Return of the King | F7: F0150, F0151, F0152, F0188, F0203, F0204, F0205
A8: Ridley Scott | B8: 8 | C8: 1979 | D8: 2017 | E8: Alien, Black Hawk Down, Body of Lies, The Martian, Prometheus, Robin Hood, alien covenant, blade runner | F8: F0015, F0050, F0051, F0213, F0259, F0267, F0361, F0365
A9: Bryan Singer | B9: 5 | C9: 2000 | D9: 2018 | E9: Bohemian Rhapsody, X-Men: Days of Future Past, X-Men: Apocalypse, X-Men, X2: X-Men United | F9: F0052, F0341, F0342, F0344, F0345
A10: Christopher McQuarrie | B10: 5 | C10: 2012 | D10: 2025 | E10: Jack Reacher, Mission: Impossible - Rogue Nation, Mission: Impossible - Fallout, Mission: Impossible - Dead Reckoning Part One, Mission: Impossible - The Final Reckoning | F10: F0171, F0225, F0226, F0227, F0228
A11: David Fincher | B11: 5 | C11: 1992 | D11: 2011 | E11: Alien³, Fight Club, The Girl with the Dragon Tattoo, Se7en, Zodiac | F11: F0017, F0112, F0120, F0276, F0350
A12: David Yates | B12: 6 | C12: 2007 | D12: 2018 | E12: Fantastic Beasts and Where to Find Them, Harry Potter and the Order of the Phoenix, Harry Potter and the Half-Blood Prince, Harry Potter and the Deathly Hallows: Part 1, Harry Potter and the Deathly Hallows: Part 2, Fantastic beasts: the crimes of grindelwald | F12: F0100, F0141, F0142, F0143, F0144, F0360
A13: J.J. Abrams | B13: 5 | C13: 2006 | D13: 2019 | E13: Mission: Impossible III, Star Trek, Star Wars: The Force Awakens, Star Wars: The Rise of Skywalker, Super 8 | F13: F0223, F0291, F0298, F0300, F0302
A14: Justin Lin | B14: 5 | C14: 2006 | D14: 2021 | E14: The Fast and the Furious: Tokyo Drift, Fast & Furious, Fast Five, Fast & Furious 6, F9: The Fast Saga | F14: F0103, F0104, F0105, F0106, F0109
A15: Steven Spielberg | B15: 6 | C15: 1993 | D15: 2018 | E15: The BFG, Catch Me If You Can, Jurassic Park, The Lost World: Jurassic Park, War of the Worlds, Ready player one | F15: F0047, F0064, F0176, F0177, F0332, F0352
A16: Carlos Saldanha | B16: 4 | C16: 2006 | D16: 2014 | E16: Ice Age: The Meltdown, Ice Age: Dawn of the Dinosaurs, Rio, Rio 2 | F16: F0160, F0161, F0265, F0266
... A206: Patrick Tatopoulos | B206: 1 | C206: 2009 | D206: 2009 | E206: Underworld: Rise of the Lycans | F206: F0327
A207: Paul Verhoeven | B207: 1 | E207: RoboCop | F207: F0268
A208: Peter Berg | B208: 1 | C208: 2013 | D208: 2013 | E208: Lone Survivor | F208: F0202
A209: Phil Johnston | B209: 1 | C209: 2018 | D209: 2018 | E209: Ralph Breaks the Internet | F209: F0337
A210: Phillip Noyce | B210: 1 | C210: 2010 | D210: 2010 | E210: Salt | F210: F0273
A211: Phyllida Lloyd | B211: 1 | C211: 2008 | D211: 2008 | E211: Mamma Mia! | F211: F0209
A212: Pierre Leduc | B212: 1 | C212: 2023 | D212: 2023 | E212: The Super Mario Bros. Movie | F212: F0212
A213: Pierre Morel | B213: 1 | C213: 2008 | D213: 2008 | E213: Taken | F213: F0306
A214: Raja Gosnell | B214: 1 | C214: 2013 | D214: 2013 | E214: The Smurfs 2 | F214: F0282
A215: Renny Harlin | B215: 1 | C215: 2014 | D215: 2014 | E215: The Legend of Hercules | F215: F0148
A216: Rian Johnson | B216: 1 | C216: 2017 | D216: 2017 | E216: Star Wars: The Last Jedi | F216: F0299
A217: Richard Donner | B217: 1 | C217: 2025 | D217: 2025 | E217: Superman | F217: F0304
A218: Richard Loncraine | B218: 1 | C218: 2006 | D218: 2006 | E218: Firewall | F218: F0114
A219: Richard Marquand | B219: 1 | C219: 1983 | D219: 1983 | E219: Star Wars: Episode VI – Return of the Jedi | F219: F0297
... A254: Peter MacDonald | B254: 1 | C254: 2008 | D254: 2008 | E254: Rambo | F254: F0261
A255: José Padilha | B255: 1 | E255: RoboCop | F255: F0268
A256: James Gunn | B256: 1 | C256: 2025 | D256: 2025 | E256: Superman | F256: F0304
A257: Thomas C. Grane | B257: 1 | C257: 2000 | D257: 2000 | E257: X-Men | F257: F0344
A1001: Paul Thomas Anderson | B1001: 1 | C1001: 2025 | D1001: 2025 | E1001: One battle after another | F1001: F0353
A1002: Baltasar Kormákur | B1002: 1 | C1002: 2013 | D1002: 2013 | E1002: 2 guns | F1002: F0355
A1003: Fede Álvarez | B1003: 1 | C1003: 2025 | D1003: 2025 | E1003: alien romulus | F1003: F0362
A1004: Peter Farrelly | B1004: 2 | C1004: 2018 | D1004: 2018 | E1004: green book, green book | F1004: F0371
A1005: Chad Stahelski | B1005: 5 | C1005: 2014 | D1005: 2023 | E1005: john wick, john wick chapter 2, John wick chapter 3, John wick chapter 4, john wick chapter 2 | F1005: F0374, F0375, F0391, F0392
A1006: Jeff Fowler | B1006: 2 | C1006: 2020 | D1006: 2025 | E1006: sonic the hedgehog, sonic the hedgehog 3 | F1006: F0378, F0379
A1007: Simon Kinberg | B1007: 1 | C1007: 2022 | D1007: 2022 | E1007: X-men dark phoenix | F1007: F0380
A1008: Ivan Reitman | B1008: 1 | C1008: 2001 | D1008: 2001 | E1008: Evolution | F1008: F0381
A1009: Tom Gormican | B1009: 2 | C1009: 2022 | D1009: 2022 | E1009: Unbearable weight of massive talent, Unbearable weight of massive talent | F1009: F0388

Sheet Awards
A1: 🏆 ACADEMY AWARDS
A2: Oscar history for every film in your collection. Filter by Best Picture, wins, acting, directing, writing or animated feature.
A4: Film ID | B4: Title | C4: Year | D4: Nominations | E4: Wins | F4: Best Picture | G4: Acting Noms | H4: Acting Wins | I4: Acting Winner(s) | J4: Directing Noms | K4: Directing Wins | L4: Director Winner(s) | M4: Writing Noms | N4: Writing Wins | O4: Animated Feature | P4: Winning Categories | Q4: All Nominated Categories | R4: Source
A5: F0001 | B5: Casino Royale | C5: 2006 | D5: 0 | E5: 0 | G5: 0 | H5: 0 | J5: 0 | K5: 0 | M5: 0 | N5: 0 | R5: https://github.com/DLu/oscar_data
A6: F0002 | B6: Quantum of Solace | C6: 2008 | D6: 0 | E6: 0 | G6: 0 | H6: 0 | J6: 0 | K6: 0 | M6: 0 | N6: 0 | R6: https://github.com/DLu/oscar_data
A7: F0003 | B7: Skyfall | C7: 2012 | D7: 5 | E7: 2 | G7: 0 | H7: 0 | J7: 0 | K7: 0 | M7: 0 | N7: 0 | P7: MUSIC (Original Song); SOUND EDITING | Q7: CINEMATOGRAPHY; MUSIC (Original Score); MUSIC (Original Song); SOUND EDITING; SOUND MIXING | R7: https://github.com/DLu/oscar_data
A8: F0004 | B8: Spectre | C8: 2015 | D8: 1 | E8: 1 | G8: 0 | H8: 0 | J8: 0 | K8: 0 | M8: 0 | N8: 0 | P8: MUSIC (Original Song) | Q8: MUSIC (Original Song) | R8: https://github.com/DLu/oscar_data
A9: F0005 | B9: No Time to Die | C9: 2021 | D9: 3 | E9: 1 | G9: 0 | H9: 0 | J9: 0 | K9: 0 | M9: 0 | N9: 0 | P9: MUSIC (Original Song) | Q9: MUSIC (Original Song); SOUND MIXING; VISUAL EFFECTS | R9: https://github.com/DLu/oscar_data
A10: F0006 | B10: 2012 | C10: 2009 | D10: 0 | E10: 0 | G10: 0 | H10: 0 | J10: 0 | K10: 0 | M10: 0 | N10: 0 | R10: https://github.com/DLu/oscar_data
A11: F0007 | B11: 21 Jump Street | C11: 2012 | D11: 0 | E11: 0 | G11: 0 | H11: 0 | J11: 0 | K11: 0 | M11: 0 | N11: 0 | R11: https://github.com/DLu/oscar_data
A12: F0008 | B12: 22 Jump Street | C12: 2014 | D12: 0 | E12: 0 | G12: 0 | H12: 0 | J12: 0 | K12: 0 | M12: 0 | N12: 0 | R12: https://github.com/DLu/oscar_data
A13: F0009 | B13: 30 Minutes or Less | C13: 2011 | D13: 0 | E13: 0 | G13: 0 | H13: 0 | J13: 0 | K13: 0 | M13: 0 | N13: 0 | R13: https://github.com/DLu/oscar_data
A14: F0010 | B14: 44 Inch Chest | C14: 2009 | D14: 0 | E14: 0 | G14: 0 | H14: 0 | J14: 0 | K14: 0 | M14: 0 | N14: 0 | R14: https://github.com/DLu/oscar_data
A15: F0011 | B15: 50/50 | C15: 2011 | D15: 0 | E15: 0 | G15: 0 | H15: 0 | J15: 0 | K15: 0 | M15: 0 | N15: 0 | R15: https://github.com/DLu/oscar_data
A16: F0012 | B16: A Bug's Life | C16: 1998 | D16: 1 | E16: 0 | G16: 0 | H16: 0 | J16: 0 | K16: 0 | M16: 0 | N16: 0 | Q16: MUSIC (Original Song Score or Adaptation Score) | R16: https://github.com/DLu/oscar_data
A17: F0013 | B17: The Accountant | C17: 2016 | D17: 0 | E17: 0 | G17: 0 | H17: 0 | J17: 0 | K17: 0 | M17: 0 | N17: 0 | R17: https://github.com/DLu/oscar_data
A18: F0014 | B18: Alan Partridge: Alpha Papa | C18: 2013 | D18: 0 | E18: 0 | G18: 0 | H18: 0 | J18: 0 | K18: 0 | M18: 0 | N18: 0 | R18: https://github.com/DLu/oscar_data
A19: F0015 | B19: Alien | C19: 1979 | D19: 2 | E19: 1 | G19: 0 | H19: 0 | J19: 0 | K19: 0 | M19: 0 | N19: 0 | P19: VISUAL EFFECTS | Q19: ART DIRECTION; VISUAL EFFECTS | R19: https://github.com/DLu/oscar_data
A20: F0016 | B20: Aliens | C20: 1986 | D20: 7 | E20: 2 | G20: 1 | H20: 0 | J20: 0 | K20: 0 | M20: 0 | N20: 0 | P20: SOUND EDITING; VISUAL EFFECTS | Q20: ACTRESS IN A LEADING ROLE; ART DIRECTION; FILM EDITING; MUSIC (Original Score); SOUND MIXING; SOUND EDITING; VISUAL EFFECTS | R20: https://github.com/DLu/oscar_data
A21: F0017 | B21: Alien³ | C21: 1992 | D21: 0 | E21: 0 | G21: 0 | H21: 0 | J21: 0 | K21: 0 | M21: 0 | N21: 0 | R21: https://github.com/DLu/oscar_data
A22: F0018 | B22: Alien Resurrection | C22: 1997 | D22: 0 | E22: 0 | G22: 0 | H22: 0 | J22: 0 | K22: 0 | M22: 0 | N22: 0 | R22: https://github.com/DLu/oscar_data
A23: F0019 | B23: The Amazing Spider-Man | C23: 2012 | D23: 0 | E23: 0 | G23: 0 | H23: 0 | J23: 0 | K23: 0 | M23: 0 | N23: 0 | R23: https://github.com/DLu/oscar_data
A24: F0020 | B24: American Hustle | C24: 2013 | D24: 10 | E24: 0 | F24: Nominated | G24: 4 | H24: 0 | J24: 1 | K24: 0 | M24: 1 | N24: 0 | Q24: ACTOR IN A LEADING ROLE; ACTOR IN A SUPPORTING ROLE; ACTRESS IN A LEADING ROLE; ACTRESS IN A SUPPORTING ROLE; COSTUME DESIGN; DIRECTING; FILM EDITING; BEST PICTURE; ART DIRECTION; WRITING (Original Screenplay) | R24: https://github.com/DLu/oscar_data
A25: F0021 | B25: A Million Ways to Die in the West | C25: 2014 | D25: 0 | E25: 0 | G25: 0 | H25: 0 | J25: 0 | K25: 0 | M25: 0 | N25: 0 | R25: https://github.com/DLu/oscar_data
A26: F0022 | B26: Anchorman: The Legend of Ron Burgundy | C26: 2004 | D26: 0 | E26: 0 | G26: 0 | H26: 0 | J26: 0 | K26: 0 | M26: 0 | N26: 0 | R26: https://github.com/DLu/oscar_data
A27: F0023 | B27: Angels & Demons | C27: 2009 | D27: 0 | E27: 0 | G27: 0 | H27: 0 | J27: 0 | K27: 0 | M27: 0 | N27: 0 | R27: https://github.com/DLu/oscar_data
A28: F0024 | B28: Anuvahood | C28: 2011 | D28: 0 | E28: 0 | G28: 0 | H28: 0 | J28: 0 | K28: 0 | M28: 0 | N28: 0 | R28: https://github.com/DLu/oscar_data
A29: F0025 | B29: Argo | C29: 2012 | D29: 7 | E29: 3 | F29: Winner | G29: 1 | H29: 0 | J29: 0 | K29: 0 | M29: 1 | N29: 1 | P29: FILM EDITING; BEST PICTURE; WRITING (Adapted Screenplay) | Q29: ACTOR IN A SUPPORTING ROLE; FILM EDITING; MUSIC (Original Score); BEST PICTURE; SOUND EDITING; SOUND MIXING; WRITING (Adapted Screenplay) | R29: https://github.com/DLu/oscar_data
A30: F0026 | B30: The A-Team | C30: 2010 | D30: 0 | E30: 0 | G30: 0 | H30: 0 | J30: 0 | K30: 0 | M30: 0 | N30: 0 | R30: https://github.com/DLu/oscar_data
A31: F0027 | B31: Attack the Block | C31: 2011 | D31: 0 | E31: 0 | G31: 0 | H31: 0 | J31: 0 | K31: 0 | M31: 0 | N31: 0 | R31: https://github.com/DLu/oscar_data
A32: F0028 | B32: Avatar | C32: 2009 | D32: 9 | E32: 3 | F32: Nominated | G32: 0 | H32: 0 | J32: 1 | K32: 0 | M32: 0 | N32: 0 | P32: ART DIRECTION; CINEMATOGRAPHY; VISUAL EFFECTS | Q32: ART DIRECTION; CINEMATOGRAPHY; DIRECTING; FILM EDITING; MUSIC (Original Score); BEST PICTURE; SOUND EDITING; SOUND MIXING; VISUAL EFFECTS | R32: https://github.com/DLu/oscar_data
A33: F0029 | B33: The Avengers | C33: 2012 | D33: 1 | E33: 0 | G33: 0 | H33: 0 | J33: 0 | K33: 0 | M33: 0 | N33: 0 | Q33: VISUAL EFFECTS | R33: https://github.com/DLu/oscar_data
A34: F0030 | B34: Avengers: Infinity War | C34: 2018 | D34: 1 | E34: 0 | G34: 0 | H34: 0 | J34: 0 | K34: 0 | M34: 0 | N34: 0 | Q34: VISUAL EFFECTS | R34: https://github.com/DLu/oscar_data
A35: F0031 | B35: Avengers: Endgame | C35: 2019 | D35: 1 | E35: 0 | G35: 0 | H35: 0 | J35: 0 | K35: 0 | M35: 0 | N35: 0 | Q35: VISUAL EFFECTS | R35: https://github.com/DLu/oscar_data
A36: F0032 | B36: Baby Driver | C36: 2017 | D36: 3 | E36: 0 | G36: 0 | H36: 0 | J36: 0 | K36: 0 | M36: 0 | N36: 0 | Q36: FILM EDITING; SOUND EDITING; SOUND MIXING | R36: https://github.com/DLu/oscar_data
A37: F0033 | B37: Back to the Future | C37: 1985 | D37: 4 | E37: 1 | G37: 0 | H37: 0 | J37: 0 | K37: 0 | M37: 1 | N37: 0 | P37: SOUND EDITING | Q37: MUSIC (Original Song); SOUND MIXING; SOUND EDITING; WRITING (Original Screenplay) | R37: https://github.com/DLu/oscar_data
A38: F0034 | B38: Back to the Future Part II | C38: 1989 | D38: 1 | E38: 0 | G38: 0 | H38: 0 | J38: 0 | K38: 0 | M38: 0 | N38: 0 | Q38: VISUAL EFFECTS | R38: https://github.com/DLu/oscar_data
A39: F0035 | B39: Back to the Future Part III | C39: 1990 | D39: 0 | E39: 0 | G39: 0 | H39: 0 | J39: 0 | K39: 0 | M39: 0 | N39: 0 | R39: https://github.com/DLu/oscar_data
A40: F0036 | B40: Bad Boys | C40: 1995 | D40: 0 | E40: 0 | G40: 0 | H40: 0 | J40: 0 | K40: 0 | M40: 0 | N40: 0 | R40: https://github.com/DLu/oscar_data
A41: F0037 | B41: Bad Boys II | C41: 2003 | D41: 0 | E41: 0 | G41: 0 | H41: 0 | J41: 0 | K41: 0 | M41: 0 | N41: 0 | R41: https://github.com/DLu/oscar_data
A42: F0038 | B42: Bad Moms | C42: 2016 | D42: 0 | E42: 0 | G42: 0 | H42: 0 | J42: 0 | K42: 0 | M42: 0 | N42: 0 | R42: https://github.com/DLu/oscar_data
A43: F0039 | B43: Bad Teacher | C43: 2011 | D43: 0 | E43: 0 | G43: 0 | H43: 0 | J43: 0 | K43: 0 | M43: 0 | N43: 0 | R43: https://github.com/DLu/oscar_data
A44: F0040 | B44: The Bank Job | C44: 2008 | D44: 0 | E44: 0 | G44: 0 | H44: 0 | J44: 0 | K44: 0 | M44: 0 | N44: 0 | R44: https://github.com/DLu/oscar_data
A45: F0041 | B45: Barbie | C45: 2023 | D45: 8 | E45: 1 | F45: Nominated | G45: 2 | H45: 0 | J45: 0 | K45: 0 | M45: 1 | N45: 0 | P45: MUSIC (Original Song) | Q45: ACTOR IN A SUPPORTING ROLE; ACTRESS IN A SUPPORTING ROLE; COSTUME DESIGN; MUSIC (Original Song); BEST PICTURE; ART DIRECTION; WRITING (Adapted Screenplay) | R45: https://github.com/DLu/oscar_data
A46: F0042 | B46: The Batman | C46: 2022 | D46: 3 | E46: 0 | G46: 0 | H46: 0 | J46: 0 | K46: 0 | M46: 0 | N46: 0 | Q46: MAKEUP AND HAIRSTYLING; SOUND MIXING; VISUAL EFFECTS | R46: https://github.com/DLu/oscar_data
A47: F0043 | B47: Batman Begins | C47: 2005 | D47: 1 | E47: 0 | G47: 0 | H47: 0 | J47: 0 | K47: 0 | M47: 0 | N47: 0 | Q47: CINEMATOGRAPHY | R47: https://github.com/DLu/oscar_data
A48: F0044 | B48: The Dark Knight | C48: 2008 | D48: 8 | E48: 2 | G48: 1 | H48: 1 | I48: Heath Ledger | J48: 0 | K48: 0 | M48: 0 | N48: 0 | P48: ACTOR IN A SUPPORTING ROLE; SOUND EDITING | Q48: ACTOR IN A SUPPORTING ROLE; ART DIRECTION; CINEMATOGRAPHY; FILM EDITING; MAKEUP AND HAIRSTYLING; SOUND EDITING; SOUND MIXING; VISUAL EFFECTS | R48: https://github.com/DLu/oscar_data
A49: F0045 | B49: The Dark Knight Rises | C49: 2012 | D49: 0 | E49: 0 | G49: 0 | H49: 0 | J49: 0 | K49: 0 | M49: 0 | N49: 0 | R49: https://github.com/DLu/oscar_data
A50: F0046 | B50: Battle: Los Angeles | C50: 2011 | D50: 0 | E50: 0 | G50: 0 | H50: 0 | J50: 0 | K50: 0 | M50: 0 | N50: 0 | R50: https://github.com/DLu/oscar_data
A51: F0047 | B51: The BFG | C51: 2016 | D51: 0 | E51: 0 | G51: 0 | H51: 0 | J51: 0 | K51: 0 | M51: 0 | N51: 0 | R51: https://github.com/DLu/oscar_data
A52: F0048 | B52: Big Hero 6 | C52: 2014 | D52: 1 | E52: 1 | G52: 0 | H52: 0 | J52: 0 | K52: 0 | M52: 0 | N52: 0 | O52: Winner | P52: ANIMATED FEATURE FILM | Q52: ANIMATED FEATURE FILM | R52: https://github.com/DLu/oscar_data
A53: F0049 | B53: The Big Lebowski | C53: 1998 | D53: 0 | E53: 0 | G53: 0 | H53: 0 | J53: 0 | K53: 0 | M53: 0 | N53: 0 | R53: https://github.com/DLu/oscar_data
A54: F0050 | B54: Black Hawk Down | C54: 2001 | D54: 4 | E54: 2 | G54: 0 | H54: 0 | J54: 1 | K54: 0 | M54: 0 | N54: 0 | P54: FILM EDITING; SOUND MIXING | Q54: CINEMATOGRAPHY; DIRECTING; FILM EDITING; SOUND MIXING | R54: https://github.com/DLu/oscar_data
A55: F0051 | B55: Body of Lies | C55: 2008 | D55: 0 | E55: 0 | G55: 0 | H55: 0 | J55: 0 | K55: 0 | M55: 0 | N55: 0 | R55: https://github.com/DLu/oscar_data
A56: F0052 | B56: Bohemian Rhapsody | C56: 2018 | D56: 5 | E56: 4 | F56: Nominated | G56: 1 | H56: 1 | I56: Rami Malek | J56: 0 | K56: 0 | M56: 0 | N56: 0 | P56: ACTOR IN A LEADING ROLE; FILM EDITING; SOUND EDITING; SOUND MIXING | Q56: ACTOR IN A LEADING ROLE; FILM EDITING; BEST PICTURE; SOUND EDITING; SOUND MIXING | R56: https://github.com/DLu/oscar_data
A57: F0053 | B57: The Bourne Identity | C57: 2002 | D57: 0 | E57: 0 | G57: 0 | H57: 0 | J57: 0 | K57: 0 | M57: 0 | N57: 0 | R57: https://github.com/DLu/oscar_data
A58: F0054 | B58: The Bourne Supremacy | C58: 2004 | D58: 0 | E58: 0 | G58: 0 | H58: 0 | J58: 0 | K58: 0 | M58: 0 | N58: 0 | R58: https://github.com/DLu/oscar_data
A59: F0055 | B59: The Bourne Ultimatum | C59: 2007 | D59: 3 | E59: 3 | G59: 0 | H59: 0 | J59: 0 | K59: 0 | M59: 0 | N59: 0 | P59: FILM EDITING; SOUND EDITING; SOUND MIXING | Q59: FILM EDITING; SOUND EDITING; SOUND MIXING | R59: https://github.com/DLu/oscar_data
A60: F0056 | B60: The Bourne Legacy | C60: 2012 | D60: 0 | E60: 0 | G60: 0 | H60: 0 | J60: 0 | K60: 0 | M60: 0 | N60: 0 | R60: https://github.com/DLu/oscar_data
A61: F0057 | B61: The Breakfast Club | C61: 1985 | D61: 0 | E61: 0 | G61: 0 | H61: 0 | J61: 0 | K61: 0 | M61: 0 | N61: 0 | R61: https://github.com/DLu/oscar_data
A62: F0058 | B62: Bridesmaids | C62: 2011 | D62: 2 | E62: 0 | G62: 1 | H62: 0 | J62: 0 | K62: 0 | M62: 1 | N62: 0 | Q62: ACTRESS IN A SUPPORTING ROLE; WRITING (Original Screenplay) | R62: https://github.com/DLu/oscar_data
A63: F0059 | B63: Brüno | C63: 2009 | D63: 0 | E63: 0 | G63: 0 | H63: 0 | J63: 0 | K63: 0 | M63: 0 | N63: 0 | R63: https://github.com/DLu/oscar_data
A64: F0060 | B64: The Bucket List | C64: 2007 | D64: 0 | E64: 0 | G64: 0 | H64: 0 | J64: 0 | K64: 0 | M64: 0 | N64: 0 | R64: https://github.com/DLu/oscar_data
A65: F0061 | B65: Bumblebee | C65: 2018 | D65: 0 | E65: 0 | G65: 0 | H65: 0 | J65: 0 | K65: 0 | M65: 0 | N65: 0 | R65: https://github.com/DLu/oscar_data
A66: F0062 | B66: Captain Phillips | C66: 2013 | D66: 6 | E66: 0 | F66: Nominated | G66: 1 | H66: 0 | J66: 0 | K66: 0 | M66: 1 | N66: 0 | Q66: ACTOR IN A SUPPORTING ROLE; FILM EDITING; BEST PICTURE; SOUND EDITING; SOUND MIXING; WRITING (Adapted Screenplay) | R66: https://github.com/DLu/oscar_data
A67: F0063 | B67: Catch.44 | C67: 2011 | D67: 0 | E67: 0 | G67: 0 | H67: 0 | J67: 0 | K67: 0 | M67: 0 | N67: 0 | R67: https://github.com/DLu/oscar_data
A68: F0064 | B68: Catch Me If You Can | C68: 2002 | D68: 2 | E68: 0 | G68: 1 | H68: 0 | J68: 0 | K68: 0 | M68: 0 | N68: 0 | Q68: ACTOR IN A SUPPORTING ROLE; MUSIC (Original Score) | R68: https://github.com/DLu/oscar_data
A69: F0065 | B69: Chef | C69: 2014 | D69: 0 | E69: 0 | G69: 0 | H69: 0 | J69: 0 | K69: 0 | M69: 0 | N69: 0 | R69: https://github.com/DLu/oscar_data
A70: F0066 | B70: Clash of the Titans | C70: 2010 | D70: 0 | E70: 0 | G70: 0 | H70: 0 | J70: 0 | K70: 0 | M70: 0 | N70: 0 | R70: https://github.com/DLu/oscar_data
A71: F0067 | B71: Cloudy with a Chance of Meatballs 2 | C71: 2013 | D71: 0 | E71: 0 | G71: 0 | H71: 0 | J71: 0 | K71: 0 | M71: 0 | N71: 0 | R71: https://github.com/DLu/oscar_data
A72: F0068 | B72: Con Air | C72: 1997 | D72: 2 | E72: 0 | G72: 0 | H72: 0 | J72: 0 | K72: 0 | M72: 0 | N72: 0 | Q72: MUSIC (Original Song); SOUND MIXING | R72: https://github.com/DLu/oscar_data
A73: F0069 | B73: Cop Out | C73: 2010 | D73: 0 | E73: 0 | G73: 0 | H73: 0 | J73: 0 | K73: 0 | M73: 0 | N73: 0 | R73: https://github.com/DLu/oscar_data
A74: F0070 | B74: Shaun of the Dead | C74: 2004 | D74: 0 | E74: 0 | G74: 0 | H74: 0 | J74: 0 | K74: 0 | M74: 0 | N74: 0 | R74: https://github.com/DLu/oscar_data
A75: F0071 | B75: Hot Fuzz | C75: 2007 | D75: 0 | E75: 0 | G75: 0 | H75: 0 | J75: 0 | K75: 0 | M75: 0 | N75: 0 | R75: https://github.com/DLu/oscar_data
A76: F0072 | B76: The World's End | C76: 2013 | D76: 0 | E76: 0 | G76: 0 | H76: 0 | J76: 0 | K76: 0 | M76: 0 | N76: 0 | R76: https://github.com/DLu/oscar_data
A77: F0073 | B77: Cowboys & Aliens | C77: 2011 | D77: 0 | E77: 0 | G77: 0 | H77: 0 | J77: 0 | K77: 0 | M77: 0 | N77: 0 | R77: https://github.com/DLu/oscar_data
A78: F0074 | B78: Creed | C78: 2015 | D78: 1 | E78: 0 | G78: 1 | H78: 0 | J78: 0 | K78: 0 | M78: 0 | N78: 0 | Q78: ACTOR IN A SUPPORTING ROLE | R78: https://github.com/DLu/oscar_data
A79: F0075 | B79: The Croods | C79: 2013 | D79: 1 | E79: 0 | G79: 0 | H79: 0 | J79: 0 | K79: 0 | M79: 0 | N79: 0 | O79: Nominated | Q79: ANIMATED FEATURE FILM | R79: https://github.com/DLu/oscar_data
A80: F0076 | B80: Deadpool | C80: 2016 | D80: 0 | E80: 0 | G80: 0 | H80: 0 | J80: 0 | K80: 0 | M80: 0 | N80: 0 | R80: https://github.com/DLu/oscar_data
A81: F0077 | B81: Deadpool 2 | C81: 2018 | D81: 0 | E81: 0 | G81: 0 | H81: 0 | J81: 0 | K81: 0 | M81: 0 | N81: 0 | R81: https://github.com/DLu/oscar_data
A82: F0078 | B82: Deadpool & Wolverine | C82: 2024 | D82: 0 | E82: 0 | G82: 0 | H82: 0 | J82: 0 | K82: 0 | M82: 0 | N82: 0 | R82: https://github.com/DLu/oscar_data
A83: F0079 | B83: Dear John | C83: 2010 | D83: 0 | E83: 0 | G83: 0 | H83: 0 | J83: 0 | K83: 0 | M83: 0 | N83: 0 | R83: https://github.com/DLu/oscar_data
A84: F0080 | B84: Delivery Man | C84: 2013 | D84: 0 | E84: 0 | G84: 0 | H84: 0 | J84: 0 | K84: 0 | M84: 0 | N84: 0 | R84: https://github.com/DLu/oscar_data
A85: F0081 | B85: The Departed | C85: 2006 | D85: 5 | E85: 4 | F85: Winner | G85: 1 | H85: 0 | J85: 1 | K85: 1 | L85: Martin Scorsese | M85: 1 | N85: 1 | P85: DIRECTING; FILM EDITING; BEST PICTURE; WRITING (Adapted Screenplay) | Q85: ACTOR IN A SUPPORTING ROLE; DIRECTING; FILM EDITING; BEST PICTURE; WRITING (Adapted Screenplay) | R85: https://github.com/DLu/oscar_data
A86: F0082 | B86: Despicable Me | C86: 2010 | D86: 0 | E86: 0 | G86: 0 | H86: 0 | J86: 0 | K86: 0 | M86: 0 | N86: 0 | R86: https://github.com/DLu/oscar_data
A87: F0083 | B87: Despicable Me 2 | C87: 2013 | D87: 2 | E87: 0 | G87: 0 | H87: 0 | J87: 0 | K87: 0 | M87: 0 | N87: 0 | O87: Nominated | Q87: ANIMATED FEATURE FILM; MUSIC (Original Song) | R87: https://github.com/DLu/oscar_data
A88: F0084 | B88: Despicable Me 3 | C88: 2017 | D88: 0 | E88: 0 | G88: 0 | H88: 0 | J88: 0 | K88: 0 | M88: 0 | N88: 0 | R88: https://github.com/DLu/oscar_data
A89: F0085 | B89: The Dictator | C89: 2012 | D89: 0 | E89: 0 | G89: 0 | H89: 0 | J89: 0 | K89: 0 | M89: 0 | N89: 0 | R89: https://github.com/DLu/oscar_data
A90: F0086 | B90: Live Free or Die Hard | C90: 2007 | D90: 0 | E90: 0 | G90: 0 | H90: 0 | J90: 0 | K90: 0 | M90: 0 | N90: 0 | R90: https://github.com/DLu/oscar_data
A91: F0087 | B91: Dirty Grandpa | C91: 2016 | D91: 0 | E91: 0 | G91: 0 | H91: 0 | J91: 0 | K91: 0 | M91: 0 | N91: 0 | R91: https://github.com/DLu/oscar_data
A92: F0088 | B92: District 9 | C92: 2009 | D92: 4 | E92: 0 | F92: Nominated | G92: 0 | H92: 0 | J92: 0 | K92: 0 | M92: 1 | N92: 0 | Q92: FILM EDITING; BEST PICTURE; VISUAL EFFECTS; WRITING (Adapted Screenplay) | R92: https://github.com/DLu/oscar_data
A93: F0089 | B93: Divergent | C93: 2014 | D93: 0 | E93: 0 | G93: 0 | H93: 0 | J93: 0 | K93: 0 | M93: 0 | N93: 0 | R93: https://github.com/DLu/oscar_data
A94: F0090 | B94: Django Unchained | C94: 2012 | D94: 5 | E94: 2 | F94: Nominated | G94: 1 | H94: 1 | I94: Christoph Waltz | J94: 0 | K94: 0 | M94: 1 | N94: 1 | P94: ACTOR IN A SUPPORTING ROLE; WRITING (Original Screenplay) | Q94: ACTOR IN A SUPPORTING ROLE; CINEMATOGRAPHY; BEST PICTURE; SOUND EDITING; WRITING (Original Screenplay) | R94: https://github.com/DLu/oscar_data
A95: F0091 | B95: Due Date | C95: 2010 | D95: 0 | E95: 0 | G95: 0 | H95: 0 | J95: 0 | K95: 0 | M95: 0 | N95: 0 | R95: https://github.com/DLu/oscar_data
A96: F0092 | B96: Elf | C96: 2003 | D96: 0 | E96: 0 | G96: 0 | H96: 0 | J96: 0 | K96: 0 | M96: 0 | N96: 0 | R96: https://github.com/DLu/oscar_data
A97: F0093 | B97: Elysium | C97: 2013 | D97: 0 | E97: 0 | G97: 0 | H97: 0 | J97: 0 | K97: 0 | M97: 0 | N97: 0 | R97: https://github.com/DLu/oscar_data
A98: F0094 | B98: Enemy of the State | C98: 1998 | D98: 0 | E98: 0 | G98: 0 | H98: 0 | J98: 0 | K98: 0 | M98: 0 | N98: 0 | R98: https://github.com/DLu/oscar_data
A99: F0095 | B99: The Expendables | C99: 2010 | D99: 0 | E99: 0 | G99: 0 | H99: 0 | J99: 0 | K99: 0 | M99: 0 | N99: 0 | R99: https://github.com/DLu/oscar_data
A100: F0096 | B100: The Expendables 2 | C100: 2012 | D100: 0 | E100: 0 | G100: 0 | H100: 0 | J100: 0 | K100: 0 | M100: 0 | N100: 0 | R100: https://github.com/DLu/oscar_data
A101: F0097 | B101: The Expendables 3 | C101: 2014 | D101: 0 | E101: 0 | G101: 0 | H101: 0 | J101: 0 | K101: 0 | M101: 0 | N101: 0 | R101: https://github.com/DLu/oscar_data
...

Sheet Ratings
A1: ⭐ RATINGS
A2: One row per film. External scores are snapshots rather than live formulas; the search links make future checking/updating quick and keep the workbook reliable.
A4: Film ID | B4: Title | C4: Year | D4: Your Rating /5 | E4: IMDb /10 | F4: IMDb Votes | G4: RT Critics % | H4: RT Audience % | I4: Letterboxd /5 | J4: Metacritic /100 | K4: TMDb /10 | L4: Consensus /100 | M4: Rating Status | N4: Last Checked | O4: IMDb Lookup | P4: Rotten Tomatoes Lookup | Q4: Letterboxd Lookup | R4: Metacritic Lookup
A5: F0001 | B5: Casino Royale | C5: 2006 | L5: =IF(COUNT(E5,G5,H5,I5,J5,K5)=0,"",ROUND((IF(E5="",0,E5*10)+IF(G5="",0,G5)+IF(H5="",0,H5)+IF(I5="",0,I5*20)+IF(J5="",0,J5)+IF(K5="",0,K5*10))/COUNT(E5,G5,H5,I5,J5,K5),1)) | M5: =IF(L5="","",IF(L5>=85,"Excellent",IF(L5>=70,"Good",IF(L5>=55,"Mixed","Poor")))) | O5: https://www.imdb.com/find/?q=Casino+Royale+2006 | P5: https://www.rottentomatoes.com/search?search=Casino+Royale | Q5: https://letterboxd.com/search/Casino%20Royale/ | R5: https://www.metacritic.com/search/Casino+Royale/
A6: F0002 | B6: Quantum of Solace | C6: 2008 | L6: =IF(COUNT(E6,G6,H6,I6,J6,K6)=0,"",ROUND((IF(E6="",0,E6*10)+IF(G6="",0,G6)+IF(H6="",0,H6)+IF(I6="",0,I6*20)+IF(J6="",0,J6)+IF(K6="",0,K6*10))/COUNT(E6,G6,H6,I6,J6,K6),1)) | M6: =IF(L6="","",IF(L6>=85,"Excellent",IF(L6>=70,"Good",IF(L6>=55,"Mixed","Poor")))) | O6: https://www.imdb.com/find/?q=Quantum+of+Solace+2008 | P6: https://www.rottentomatoes.com/search?search=Quantum+of+Solace | Q6: https://letterboxd.com/search/Quantum%20of%20Solace/ | R6: https://www.metacritic.com/search/Quantum+of+Solace/
A7: F0003 | B7: Skyfall | C7: 2012 | L7: =IF(COUNT(E7,G7,H7,I7,J7,K7)=0,"",ROUND((IF(E7="",0,E7*10)+IF(G7="",0,G7)+IF(H7="",0,H7)+IF(I7="",0,I7*20)+IF(J7="",0,J7)+IF(K7="",0,K7*10))/COUNT(E7,G7,H7,I7,J7,K7),1)) | M7: =IF(L7="","",IF(L7>=85,"Excellent",IF(L7>=70,"Good",IF(L7>=55,"Mixed","Poor")))) | O7: https://www.imdb.com/find/?q=Skyfall+2012 | P7: https://www.rottentomatoes.com/search?search=Skyfall | Q7: https://letterboxd.com/search/Skyfall/ | R7: https://www.metacritic.com/search/Skyfall/
A8: F0004 | B8: Spectre | C8: 2015 | L8: =IF(COUNT(E8,G8,H8,I8,J8,K8)=0,"",ROUND((IF(E8="",0,E8*10)+IF(G8="",0,G8)+IF(H8="",0,H8)+IF(I8="",0,I8*20)+IF(J8="",0,J8)+IF(K8="",0,K8*10))/COUNT(E8,G8,H8,I8,J8,K8),1)) | M8: =IF(L8="","",IF(L8>=85,"Excellent",IF(L8>=70,"Good",IF(L8>=55,"Mixed","Poor")))) | O8: https://www.imdb.com/find/?q=Spectre+2015 | P8: https://www.rottentomatoes.com/search?search=Spectre | Q8: https://letterboxd.com/search/Spectre/ | R8: https://www.metacritic.com/search/Spectre/
A9: F0005 | B9: No Time to Die | C9: 2021 | L9: =IF(COUNT(E9,G9,H9,I9,J9,K9)=0,"",ROUND((IF(E9="",0,E9*10)+IF(G9="",0,G9)+IF(H9="",0,H9)+IF(I9="",0,I9*20)+IF(J9="",0,J9)+IF(K9="",0,K9*10))/COUNT(E9,G9,H9,I9,J9,K9),1)) | M9: =IF(L9="","",IF(L9>=85,"Excellent",IF(L9>=70,"Good",IF(L9>=55,"Mixed","Poor")))) | O9: https://www.imdb.com/find/?q=No+Time+to+Die+2021 | P9: https://www.rottentomatoes.com/search?search=No+Time+to+Die | Q9: https://letterboxd.com/search/No%20Time%20to%20Die/ | R9: https://www.metacritic.com/search/No+Time+to+Die/
A10: F0006 | B10: 2012 | C10: 2009 | L10: =IF(COUNT(E10,G10,H10,I10,J10,K10)=0,"",ROUND((IF(E10="",0,E10*10)+IF(G10="",0,G10)+IF(H10="",0,H10)+IF(I10="",0,I10*20)+IF(J10="",0,J10)+IF(K10="",0,K10*10))/COUNT(E10,G10,H10,I10,J10,K10),1)) | M10: =IF(L10="","",IF(L10>=85,"Excellent",IF(L10>=70,"Good",IF(L10>=55,"Mixed","Poor")))) | O10: https://www.imdb.com/find/?q=2012+2009 | P10: https://www.rottentomatoes.com/search?search=2012 | Q10: https://letterboxd.com/search/2012/ | R10: https://www.metacritic.com/search/2012/
A11: F0007 | B11: 21 Jump Street | C11: 2012 | D11: 3 | L11: =IF(COUNT(E11,G11,H11,I11,J11,K11)=0,"",ROUND((IF(E11="",0,E11*10)+IF(G11="",0,G11)+IF(H11="",0,H11)+IF(I11="",0,I11*20)+IF(J11="",0,J11)+IF(K11="",0,K11*10))/COUNT(E11,G11,H11,I11,J11,K11),1)) | M11: =IF(L11="","",IF(L11>=85,"Excellent",IF(L11>=70,"Good",IF(L11>=55,"Mixed","Poor")))) | O11: https://www.imdb.com/find/?q=21+Jump+Street+2012 | P11: https://www.rottentomatoes.com/search?search=21+Jump+Street | Q11: https://letterboxd.com/search/21%20Jump%20Street/ | R11: https://www.metacritic.com/search/21+Jump+Street/
A12: F0008 | B12: 22 Jump Street | C12: 2014 | D12: 3 | L12: =IF(COUNT(E12,G12,H12,I12,J12,K12)=0,"",ROUND((IF(E12="",0,E12*10)+IF(G12="",0,G12)+IF(H12="",0,H12)+IF(I12="",0,I12*20)+IF(J12="",0,J12)+IF(K12="",0,K12*10))/COUNT(E12,G12,H12,I12,J12,K12),1)) | M12: =IF(L12="","",IF(L12>=85,"Excellent",IF(L12>=70,"Good",IF(L12>=55,"Mixed","Poor")))) | O12: https://www.imdb.com/find/?q=22+Jump+Street+2014 | P12: https://www.rottentomatoes.com/search?search=22+Jump+Street | Q12: https://letterboxd.com/search/22%20Jump%20Street/ | R12: https://www.metacritic.com/search/22+Jump+Street/
A13: F0009 | B13: 30 Minutes or Less | C13: 2011 | L13: =IF(COUNT(E13,G13,H13,I13,J13,K13)=0,"",ROUND((IF(E13="",0,E13*10)+IF(G13="",0,G13)+IF(H13="",0,H13)+IF(I13="",0,I13*20)+IF(J13="",0,J13)+IF(K13="",0,K13*10))/COUNT(E13,G13,H13,I13,J13,K13),1)) | M13: =IF(L13="","",IF(L13>=85,"Excellent",IF(L13>=70,"Good",IF(L13>=55,"Mixed","Poor")))) | O13: https://www.imdb.com/find/?q=30+Minutes+or+Less+2011 | P13: https://www.rottentomatoes.com/search?search=30+Minutes+or+Less | Q13: https://letterboxd.com/search/30%20Minutes%20or%20Less/ | R13: https://www.metacritic.com/search/30+Minutes+or+Less/
A14: F0010 | B14: 44 Inch Chest | C14: 2009 | L14: =IF(COUNT(E14,G14,H14,I14,J14,K14)=0,"",ROUND((IF(E14="",0,E14*10)+IF(G14="",0,G14)+IF(H14="",0,H14)+IF(I14="",0,I14*20)+IF(J14="",0,J14)+IF(K14="",0,K14*10))/COUNT(E14,G14,H14,I14,J14,K14),1)) | M14: =IF(L14="","",IF(L14>=85,"Excellent",IF(L14>=70,"Good",IF(L14>=55,"Mixed","Poor")))) | O14: https://www.imdb.com/find/?q=44+Inch+Chest+2009 | P14: https://www.rottentomatoes.com/search?search=44+Inch+Chest | Q14: https://letterboxd.com/search/44%20Inch%20Chest/ | R14: https://www.metacritic.com/search/44+Inch+Chest/
A15: F0011 | B15: 50/50 | C15: 2011 | L15: =IF(COUNT(E15,G15,H15,I15,J15,K15)=0,"",ROUND((IF(E15="",0,E15*10)+IF(G15="",0,G15)+IF(H15="",0,H15)+IF(I15="",0,I15*20)+IF(J15="",0,J15)+IF(K15="",0,K15*10))/COUNT(E15,G15,H15,I15,J15,K15),1)) | M15: =IF(L15="","",IF(L15>=85,"Excellent",IF(L15>=70,"Good",IF(L15>=55,"Mixed","Poor")))) | O15: https://www.imdb.com/find/?q=50%2F50+2011 | P15: https://www.rottentomatoes.com/search?search=50%2F50 | Q15: https://letterboxd.com/search/50/50/ | R15: https://www.metacritic.com/search/50%2F50/
A16: F0012 | B16: A Bug's Life | C16: 1998 | D16: 4 | L16: =IF(COUNT(E16,G16,H16,I16,J16,K16)=0,"",ROUND((IF(E16="",0,E16*10)+IF(G16="",0,G16)+IF(H16="",0,H16)+IF(I16="",0,I16*20)+IF(J16="",0,J16)+IF(K16="",0,K16*10))/COUNT(E16,G16,H16,I16,J16,K16),1)) | M16: =IF(L16="","",IF(L16>=85,"Excellent",IF(L16>=70,"Good",IF(L16>=55,"Mixed","Poor")))) | O16: https://www.imdb.com/find/?q=A+Bug%27s+Life+1998 | P16: https://www.rottentomatoes.com/search?search=A+Bug%27s+Life | Q16: https://letterboxd.com/search/A%20Bug%27s%20Life/ | R16: https://www.metacritic.com/search/A+Bug%27s+Life/
A17: F0013 | B17: The Accountant | C17: 2016 | L17: =IF(COUNT(E17,G17,H17,I17,J17,K17)=0,"",ROUND((IF(E17="",0,E17*10)+IF(G17="",0,G17)+IF(H17="",0,H17)+IF(I17="",0,I17*20)+IF(J17="",0,J17)+IF(K17="",0,K17*10))/COUNT(E17,G17,H17,I17,J17,K17),1)) | M17: =IF(L17="","",IF(L17>=85,"Excellent",IF(L17>=70,"Good",IF(L17>=55,"Mixed","Poor")))) | O17: https://www.imdb.com/find/?q=The+Accountant+2016 | P17: https://www.rottentomatoes.com/search?search=The+Accountant | Q17: https://letterboxd.com/search/The%20Accountant/ | R17: https://www.metacritic.com/search/The+Accountant/
A18: F0014 | B18: Alan Partridge: Alpha Papa | C18: 2013 | L18: =IF(COUNT(E18,G18,H18,I18,J18,K18)=0,"",ROUND((IF(E18="",0,E18*10)+IF(G18="",0,G18)+IF(H18="",0,H18)+IF(I18="",0,I18*20)+IF(J18="",0,J18)+IF(K18="",0,K18*10))/COUNT(E18,G18,H18,I18,J18,K18),1)) | M18: =IF(L18="","",IF(L18>=85,"Excellent",IF(L18>=70,"Good",IF(L18>=55,"Mixed","Poor")))) | O18: https://www.imdb.com/find/?q=Alan+Partridge%3A+Alpha+Papa+2013 | P18: https://www.rottentomatoes.com/search?search=Alan+Partridge%3A+Alpha+Papa | Q18: https://letterboxd.com/search/Alan%20Partridge%3A%20Alpha%20Papa/ | R18: https://www.metacritic.com/search/Alan+Partridge%3A+Alpha+Papa/
A19: F0015 | B19: Alien | C19: 1979 | L19: =IF(COUNT(E19,G19,H19,I19,J19,K19)=0,"",ROUND((IF(E19="",0,E19*10)+IF(G19="",0,G19)+IF(H19="",0,H19)+IF(I19="",0,I19*20)+IF(J19="",0,J19)+IF(K19="",0,K19*10))/COUNT(E19,G19,H19,I19,J19,K19),1)) | M19: =IF(L19="","",IF(L19>=85,"Excellent",IF(L19>=70,"Good",IF(L19>=55,"Mixed","Poor")))) | O19: https://www.imdb.com/find/?q=Alien+1979 | P19: https://www.rottentomatoes.com/search?search=Alien | Q19: https://letterboxd.com/search/Alien/ | R19: https://www.metacritic.com/search/Alien/
A20: F0016 | B20: Aliens | C20: 1986 | L20: =IF(COUNT(E20,G20,H20,I20,J20,K20)=0,"",ROUND((IF(E20="",0,E20*10)+IF(G20="",0,G20)+IF(H20="",0,H20)+IF(I20="",0,I20*20)+IF(J20="",0,J20)+IF(K20="",0,K20*10))/COUNT(E20,G20,H20,I20,J20,K20),1)) | M20: =IF(L20="","",IF(L20>=85,"Excellent",IF(L20>=70,"Good",IF(L20>=55,"Mixed","Poor")))) | O20: https://www.imdb.com/find/?q=Aliens+1986 | P20: https://www.rottentomatoes.com/search?search=Aliens | Q20: https://letterboxd.com/search/Aliens/ | R20: https://www.metacritic.com/search/Aliens/
A21: F0017 | B21: Alien³ | C21: 1992 | L21: =IF(COUNT(E21,G21,H21,I21,J21,K21)=0,"",ROUND((IF(E21="",0,E21*10)+IF(G21="",0,G21)+IF(H21="",0,H21)+IF(I21="",0,I21*20)+IF(J21="",0,J21)+IF(K21="",0,K21*10))/COUNT(E21,G21,H21,I21,J21,K21),1)) | M21: =IF(L21="","",IF(L21>=85,"Excellent",IF(L21>=70,"Good",IF(L21>=55,"Mixed","Poor")))) | O21: https://www.imdb.com/find/?q=Alien%C2%B3+1992 | P21: https://www.rottentomatoes.com/search?search=Alien%C2%B3 | Q21: https://letterboxd.com/search/Alien%C2%B3/ | R21: https://www.metacritic.com/search/Alien%C2%B3/
A22: F0018 | B22: Alien Resurrection | C22: 1997 | L22: =IF(COUNT(E22,G22,H22,I22,J22,K22)=0,"",ROUND((IF(E22="",0,E22*10)+IF(G22="",0,G22)+IF(H22="",0,H22)+IF(I22="",0,I22*20)+IF(J22="",0,J22)+IF(K22="",0,K22*10))/COUNT(E22,G22,H22,I22,J22,K22),1)) | M22: =IF(L22="","",IF(L22>=85,"Excellent",IF(L22>=70,"Good",IF(L22>=55,"Mixed","Poor")))) | O22: https://www.imdb.com/find/?q=Alien+Resurrection+1997 | P22: https://www.rottentomatoes.com/search?search=Alien+Resurrection | Q22: https://letterboxd.com/search/Alien%20Resurrection/ | R22: https://www.metacritic.com/search/Alien+Resurrection/
A23: F0019 | B23: The Amazing Spider-Man | C23: 2012 | L23: =IF(COUNT(E23,G23,H23,I23,J23,K23)=0,"",ROUND((IF(E23="",0,E23*10)+IF(G23="",0,G23)+IF(H23="",0,H23)+IF(I23="",0,I23*20)+IF(J23="",0,J23)+IF(K23="",0,K23*10))/COUNT(E23,G23,H23,I23,J23,K23),1)) | M23: =IF(L23="","",IF(L23>=85,"Excellent",IF(L23>=70,"Good",IF(L23>=55,"Mixed","Poor")))) | O23: https://www.imdb.com/find/?q=The+Amazing+Spider-Man+2012 | P23: https://www.rottentomatoes.com/search?search=The+Amazing+Spider-Man | Q23: https://letterboxd.com/search/The%20Amazing%20Spider-Man/ | R23: https://www.metacritic.com/search/The+Amazing+Spider-Man/
A24: F0020 | B24: American Hustle | C24: 2013 | L24: =IF(COUNT(E24,G24,H24,I24,J24,K24)=0,"",ROUND((IF(E24="",0,E24*10)+IF(G24="",0,G24)+IF(H24="",0,H24)+IF(I24="",0,I24*20)+IF(J24="",0,J24)+IF(K24="",0,K24*10))/COUNT(E24,G24,H24,I24,J24,K24),1)) | M24: =IF(L24="","",IF(L24>=85,"Excellent",IF(L24>=70,"Good",IF(L24>=55,"Mixed","Poor")))) | O24: https://www.imdb.com/find/?q=American+Hustle+2013 | P24: https://www.rottentomatoes.com/search?search=American+Hustle | Q24: https://letterboxd.com/search/American%20Hustle/ | R24: https://www.metacritic.com/search/American+Hustle/
A25: F0021 | B25: A Million Ways to Die in the West | C25: 2014 | L25: =IF(COUNT(E25,G25,H25,I25,J25,K25)=0,"",ROUND((IF(E25="",0,E25*10)+IF(G25="",0,G25)+IF(H25="",0,H25)+IF(I25="",0,I25*20)+IF(J25="",0,J25)+IF(K25="",0,K25*10))/COUNT(E25,G25,H25,I25,J25,K25),1)) | M25: =IF(L25="","",IF(L25>=85,"Excellent",IF(L25>=70,"Good",IF(L25>=55,"Mixed","Poor")))) | O25: https://www.imdb.com/find/?q=A+Million+Ways+to+Die+in+the+West+2014 | P25: https://www.rottentomatoes.com/search?search=A+Million+Ways+to+Die+in+the+West | Q25: https://letterboxd.com/search/A%20Million%20Ways%20to%20Die%20in%20the%20West/ | R25: https://www.metacritic.com/search/A+Million+Ways+to+Die+in+the+West/
A26: F0022 | B26: Anchorman: The Legend of Ron Burgundy | C26: 2004 | D26: 4 | L26: =IF(COUNT(E26,G26,H26,I26,J26,K26)=0,"",ROUND((IF(E26="",0,E26*10)+IF(G26="",0,G26)+IF(H26="",0,H26)+IF(I26="",0,I26*20)+IF(J26="",0,J26)+IF(K26="",0,K26*10))/COUNT(E26,G26,H26,I26,J26,K26),1)) | M26: =IF(L26="","",IF(L26>=85,"Excellent",IF(L26>=70,"Good",IF(L26>=55,"Mixed","Poor")))) | O26: https://www.imdb.com/find/?q=Anchorman%3A+The+Legend+of+Ron+Burgundy+2004 | P26: https://www.rottentomatoes.com/search?search=Anchorman%3A+The+Legend+of+Ron+Burgundy | Q26: https://letterboxd.com/search/Anchorman%3A%20The%20Legend%20of%20Ron%20Burgundy/ | R26: https://www.metacritic.com/search/Anchorman%3A+The+Legend+of+Ron+Burgundy/
A27: F0023 | B27: Angels & Demons | C27: 2009 | L27: =IF(COUNT(E27,G27,H27,I27,J27,K27)=0,"",ROUND((IF(E27="",0,E27*10)+IF(G27="",0,G27)+IF(H27="",0,H27)+IF(I27="",0,I27*20)+IF(J27="",0,J27)+IF(K27="",0,K27*10))/COUNT(E27,G27,H27,I27,J27,K27),1)) | M27: =IF(L27="","",IF(L27>=85,"Excellent",IF(L27>=70,"Good",IF(L27>=55,"Mixed","Poor")))) | O27: https://www.imdb.com/find/?q=Angels+%26+Demons+2009 | P27: https://www.rottentomatoes.com/search?search=Angels+%26+Demons | Q27: https://letterboxd.com/search/Angels%20%26%20Demons/ | R27: https://www.metacritic.com/search/Angels+%26+Demons/
A28: F0024 | B28: Anuvahood | C28: 2011 | L28: =IF(COUNT(E28,G28,H28,I28,J28,K28)=0,"",ROUND((IF(E28="",0,E28*10)+IF(G28="",0,G28)+IF(H28="",0,H28)+IF(I28="",0,I28*20)+IF(J28="",0,J28)+IF(K28="",0,K28*10))/COUNT(E28,G28,H28,I28,J28,K28),1)) | M28: =IF(L28="","",IF(L28>=85,"Excellent",IF(L28>=70,"Good",IF(L28>=55,"Mixed","Poor")))) | O28: https://www.imdb.com/find/?q=Anuvahood+2011 | P28: https://www.rottentomatoes.com/search?search=Anuvahood | Q28: https://letterboxd.com/search/Anuvahood/ | R28: https://www.metacritic.com/search/Anuvahood/
A29: F0025 | B29: Argo | C29: 2012 | L29: =IF(COUNT(E29,G29,H29,I29,J29,K29)=0,"",ROUND((IF(E29="",0,E29*10)+IF(G29="",0,G29)+IF(H29="",0,H29)+IF(I29="",0,I29*20)+IF(J29="",0,J29)+IF(K29="",0,K29*10))/COUNT(E29,G29,H29,I29,J29,K29),1)) | M29: =IF(L29="","",IF(L29>=85,"Excellent",IF(L29>=70,"Good",IF(L29>=55,"Mixed","Poor")))) | O29: https://www.imdb.com/find/?q=Argo+2012 | P29: https://www.rottentomatoes.com/search?search=Argo | Q29: https://letterboxd.com/search/Argo/ | R29: https://www.metacritic.com/search/Argo/
A30: F0026 | B30: The A-Team | C30: 2010 | L30: =IF(COUNT(E30,G30,H30,I30,J30,K30)=0,"",ROUND((IF(E30="",0,E30*10)+IF(G30="",0,G30)+IF(H30="",0,H30)+IF(I30="",0,I30*20)+IF(J30="",0,J30)+IF(K30="",0,K30*10))/COUNT(E30,G30,H30,I30,J30,K30),1)) | M30: =IF(L30="","",IF(L30>=85,"Excellent",IF(L30>=70,"Good",IF(L30>=55,"Mixed","Poor")))) | O30: https://www.imdb.com/find/?q=The+A-Team+2010 | P30: https://www.rottentomatoes.com/search?search=The+A-Team | Q30: https://letterboxd.com/search/The%20A-Team/ | R30: https://www.metacritic.com/search/The+A-Team/
A31: F0027 | B31: Attack the Block | C31: 2011 | L31: =IF(COUNT(E31,G31,H31,I31,J31,K31)=0,"",ROUND((IF(E31="",0,E31*10)+IF(G31="",0,G31)+IF(H31="",0,H31)+IF(I31="",0,I31*20)+IF(J31="",0,J31)+IF(K31="",0,K31*10))/COUNT(E31,G31,H31,I31,J31,K31),1)) | M31: =IF(L31="","",IF(L31>=85,"Excellent",IF(L31>=70,"Good",IF(L31>=55,"Mixed","Poor")))) | O31: https://www.imdb.com/find/?q=Attack+the+Block+2011 | P31: https://www.rottentomatoes.com/search?search=Attack+the+Block | Q31: https://letterboxd.com/search/Attack%20the%20Block/ | R31: https://www.metacritic.com/search/Attack+the+Block/
A32: F0028 | B32: Avatar | C32: 2009 | L32: =IF(COUNT(E32,G32,H32,I32,J32,K32)=0,"",ROUND((IF(E32="",0,E32*10)+IF(G32="",0,G32)+IF(H32="",0,H32)+IF(I32="",0,I32*20)+IF(J32="",0,J32)+IF(K32="",0,K32*10))/COUNT(E32,G32,H32,I32,J32,K32),1)) | M32: =IF(L32="","",IF(L32>=85,"Excellent",IF(L32>=70,"Good",IF(L32>=55,"Mixed","Poor")))) | O32: https://www.imdb.com/find/?q=Avatar+2009 | P32: https://www.rottentomatoes.com/search?search=Avatar | Q32: https://letterboxd.com/search/Avatar/ | R32: https://www.metacritic.com/search/Avatar/
A33: F0029 | B33: The Avengers | C33: 2012 | L33: =IF(COUNT(E33,G33,H33,I33,J33,K33)=0,"",ROUND((IF(E33="",0,E33*10)+IF(G33="",0,G33)+IF(H33="",0,H33)+IF(I33="",0,I33*20)+IF(J33="",0,J33)+IF(K33="",0,K33*10))/COUNT(E33,G33,H33,I33,J33,K33),1)) | M33: =IF(L33="","",IF(L33>=85,"Excellent",IF(L33>=70,"Good",IF(L33>=55,"Mixed","Poor")))) | O33: https://www.imdb.com/find/?q=The+Avengers+2012 | P33: https://www.rottentomatoes.com/search?search=The+Avengers | Q33: https://letterboxd.com/search/The%20Avengers/ | R33: https://www.metacritic.com/search/The+Avengers/
A34: F0030 | B34: Avengers: Infinity War | C34: 2018 | L34: =IF(COUNT(E34,G34,H34,I34,J34,K34)=0,"",ROUND((IF(E34="",0,E34*10)+IF(G34="",0,G34)+IF(H34="",0,H34)+IF(I34="",0,I34*20)+IF(J34="",0,J34)+IF(K34="",0,K34*10))/COUNT(E34,G34,H34,I34,J34,K34),1)) | M34: =IF(L34="","",IF(L34>=85,"Excellent",IF(L34>=70,"Good",IF(L34>=55,"Mixed","Poor")))) | O34: https://www.imdb.com/find/?q=Avengers%3A+Infinity+War+2018 | P34: https://www.rottentomatoes.com/search?search=Avengers%3A+Infinity+War | Q34: https://letterboxd.com/search/Avengers%3A%20Infinity%20War/ | R34: https://www.metacritic.com/search/Avengers%3A+Infinity+War/
A35: F0031 | B35: Avengers: Endgame | C35: 2019 | L35: =IF(COUNT(E35,G35,H35,I35,J35,K35)=0,"",ROUND((IF(E35="",0,E35*10)+IF(G35="",0,G35)+IF(H35="",0,H35)+IF(I35="",0,I35*20)+IF(J35="",0,J35)+IF(K35="",0,K35*10))/COUNT(E35,G35,H35,I35,J35,K35),1)) | M35: =IF(L35="","",IF(L35>=85,"Excellent",IF(L35>=70,"Good",IF(L35>=55,"Mixed","Poor")))) | O35: https://www.imdb.com/find/?q=Avengers%3A+Endgame+2019 | P35: https://www.rottentomatoes.com/search?search=Avengers%3A+Endgame | Q35: https://letterboxd.com/search/Avengers%3A%20Endgame/ | R35: https://www.metacritic.com/search/Avengers%3A+Endgame/
A36: F0032 | B36: Baby Driver | C36: 2017 | L36: =IF(COUNT(E36,G36,H36,I36,J36,K36)=0,"",ROUND((IF(E36="",0,E36*10)+IF(G36="",0,G36)+IF(H36="",0,H36)+IF(I36="",0,I36*20)+IF(J36="",0,J36)+IF(K36="",0,K36*10))/COUNT(E36,G36,H36,I36,J36,K36),1)) | M36: =IF(L36="","",IF(L36>=85,"Excellent",IF(L36>=70,"Good",IF(L36>=55,"Mixed","Poor")))) | O36: https://www.imdb.com/find/?q=Baby+Driver+2017 | P36: https://www.rottentomatoes.com/search?search=Baby+Driver | Q36: https://letterboxd.com/search/Baby%20Driver/ | R36: https://www.metacritic.com/search/Baby+Driver/
A37: F0033 | B37: Back to the Future | C37: 1985 | L37: =IF(COUNT(E37,G37,H37,I37,J37,K37)=0,"",ROUND((IF(E37="",0,E37*10)+IF(G37="",0,G37)+IF(H37="",0,H37)+IF(I37="",0,I37*20)+IF(J37="",0,J37)+IF(K37="",0,K37*10))/COUNT(E37,G37,H37,I37,J37,K37),1)) | M37: =IF(L37="","",IF(L37>=85,"Excellent",IF(L37>=70,"Good",IF(L37>=55,"Mixed","Poor")))) | O37: https://www.imdb.com/find/?q=Back+to+the+Future+1985 | P37: https://www.rottentomatoes.com/search?search=Back+to+the+Future | Q37: https://letterboxd.com/search/Back%20to%20the%20Future/ | R37: https://www.metacritic.com/search/Back+to+the+Future/
A38: F0034 | B38: Back to the Future Part II | C38: 1989 | L38: =IF(COUNT(E38,G38,H38,I38,J38,K38)=0,"",ROUND((IF(E38="",0,E38*10)+IF(G38="",0,G38)+IF(H38="",0,H38)+IF(I38="",0,I38*20)+IF(J38="",0,J38)+IF(K38="",0,K38*10))/COUNT(E38,G38,H38,I38,J38,K38),1)) | M38: =IF(L38="","",IF(L38>=85,"Excellent",IF(L38>=70,"Good",IF(L38>=55,"Mixed","Poor")))) | O38: https://www.imdb.com/find/?q=Back+to+the+Future+Part+II+1989 | P38: https://www.rottentomatoes.com/search?search=Back+to+the+Future+Part+II | Q38: https://letterboxd.com/search/Back%20to%20the%20Future%20Part%20II/ | R38: https://www.metacritic.com/search/Back+to+the+Future+Part+II/
... A56: F0052 | B56: Bohemian Rhapsody | C56: 2018 | L56: =IF(COUNT(E56,G56,H56,I56,J56,K56)=0,"",ROUND((IF(E56="",0,E56*10)+IF(G56="",0,G56)+IF(H56="",0,H56)+IF(I56="",0,I56*20)+IF(J56="",0,J56)+IF(K56="",0,K56*10))/COUNT(E56,G56,H56,I56,J56,K56),1)) | M56: =IF(L56="","",IF(L56>=85,"Excellent",IF(L56>=70,"Good",IF(L56>=55,"Mixed","Poor")))) | O56: https://www.imdb.com/find/?q=Bohemian+Rhapsody+2018 | P56: https://www.rottentomatoes.com/search?search=Bohemian+Rhapsody | Q56: https://letterboxd.com/search/Bohemian%20Rhapsody/ | R56: https://www.metacritic.com/search/Bohemian+Rhapsody/
A57: F0053 | B57: The Bourne Identity | C57: 2002 | D57: 3 | L57: =IF(COUNT(E57,G57,H57,I57,J57,K57)=0,"",ROUND((IF(E57="",0,E57*10)+IF(G57="",0,G57)+IF(H57="",0,H57)+IF(I57="",0,I57*20)+IF(J57="",0,J57)+IF(K57="",0,K57*10))/COUNT(E57,G57,H57,I57,J57,K57),1)) | M57: =IF(L57="","",IF(L57>=85,"Excellent",IF(L57>=70,"Good",IF(L57>=55,"Mixed","Poor")))) | O57: https://www.imdb.com/find/?q=The+Bourne+Identity+2002 | P57: https://www.rottentomatoes.com/search?search=The+Bourne+Identity | Q57: https://letterboxd.com/search/The%20Bourne%20Identity/ | R57: https://www.metacritic.com/search/The+Bourne+Identity/
A58: F0054 | B58: The Bourne Supremacy | C58: 2004 | D58: 4 | L58: =IF(COUNT(E58,G58,H58,I58,J58,K58)=0,"",ROUND((IF(E58="",0,E58*10)+IF(G58="",0,G58)+IF(H58="",0,H58)+IF(I58="",0,I58*20)+IF(J58="",0,J58)+IF(K58="",0,K58*10))/COUNT(E58,G58,H58,I58,J58,K58),1)) | M58: =IF(L58="","",IF(L58>=85,"Excellent",IF(L58>=70,"Good",IF(L58>=55,"Mixed","Poor")))) | O58: https://www.imdb.com/find/?q=The+Bourne+Supremacy+2004 | P58: https://www.rottentomatoes.com/search?search=The+Bourne+Supremacy | Q58: https://letterboxd.com/search/The%20Bourne%20Supremacy/ | R58: https://www.metacritic.com/search/The+Bourne+Supremacy/
A59: F0055 | B59: The Bourne Ultimatum | C59: 2007 | D59: 4 | L59: =IF(COUNT(E59,G59,H59,I59,J59,K59)=0,"",ROUND((IF(E59="",0,E59*10)+IF(G59="",0,G59)+IF(H59="",0,H59)+IF(I59="",0,I59*20)+IF(J59="",0,J59)+IF(K59="",0,K59*10))/COUNT(E59,G59,H59,I59,J59,K59),1)) | M59: =IF(L59="","",IF(L59>=85,"Excellent",IF(L59>=70,"Good",IF(L59>=55,"Mixed","Poor")))) | O59: https://www.imdb.com/find/?q=The+Bourne+Ultimatum+2007 | P59: https://www.rottentomatoes.com/search?search=The+Bourne+Ultimatum | Q59: https://letterboxd.com/search/The%20Bourne%20Ultimatum/ | R59: https://www.metacritic.com/search/The+Bourne+Ultimatum/
A60: F0056 | B60: The Bourne Legacy | C60: 2012 | D60: 3 | L60: =IF(COUNT(E60,G60,H60,I60,J60,K60)=0,"",ROUND((IF(E60="",0,E60*10)+IF(G60="",0,G60)+IF(H60="",0,H60)+IF(I60="",0,I60*20)+IF(J60="",0,J60)+IF(K60="",0,K60*10))/COUNT(E60,G60,H60,I60,J60,K60),1)) | M60: =IF(L60="","",IF(L60>=85,"Excellent",IF(L60>=70,"Good",IF(L60>=55,"Mixed","Poor")))) | O60: https://www.imdb.com/find/?q=The+Bourne+Legacy+2012 | P60: https://www.rottentomatoes.com/search?search=The+Bourne+Legacy | Q60: https://letterboxd.com/search/The%20Bourne%20Legacy/ | R60: https://www.metacritic.com/search/The+Bourne+Legacy/
A61: F0057 | B61: The Breakfast Club | C61: 1985 | L61: =IF(COUNT(E61,G61,H61,I61,J61,K61)=0,"",ROUND((IF(E61="",0,E61*10)+IF(G61="",0,G61)+IF(H61="",0,H61)+IF(I61="",0,I61*20)+IF(J61="",0,J61)+IF(K61="",0,K61*10))/COUNT(E61,G61,H61,I61,J61,K61),1)) | M61: =IF(L61="","",IF(L61>=85,"Excellent",IF(L61>=70,"Good",IF(L61>=55,"Mixed","Poor")))) | O61: https://www.imdb.com/find/?q=The+Breakfast+Club+1985 | P61: https://www.rottentomatoes.com/search?search=The+Breakfast+Club | Q61: https://letterboxd.com/search/The%20Breakfast%20Club/ | R61: https://www.metacritic.com/search/The+Breakfast+Club/
A62: F0058 | B62: Bridesmaids | C62: 2011 | L62: =IF(COUNT(E62,G62,H62,I62,J62,K62)=0,"",ROUND((IF(E62="",0,E62*10)+IF(G62="",0,G62)+IF(H62="",0,H62)+IF(I62="",0,I62*20)+IF(J62="",0,J62)+IF(K62="",0,K62*10))/COUNT(E62,G62,H62,I62,J62,K62),1)) | M62: =IF(L62="","",IF(L62>=85,"Excellent",IF(L62>=70,"Good",IF(L62>=55,"Mixed","Poor")))) | O62: https://www.imdb.com/find/?q=Bridesmaids+2011 | P62: https://www.rottentomatoes.com/search?search=Bridesmaids | Q62: https://letterboxd.com/search/Bridesmaids/ | R62: https://www.metacritic.com/search/Bridesmaids/
A63: F0059 | B63: Brüno | C63: 2009 | L63: =IF(COUNT(E63,G63,H63,I63,J63,K63)=0,"",ROUND((IF(E63="",0,E63*10)+IF(G63="",0,G63)+IF(H63="",0,H63)+IF(I63="",0,I63*20)+IF(J63="",0,J63)+IF(K63="",0,K63*10))/COUNT(E63,G63,H63,I63,J63,K63),1)) | M63: =IF(L63="","",IF(L63>=85,"Excellent",IF(L63>=70,"Good",IF(L63>=55,"Mixed","Poor")))) | O63: https://www.imdb.com/find/?q=Br%C3%BCno+2009 | P63: https://www.rottentomatoes.com/search?search=Br%C3%BCno | Q63: https://letterboxd.com/search/Br%C3%BCno/ | R63: https://www.metacritic.com/search/Br%C3%BCno/
A64: F0060 | B64: The Bucket List | C64: 2007 | L64: =IF(COUNT(E64,G64,H64,I64,J64,K64)=0,"",ROUND((IF(E64="",0,E64*10)+IF(G64="",0,G64)+IF(H64="",0,H64)+IF(I64="",0,I64*20)+IF(J64="",0,J64)+IF(K64="",0,K64*10))/COUNT(E64,G64,H64,I64,J64,K64),1)) | M64: =IF(L64="","",IF(L64>=85,"Excellent",IF(L64>=70,"Good",IF(L64>=55,"Mixed","Poor")))) | O64: https://www.imdb.com/find/?q=The+Bucket+List+2007 | P64: https://www.rottentomatoes.com/search?search=The+Bucket+List | Q64: https://letterboxd.com/search/The%20Bucket%20List/ | R64: https://www.metacritic.com/search/The+Bucket+List/
A65: F0061 | B65: Bumblebee | C65: 2018 | D65: 4 | L65: =IF(COUNT(E65,G65,H65,I65,J65,K65)=0,"",ROUND((IF(E65="",0,E65*10)+IF(G65="",0,G65)+IF(H65="",0,H65)+IF(I65="",0,I65*20)+IF(J65="",0,J65)+IF(K65="",0,K65*10))/COUNT(E65,G65,H65,I65,J65,K65),1)) | M65: =IF(L65="","",IF(L65>=85,"Excellent",IF(L65>=70,"Good",IF(L65>=55,"Mixed","Poor")))) | O65: https://www.imdb.com/find/?q=Bumblebee+2018 | P65: https://www.rottentomatoes.com/search?search=Bumblebee | Q65: https://letterboxd.com/search/Bumblebee/ | R65: https://www.metacritic.com/search/Bumblebee/
A66: F0062 | B66: Captain Phillips | C66: 2013 | L66: =IF(COUNT(E66,G66,H66,I66,J66,K66)=0,"",ROUND((IF(E66="",0,E66*10)+IF(G66="",0,G66)+IF(H66="",0,H66)+IF(I66="",0,I66*20)+IF(J66="",0,J66)+IF(K66="",0,K66*10))/COUNT(E66,G66,H66,I66,J66,K66),1)) | M66: =IF(L66="","",IF(L66>=85,"Excellent",IF(L66>=70,"Good",IF(L66>=55,"Mixed","Poor")))) | O66: https://www.imdb.com/find/?q=Captain+Phillips+2013 | P66: https://www.rottentomatoes.com/search?search=Captain+Phillips | Q66: https://letterboxd.com/search/Captain%20Phillips/ | R66: https://www.metacritic.com/search/Captain+Phillips/
A67: F0063 | B67: Catch.44 | C67: 2011 | L67: =IF(COUNT(E67,G67,H67,I67,J67,K67)=0,"",ROUND((IF(E67="",0,E67*10)+IF(G67="",0,G67)+IF(H67="",0,H67)+IF(I67="",0,I67*20)+IF(J67="",0,J67)+IF(K67="",0,K67*10))/COUNT(E67,G67,H67,I67,J67,K67),1)) | M67: =IF(L67="","",IF(L67>=85,"Excellent",IF(L67>=70,"Good",IF(L67>=55,"Mixed","Poor")))) | O67: https://www.imdb.com/find/?q=Catch.44+2011 | P67: https://www.rottentomatoes.com/search?search=Catch.44 | Q67: https://letterboxd.com/search/Catch.44/ | R67: https://www.metacritic.com/search/Catch.44/
A68: F0064 | B68: Catch Me If You Can | C68: 2002 | L68: =IF(COUNT(E68,G68,H68,I68,J68,K68)=0,"",ROUND((IF(E68="",0,E68*10)+IF(G68="",0,G68)+IF(H68="",0,H68)+IF(I68="",0,I68*20)+IF(J68="",0,J68)+IF(K68="",0,K68*10))/COUNT(E68,G68,H68,I68,J68,K68),1)) | M68: =IF(L68="","",IF(L68>=85,"Excellent",IF(L68>=70,"Good",IF(L68>=55,"Mixed","Poor")))) | O68: https://www.imdb.com/find/?q=Catch+Me+If+You+Can+2002 | P68: https://www.rottentomatoes.com/search?search=Catch+Me+If+You+Can | Q68: https://letterboxd.com/search/Catch%20Me%20If%20You%20Can/ | R68: https://www.metacritic.com/search/Catch+Me+If+You+Can/
A69: F0065 | B69: Chef | C69: 2014 | D69: 5 | L69: =IF(COUNT(E69,G69,H69,I69,J69,K69)=0,"",ROUND((IF(E69="",0,E69*10)+IF(G69="",0,G69)+IF(H69="",0,H69)+IF(I69="",0,I69*20)+IF(J69="",0,J69)+IF(K69="",0,K69*10))/COUNT(E69,G69,H69,I69,J69,K69),1)) | M69: =IF(L69="","",IF(L69>=85,"Excellent",IF(L69>=70,"Good",IF(L69>=55,"Mixed","Poor")))) | O69: https://www.imdb.com/find/?q=Chef+2014 | P69: https://www.rottentomatoes.com/search?search=Chef | Q69: https://letterboxd.com/search/Chef/ | R69: https://www.metacritic.com/search/Chef/
A70: F0066 | B70: Clash of the Titans | C70: 2010 | L70: =IF(COUNT(E70,G70,H70,I70,J70,K70)=0,"",ROUND((IF(E70="",0,E70*10)+IF(G70="",0,G70)+IF(H70="",0,H70)+IF(I70="",0,I70*20)+IF(J70="",0,J70)+IF(K70="",0,K70*10))/COUNT(E70,G70,H70,I70,J70,K70),1)) | M70: =IF(L70="","",IF(L70>=85,"Excellent",IF(L70>=70,"Good",IF(L70>=55,"Mixed","Poor")))) | O70: https://www.imdb.com/find/?q=Clash+of+the+Titans+2010 | P70: https://www.rottentomatoes.com/search?search=Clash+of+the+Titans | Q70: https://letterboxd.com/search/Clash%20of%20the%20Titans/ | R70: https://www.metacritic.com/search/Clash+of+the+Titans/
A71: F0067 | B71: Cloudy with a Chance of Meatballs 2 | C71: 2013 | L71: =IF(COUNT(E71,G71,H71,I71,J71,K71)=0,"",ROUND((IF(E71="",0,E71*10)+IF(G71="",0,G71)+IF(H71="",0,H71)+IF(I71="",0,I71*20)+IF(J71="",0,J71)+IF(K71="",0,K71*10))/COUNT(E71,G71,H71,I71,J71,K71),1)) | M71: =IF(L71="","",IF(L71>=85,"Excellent",IF(L71>=70,"Good",IF(L71>=55,"Mixed","Poor")))) | O71: https://www.imdb.com/find/?q=Cloudy+with+a+Chance+of+Meatballs+2+2013 | P71: https://www.rottentomatoes.com/search?search=Cloudy+with+a+Chance+of+Meatballs+2 | Q71: https://letterboxd.com/search/Cloudy%20with%20a%20Chance%20of%20Meatballs%202/ | R71: https://www.metacritic.com/search/Cloudy+with+a+Chance+of+Meatballs+2/
A72: F0068 | B72: Con Air | C72: 1997 | L72: =IF(COUNT(E72,G72,H72,I72,J72,K72)=0,"",ROUND((IF(E72="",0,E72*10)+IF(G72="",0,G72)+IF(H72="",0,H72)+IF(I72="",0,I72*20)+IF(J72="",0,J72)+IF(K72="",0,K72*10))/COUNT(E72,G72,H72,I72,J72,K72),1)) | M72: =IF(L72="","",IF(L72>=85,"Excellent",IF(L72>=70,"Good",IF(L72>=55,"Mixed","Poor")))) | O72: https://www.imdb.com/find/?q=Con+Air+1997 | P72: https://www.rottentomatoes.com/search?search=Con+Air | Q72: https://letterboxd.com/search/Con%20Air/ | R72: https://www.metacritic.com/search/Con+Air/
A73: F0069 | B73: Cop Out | C73: 2010 | L73: =IF(COUNT(E73,G73,H73,I73,J73,K73)=0,"",ROUND((IF(E73="",0,E73*10)+IF(G73="",0,G73)+IF(H73="",0,H73)+IF(I73="",0,I73*20)+IF(J73="",0,J73)+IF(K73="",0,K73*10))/COUNT(E73,G73,H73,I73,J73,K73),1)) | M73: =IF(L73="","",IF(L73>=85,"Excellent",IF(L73>=70,"Good",IF(L73>=55,"Mixed","Poor")))) | O73: https://www.imdb.com/find/?q=Cop+Out+2010 | P73: https://www.rottentomatoes.com/search?search=Cop+Out | Q73: https://letterboxd.com/search/Cop%20Out/ | R73: https://www.metacritic.com/search/Cop+Out/
A74: F0070 | B74: Shaun of the Dead | C74: 2004 | L74: =IF(COUNT(E74,G74,H74,I74,J74,K74)=0,"",ROUND((IF(E74="",0,E74*10)+IF(G74="",0,G74)+IF(H74="",0,H74)+IF(I74="",0,I74*20)+IF(J74="",0,J74)+IF(K74="",0,K74*10))/COUNT(E74,G74,H74,I74,J74,K74),1)) | M74: =IF(L74="","",IF(L74>=85,"Excellent",IF(L74>=70,"Good",IF(L74>=55,"Mixed","Poor")))) | O74: https://www.imdb.com/find/?q=Shaun+of+the+Dead+2004 | P74: https://www.rottentomatoes.com/search?search=Shaun+of+the+Dead | Q74: https://letterboxd.com/search/Shaun%20of%20the%20Dead/ | R74: https://www.metacritic.com/search/Shaun+of+the+Dead/
A75: F0071 | B75: Hot Fuzz | C75: 2007 | L75: =IF(COUNT(E75,G75,H75,I75,J75,K75)=0,"",ROUND((IF(E75="",0,E75*10)+IF(G75="",0,G75)+IF(H75="",0,H75)+IF(I75="",0,I75*20)+IF(J75="",0,J75)+IF(K75="",0,K75*10))/COUNT(E75,G75,H75,I75,J75,K75),1)) | M75: =IF(L75="","",IF(L75>=85,"Excellent",IF(L75>=70,"Good",IF(L75>=55,"Mixed","Poor")))) | O75: https://www.imdb.com/find/?q=Hot+Fuzz+2007 | P75: https://www.rottentomatoes.com/search?search=Hot+Fuzz | Q75: https://letterboxd.com/search/Hot%20Fuzz/ | R75: https://www.metacritic.com/search/Hot+Fuzz/
A76: F0072 | B76: The World's End | C76: 2013 | L76: =IF(COUNT(E76,G76,H76,I76,J76,K76)=0,"",ROUND((IF(E76="",0,E76*10)+IF(G76="",0,G76)+IF(H76="",0,H76)+IF(I76="",0,I76*20)+IF(J76="",0,J76)+IF(K76="",0,K76*10))/COUNT(E76,G76,H76,I76,J76,K76),1)) | M76: =IF(L76="","",IF(L76>=85,"Excellent",IF(L76>=70,"Good",IF(L76>=55,"Mixed","Poor")))) | O76: https://www.imdb.com/find/?q=The+World%27s+End+2013 | P76: https://www.rottentomatoes.com/search?search=The+World%27s+End | Q76: https://letterboxd.com/search/The%20World%27s%20End/ | R76: https://www.metacritic.com/search/The+World%27s+End/
A77: F0073 | B77: Cowboys & Aliens | C77: 2011 | L77: =IF(COUNT(E77,G77,H77,I77,J77,K77)=0,"",ROUND((IF(E77="",0,E77*10)+IF(G77="",0,G77)+IF(H77="",0,H77)+IF(I77="",0,I77*20)+IF(J77="",0,J77)+IF(K77="",0,K77*10))/COUNT(E77,G77,H77,I77,J77,K77),1)) | M77: =IF(L77="","",IF(L77>=85,"Excellent",IF(L77>=70,"Good",IF(L77>=55,"Mixed","Poor")))) | O77: https://www.imdb.com/find/?q=Cowboys+%26+Aliens+2011 | P77: https://www.rottentomatoes.com/search?search=Cowboys+%26+Aliens | Q77: https://letterboxd.com/search/Cowboys%20%26%20Aliens/ | R77: https://www.metacritic.com/search/Cowboys+%26+Aliens/
A78: F0074 | B78: Creed | C78: 2015 | L78: =IF(COUNT(E78,G78,H78,I78,J78,K78)=0,"",ROUND((IF(E78="",0,E78*10)+IF(G78="",0,G78)+IF(H78="",0,H78)+IF(I78="",0,I78*20)+IF(J78="",0,J78)+IF(K78="",0,K78*10))/COUNT(E78,G78,H78,I78,J78,K78),1)) | M78: =IF(L78="","",IF(L78>=85,"Excellent",IF(L78>=70,"Good",IF(L78>=55,"Mixed","Poor")))) | O78: https://www.imdb.com/find/?q=Creed+2015 | P78: https://www.rottentomatoes.com/search?search=Creed | Q78: https://letterboxd.com/search/Creed/ | R78: https://www.metacritic.com/search/Creed/
A79: F0075 | B79: The Croods | C79: 2013 | L79: =IF(COUNT(E79,G79,H79,I79,J79,K79)=0,"",ROUND((IF(E79="",0,E79*10)+IF(G79="",0,G79)+IF(H79="",0,H79)+IF(I79="",0,I79*20)+IF(J79="",0,J79)+IF(K79="",0,K79*10))/COUNT(E79,G79,H79,I79,J79,K79),1)) | M79: =IF(L79="","",IF(L79>=85,"Excellent",IF(L79>=70,"Good",IF(L79>=55,"Mixed","Poor")))) | O79: https://www.imdb.com/find/?q=The+Croods+2013 | P79: https://www.rottentomatoes.com/search?search=The+Croods | Q79: https://letterboxd.com/search/The%20Croods/ | R79: https://www.metacritic.com/search/The+Croods/
A80: F0076 | B80: Deadpool | C80: 2016 | D80: 5 | L80: =IF(COUNT(E80,G80,H80,I80,J80,K80)=0,"",ROUND((IF(E80="",0,E80*10)+IF(G80="",0,G80)+IF(H80="",0,H80)+IF(I80="",0,I80*20)+IF(J80="",0,J80)+IF(K80="",0,K80*10))/COUNT(E80,G80,H80,I80,J80,K80),1)) | M80: =IF(L80="","",IF(L80>=85,"Excellent",IF(L80>=70,"Good",IF(L80>=55,"Mixed","Poor")))) | O80: https://www.imdb.com/find/?q=Deadpool+2016 | P80: https://www.rottentomatoes.com/search?search=Deadpool | Q80: https://letterboxd.com/search/Deadpool/ | R80: https://www.metacritic.com/search/Deadpool/
A81: F0077 | B81: Deadpool 2 | C81: 2018 | D81: 5 | L81: =IF(COUNT(E81,G81,H81,I81,J81,K81)=0,"",ROUND((IF(E81="",0,E81*10)+IF(G81="",0,G81)+IF(H81="",0,H81)+IF(I81="",0,I81*20)+IF(J81="",0,J81)+IF(K81="",0,K81*10))/COUNT(E81,G81,H81,I81,J81,K81),1)) | M81: =IF(L81="","",IF(L81>=85,"Excellent",IF(L81>=70,"Good",IF(L81>=55,"Mixed","Poor")))) | O81: https://www.imdb.com/find/?q=Deadpool+2+2018 | P81: https://www.rottentomatoes.com/search?search=Deadpool+2 | Q81: https://letterboxd.com/search/Deadpool%202/ | R81: https://www.metacritic.com/search/Deadpool+2/
A82: F0078 | B82: Deadpool & Wolverine | C82: 2024 | D82: 5 | L82: =IF(COUNT(E82,G82,H82,I82,J82,K82)=0,"",ROUND((IF(E82="",0,E82*10)+IF(G82="",0,G82)+IF(H82="",0,H82)+IF(I82="",0,I82*20)+IF(J82="",0,J82)+IF(K82="",0,K82*10))/COUNT(E82,G82,H82,I82,J82,K82),1)) | M82: =IF(L82="","",IF(L82>=85,"Excellent",IF(L82>=70,"Good",IF(L82>=55,"Mixed","Poor")))) | O82: https://www.imdb.com/find/?q=Deadpool+%26+Wolverine+2024 | P82: https://www.rottentomatoes.com/search?search=Deadpool+%26+Wolverine | Q82: https://letterboxd.com/search/Deadpool%20%26%20Wolverine/ | R82: https://www.metacritic.com/search/Deadpool+%26+Wolverine/
A83: F0079 | B83: Dear John | C83: 2010 | L83: =IF(COUNT(E83,G83,H83,I83,J83,K83)=0,"",ROUND((IF(E83="",0,E83*10)+IF(G83="",0,G83)+IF(H83="",0,H83)+IF(I83="",0,I83*20)+IF(J83="",0,J83)+IF(K83="",0,K83*10))/COUNT(E83,G83,H83,I83,J83,K83),1)) | M83: =IF(L83="","",IF(L83>=85,"Excellent",IF(L83>=70,"Good",IF(L83>=55,"Mixed","Poor")))) | O83: https://www.imdb.com/find/?q=Dear+John+2010 | P83: https://www.rottentomatoes.com/search?search=Dear+John | Q83: https://letterboxd.com/search/Dear%20John/ | R83: https://www.metacritic.com/search/Dear+John/
A84: F0080 | B84: Delivery Man | C84: 2013 | L84: =IF(COUNT(E84,G84,H84,I84,J84,K84)=0,"",ROUND((IF(E84="",0,E84*10)+IF(G84="",0,G84)+IF(H84="",0,H84)+IF(I84="",0,I84*20)+IF(J84="",0,J84)+IF(K84="",0,K84*10))/COUNT(E84,G84,H84,I84,J84,K84),1)) | M84: =IF(L84="","",IF(L84>=85,"Excellent",IF(L84>=70,"Good",IF(L84>=55,"Mixed","Poor")))) | O84: https://www.imdb.com/find/?q=Delivery+Man+2013 | P84: https://www.rottentomatoes.com/search?search=Delivery+Man | Q84: https://letterboxd.com/search/Delivery%20Man/ | R84: https://www.metacritic.com/search/Delivery+Man/
A85: F0081 | B85: The Departed | C85: 2006 | L85: =IF(COUNT(E85,G85,H85,I85,J85,K85)=0,"",ROUND((IF(E85="",0,E85*10)+IF(G85="",0,G85)+IF(H85="",0,H85)+IF(I85="",0,I85*20)+IF(J85="",0,J85)+IF(K85="",0,K85*10))/COUNT(E85,G85,H85,I85,J85,K85),1)) | M85: =IF(L85="","",IF(L85>=85,"Excellent",IF(L85>=70,"Good",IF(L85>=55,"Mixed","Poor")))) | O85: https://www.imdb.com/find/?q=The+Departed+2006 | P85: https://www.rottentomatoes.com/search?search=The+Departed | Q85: https://letterboxd.com/search/The%20Departed/ | R85: https://www.metacritic.com/search/The+Departed/
A86: F0082 | B86: Despicable Me | C86: 2010 | L86: =IF(COUNT(E86,G86,H86,I86,J86,K86)=0,"",ROUND((IF(E86="",0,E86*10)+IF(G86="",0,G86)+IF(H86="",0,H86)+IF(I86="",0,I86*20)+IF(J86="",0,J86)+IF(K86="",0,K86*10))/COUNT(E86,G86,H86,I86,J86,K86),1)) | M86: =IF(L86="","",IF(L86>=85,"Excellent",IF(L86>=70,"Good",IF(L86>=55,"Mixed","Poor")))) | O86: https://www.imdb.com/find/?q=Despicable+Me+2010 | P86: https://www.rottentomatoes.com/search?search=Despicable+Me | Q86: https://letterboxd.com/search/Despicable%20Me/ | R86: https://www.metacritic.com/search/Despicable+Me/
A87: F0083 | B87: Despicable Me 2 | C87: 2013 | L87: =IF(COUNT(E87,G87,H87,I87,J87,K87)=0,"",ROUND((IF(E87="",0,E87*10)+IF(G87="",0,G87)+IF(H87="",0,H87)+IF(I87="",0,I87*20)+IF(J87="",0,J87)+IF(K87="",0,K87*10))/COUNT(E87,G87,H87,I87,J87,K87),1)) | M87: =IF(L87="","",IF(L87>=85,"Excellent",IF(L87>=70,"Good",IF(L87>=55,"Mixed","Poor")))) | O87: https://www.imdb.com/find/?q=Despicable+Me+2+2013 | P87: https://www.rottentomatoes.com/search?search=Despicable+Me+2 | Q87: https://letterboxd.com/search/Despicable%20Me%202/ | R87: https://www.metacritic.com/search/Despicable+Me+2/
A88: F0084 | B88: Despicable Me 3 | C88: 2017 | L88: =IF(COUNT(E88,G88,H88,I88,J88,K88)=0,"",ROUND((IF(E88="",0,E88*10)+IF(G88="",0,G88)+IF(H88="",0,H88)+IF(I88="",0,I88*20)+IF(J88="",0,J88)+IF(K88="",0,K88*10))/COUNT(E88,G88,H88,I88,J88,K88),1)) | M88: =IF(L88="","",IF(L88>=85,"Excellent",IF(L88>=70,"Good",IF(L88>=55,"Mixed","Poor")))) | O88: https://www.imdb.com/find/?q=Despicable+Me+3+2017 | P88: https://www.rottentomatoes.com/search?search=Despicable+Me+3 | Q88: https://letterboxd.com/search/Despicable%20Me%203/ | R88: https://www.metacritic.com/search/Despicable+Me+3/
A89: F0085 | B89: The Dictator | C89: 2012 | L89: =IF(COUNT(E89,G89,H89,I89,J89,K89)=0,"",ROUND((IF(E89="",0,E89*10)+IF(G89="",0,G89)+IF(H89="",0,H89)+IF(I89="",0,I89*20)+IF(J89="",0,J89)+IF(K89="",0,K89*10))/COUNT(E89,G89,H89,I89,J89,K89),1)) | M89: =IF(L89="","",IF(L89>=85,"Excellent",IF(L89>=70,"Good",IF(L89>=55,"Mixed","Poor")))) | O89: https://www.imdb.com/find/?q=The+Dictator+2012 | P89: https://www.rottentomatoes.com/search?search=The+Dictator | Q89: https://letterboxd.com/search/The%20Dictator/ | R89: https://www.metacritic.com/search/The+Dictator/
A90: F0086 | B90: Live Free or Die Hard | C90: 2007 | L90: =IF(COUNT(E90,G90,H90,I90,J90,K90)=0,"",ROUND((IF(E90="",0,E90*10)+IF(G90="",0,G90)+IF(H90="",0,H90)+IF(I90="",0,I90*20)+IF(J90="",0,J90)+IF(K90="",0,K90*10))/COUNT(E90,G90,H90,I90,J90,K90),1)) | M90: =IF(L90="","",IF(L90>=85,"Excellent",IF(L90>=70,"Good",IF(L90>=55,"Mixed","Poor")))) | O90: https://www.imdb.com/find/?q=Live+Free+or+Die+Hard+2007 | P90: https://www.rottentomatoes.com/search?search=Live+Free+or+Die+Hard | Q90: https://letterboxd.com/search/Live%20Free%20or%20Die%20Hard/ | R90: https://www.metacritic.com/search/Live+Free+or+Die+Hard/
A91: F0087 | B91: Dirty Grandpa | C91: 2016 | L91: =IF(COUNT(E91,G91,H91,I91,J91,K91)=0,"",ROUND((IF(E91="",0,E91*10)+IF(G91="",0,G91)+IF(H91="",0,H91)+IF(I91="",0,I91*20)+IF(J91="",0,J91)+IF(K91="",0,K91*10))/COUNT(E91,G91,H91,I91,J91,K91),1)) | M91: =IF(L91="","",IF(L91>=85,"Excellent",IF(L91>=70,"Good",IF(L91>=55,"Mixed","Poor")))) | O91: https://www.imdb.com/find/?q=Dirty+Grandpa+2016 | P91: https://www.rottentomatoes.com/search?search=Dirty+Grandpa | Q91: https://letterboxd.com/search/Dirty%20Grandpa/ | R91: https://www.metacritic.com/search/Dirty+Grandpa/
A92: F0088 | B92: District 9 | C92: 2009 | L92: =IF(COUNT(E92,G92,H92,I92,J92,K92)=0,"",ROUND((IF(E92="",0,E92*10)+IF(G92="",0,G92)+IF(H92="",0,H92)+IF(I92="",0,I92*20)+IF(J92="",0,J92)+IF(K92="",0,K92*10))/COUNT(E92,G92,H92,I92,J92,K92),1)) | M92: =IF(L92="","",IF(L92>=85,"Excellent",IF(L92>=70,"Good",IF(L92>=55,"Mixed","Poor")))) | O92: https://www.imdb.com/find/?q=District+9+2009 | P92: https://www.rottentomatoes.com/search?search=District+9 | Q92: https://letterboxd.com/search/District%209/ | R92: https://www.metacritic.com/search/District+9/
A93: F0089 | B93: Divergent | C93: 2014 | L93: =IF(COUNT(E93,G93,H93,I93,J93,K93)=0,"",ROUND((IF(E93="",0,E93*10)+IF(G93="",0,G93)+IF(H93="",0,H93)+IF(I93="",0,I93*20)+IF(J93="",0,J93)+IF(K93="",0,K93*10))/COUNT(E93,G93,H93,I93,J93,K93),1)) | M93: =IF(L93="","",IF(L93>=85,"Excellent",IF(L93>=70,"Good",IF(L93>=55,"Mixed","Poor")))) | O93: https://www.imdb.com/find/?q=Divergent+2014 | P93: https://www.rottentomatoes.com/search?search=Divergent | Q93: https://letterboxd.com/search/Divergent/ | R93: https://www.metacritic.com/search/Divergent/
A94: F0090 | B94: Django Unchained | C94: 2012 | L94: =IF(COUNT(E94,G94,H94,I94,J94,K94)=0,"",ROUND((IF(E94="",0,E94*10)+IF(G94="",0,G94)+IF(H94="",0,H94)+IF(I94="",0,I94*20)+IF(J94="",0,J94)+IF(K94="",0,K94*10))/COUNT(E94,G94,H94,I94,J94,K94),1)) | M94: =IF(L94="","",IF(L94>=85,"Excellent",IF(L94>=70,"Good",IF(L94>=55,"Mixed","Poor")))) | O94: https://www.imdb.com/find/?q=Django+Unchained+2012 | P94: https://www.rottentomatoes.com/search?search=Django+Unchained | Q94: https://letterboxd.com/search/Django%20Unchained/ | R94: https://www.metacritic.com/search/Django+Unchained/
A95: F0091 | B95: Due Date | C95: 2010 | D95: 4 | L95: =IF(COUNT(E95,G95,H95,I95,J95,K95)=0,"",ROUND((IF(E95="",0,E95*10)+IF(G95="",0,G95)+IF(H95="",0,H95)+IF(I95="",0,I95*20)+IF(J95="",0,J95)+IF(K95="",0,K95*10))/COUNT(E95,G95,H95,I95,J95,K95),1)) | M95: =IF(L95="","",IF(L95>=85,"Excellent",IF(L95>=70,"Good",IF(L95>=55,"Mixed","Poor")))) | O95: https://www.imdb.com/find/?q=Due+Date+2010 | P95: https://www.rottentomatoes.com/search?search=Due+Date | Q95: https://letterboxd.com/search/Due%20Date/ | R95: https://www.metacritic.com/search/Due+Date/
A96: F0092 | B96: Elf | C96: 2003 | L96: =IF(COUNT(E96,G96,H96,I96,J96,K96)=0,"",ROUND((IF(E96="",0,E96*10)+IF(G96="",0,G96)+IF(H96="",0,H96)+IF(I96="",0,I96*20)+IF(J96="",0,J96)+IF(K96="",0,K96*10))/COUNT(E96,G96,H96,I96,J96,K96),1)) | M96: =IF(L96="","",IF(L96>=85,"Excellent",IF(L96>=70,"Good",IF(L96>=55,"Mixed","Poor")))) | O96: https://www.imdb.com/find/?q=Elf+2003 | P96: https://www.rottentomatoes.com/search?search=Elf | Q96: https://letterboxd.com/search/Elf/ | R96: https://www.metacritic.com/search/Elf/
